Workbook

Sheet DIAGNOSTICO
A1: DIAGNÓSTICO — NÃO É O MASTER | B1: Anterior / Old | C1: Escalar / Scalar | D1: Igual / Equal | E1: Procedimento
A3: Valores guardados não validam o cálculo no Excel. | E3: 1. Ative edição. 2. Ctrl+Alt+F9. 3. Guarde, feche e reabra. 4. Registe que células falham.
A5: Peso total construção | B5: =SUM('V06 Motor'!G5:G184) -> 1 | C5: =SUM('V06 Motor'!H5:H184) -> 1 | D5: =ABS(B5-C5)<0.00001 -> TRUE | E5: As fórmulas antigas são cópias exatas do V06 anterior. As novas usam a mesma curva e as mesmas 94 frações, sem IF matricial/SUMPRODUCT.
A6: Recebimentos totais | B6: =SUM('V06 Motor'!O5:O184) -> 50656336 | C6: =SUM('V06 Motor'!P5:P184) -> 50656336 | D6: =ABS(B6-C6)<0.00001 -> TRUE
E7: Microsoft Excel 365: NOT TESTED neste ambiente. Este ficheiro permite isolar os dois blocos, sem carregar o master completo.
A9: Peso construção M1 | B9: ='V06 Motor'!G5 -> 0.01 | C9: ='V06 Motor'!H5 -> 0.01 | D9: =ABS(B9-C9)<0.00001 -> TRUE
A10: Recebimentos M1 | B10: ='V06 Motor'!O5 -> 2032938.9 | C10: ='V06 Motor'!P5 -> 2032938.9 | D10: =ABS(B10-C10)<0.00001 -> TRUE
A12: Não há IFERROR a ocultar erros neste diagnóstico. | E12: O diagnóstico não prova que o problema original tem esta causa; compara os blocos suspeitos em Excel nativo.

Sheet V06 Controlos
A5: Idioma | B5: PT
A6: IVA de estudo | B6: 0.15
A7: Fração recuperável IVA | B7: 1
A8: Prazo reembolso IVA | B8: 6
A9: Taxa IRPC | B9: 0.2
A10: Anos isenção simulada | B10: 0
A11: Prazo pagamento IRPC | B11: 3
A12: Base depreciável | B12: 40100000
A13: Vida útil fiscal | B13: 30
A14: Base IPI Hotel/MICE | B14: 40100000
A15: Taxa IPI | B15: 0
A16: ITI referência | B16: 0.015
A17: Fração ITI suportada KK | B17: 0
... A53: Reserva contingência jurídica HOTUSA | B53: 1000000
A54: Estado HOTUSA | B54: Pending
A55: Obrigação HOTUSA confirmada | B55: 0
A56: Mês resolução HOTUSA | B56: 180
A57: Política dividendos | B57: Auto
A58: Cobertura 12M | B58: 1.2
A59: Lucros documentados ou proxy | B59: Proxy
A60: Limite dividendos documentado | B60: 0
A61: Fração distribuição parcial | B61: 0.5
A62: Múltiplo saída | B62: 12
A63: Custo saída | B63: 0.02
A64: Mês saída | B64: 180
A65: Desconto equity | B65: 0.12
A66: Desconto projeto | B66: 0.1
A67: Cenário Hotel | B67: Favorável
A68: Fee base operador | B68: 0.03
A69: Sistemas e distribuição | B69: 0.03
A70: Fee incentivo | B70: 0.06
A71: Outros fees receita | B71: 0
A72: Yield residencial inicial | B72: 0.0425
A73: Incremento anual yield | B73: 0.0025
A74: Estado Convenção | B74: Em preparação
A75: ETC adicional | B75: 0
A76: Mês controlo obra | B76: 0
A77: Direitos aduaneiros KK | B77: 0
A78: Imposto selo KK | B78: 0
A79: Outras taxas institucionais | B79: 0
A80: Taxa informativa proprietários | B80: 0
A81: Último mês utilização banco | B81: 30

Sheet V06 Curva
A5: 1 | B5: 0.01
A6: 2 | B6: 0.0124
A7: 3 | B7: 0.0184
A8: 4 | B8: 0.02345
A9: 5 | B9: 0.0265
A10: 6 | B10: 0.0225
A11: 7 | B11: 0.0141
A12: 8 | B12: 0.0141
A13: 9 | B13: 0.0147
A14: 10 | B14: 0.0134
A15: 11 | B15: 0.0188
A16: 12 | B16: 0.0256
... A34: 30 | B34: 0.001

Sheet V06 Unidades
A5: 201 | H5: 552000 | I5: 1 | L5: 28
A6: 202 | H6: 402500 | I6: 1 | L6: 29
A7: 203 | H7: 253000 | I7: 1 | L7: 30
A8: 204 | H8: 253000 | I8: 1 | L8: 28
A9: 205 | H9: 402500 | I9: 1 | L9: 29
A10: 206 | H10: 408250 | I10: 1 | L10: 30
A11: 207 | H11: 253000 | I11: 1 | L11: 28
A12: 208 | H12: 253000 | I12: 1 | L12: 29
A13: 209 | H13: 402500 | I13: 4 | L13: 30
A14: 210 | H14: 552000 | I14: 4 | L14: 28
A15: 301 | H15: 563040 | I15: 4 | L15: 29
A16: 302 | H16: 410550 | I16: 4 | L16: 30
... A98: 1104 | H98: 1530100 | I98: 22 | L98: 30

Sheet V06 Calend 01
A4: Unit | B4: Price EUR | C4: Sale month | D4: Deed month | E4: Progress instalments | F4: Deposit 5% | G4: Contract 20% | H4: Progress 55% | I4: Instalment EUR | J4: Final EUR | K4: Selling costs | L4: Forecast only | M4: M001 | N4: M002 | O4: M003 | P4: M004 | Q4: M005 | R4: M006 | S4: M007 | T4: M008 | U4: M009 | V4: M010 | W4: M011 | X4: M012 | Y4: M013 | Z4: M014 | AA4: M015 | AB4: M016 | AC4: M017 | AD4: M018 | AE4: M019 | AF4: M020 | AG4: M021 | AH4: M022 | AI4: M023 | AJ4: M024 | AK4: M025 | AL4: M026 | AM4: M027 | AN4: M028 | AO4: M029 | AP4: M030 | AQ4: M031 | AR4: M032 | AS4: M033 | AT4: M034 | AU4: M035 | AV4: M036 | AW4: M037 | AX4: M038 | AY4: M039 | AZ4: M040 | BA4: M041 | BB4: M042 | BC4: M043 | BD4: M044 | BE4: M045 | BF4: M046 | BG4: M047 | BH4: M048 | BI4: M049 | BJ4: M050 | BK4: M051 | BL4: M052 | BM4: M053 | BN4: M054 | BO4: M055 | BP4: M056 | BQ4: M057 | BR4: M058 | BS4: M059 | BT4: M060 | BU4: M061 | BV4: M062 | BW4: M063 | BX4: M064 | BY4: M065 | BZ4: M066 | CA4: M067 | CB4: M068 | CC4: M069 | CD4: M070 | CE4: M071 | CF4: M072 | CG4: M073 | CH4: M074 | CI4: M075 | CJ4: M076 | CK4: M077 | CL4: M078 | CM4: M079 | CN4: M080 | CO4: M081 | CP4: M082 | CQ4: M083 | CR4: M084 | CS4: M085 | CT4: M086 | CU4: M087 | CV4: M088 | CW4: M089 | CX4: M090 | CY4: M091 | CZ4: M092 | DA4: M093 | DB4: M094 | DC4: M095 | DD4: M096 | DE4: M097 | DF4: M098 | DG4: M099 | DH4: M100 | DI4: M101 | DJ4: M102 | DK4: M103 | DL4: M104 | DM4: M105 | DN4: M106 | DO4: M107 | DP4: M108 | DQ4: M109 | DR4: M110 | DS4: M111 | DT4: M112 | DU4: M113 | DV4: M114 | DW4: M115 | DX4: M116 | DY4: M117 | DZ4: M118 | EA4: M119 | EB4: M120 | EC4: M121 | ED4: M122 | EE4: M123 | EF4: M124 | EG4: M125 | EH4: M126 | EI4: M127 | EJ4: M128 | EK4: M129 | EL4: M130 | EM4: M131 | EN4: M132 | EO4: M133 | EP4: M134 | EQ4: M135 | ER4: M136 | ES4: M137 | ET4: M138 | EU4: M139 | EV4: M140 | EW4: M141 | EX4: M142 | EY4: M143 | EZ4: M144 | FA4: M145 | FB4: M146 | FC4: M147 | FD4: M148 | FE4: M149 | FF4: M150 | FG4: M151 | FH4: M152 | FI4: M153 | FJ4: M154 | FK4: M155 | FL4: M156 | FM4: M157 | FN4: M158 | FO4: M159 | FP4: M160 | FQ4: M161 | FR4: M162 | FS4: M163 | FT4: M164 | FU4: M165 | FV4: M166 | FW4: M167 | FX4: M168 | FY4: M169 | FZ4: M170 | GA4: M171 | GB4: M172 | GC4: M173 | GD4: M174 | GE4: M175 | GF4: M176 | GG4: M177 | GH4: M178 | GI4: M179 | GJ4: M180
A5: ='V06 Unidades'!$A$5 -> 201 | B5: ='V06 Unidades'!$H$5 -> 552000 | C5: =('V06 Unidades'!$I$5+'V06 Controlos'!$B$37) -> 1 | D5: =IF(('V06 Controlos'!$B$38>0),MAX(('V06 Unidades'!$L$5+'V06 Controlos'!$B$37),(30+'V06 Controlos'!$B$38)),('V06 Unidades'!$L$5+'V06 Controlos'!$B$37)) -> 28 | E5: =MAX(0,INT(((('V06 Calend 01'!D5-'V06 Calend 01'!C5)-1)/6))) -> 4 | F5: =ROUND(('V06 Calend 01'!B5*0.05),2) -> 27600 | G5: =ROUND(('V06 Calend 01'!B5*0.2),2) -> 110400 | H5: =ROUND(('V06 Calend 01'!B5*0.55),2) -> 303600 | I5: =ROUND(('V06 Calend 01'!H5/MAX(1,'V06 Calend 01'!E5)),2) -> 75900 | J5: =((('V06 Calend 01'!B5-'V06 Calend 01'!F5)-'V06 Calend 01'!G5)-'V06 Calend 01'!H5) -> 110400 | K5: =('V06 Calend 01'!B5*0.025) -> 13800 | L5: Forecast; actual receipts are separate | M5: =((IF((1='V06 Calend 01'!C5),('V06 Calend 01'!F5+'V06 Calend 01'!G5),0)+IF(AND(('V06 Calend 01'!E5>0),(1>'V06 Calend 01'!C5),(1<'V06 Calend 01'!D5),(MOD((1-'V06 Calend 01'!C5),6)=0),(((1-'V06 Calend 01'!C5)/6)<='V06 Calend 01'!E5)),IF((1=('V06 Calend 01'!C5+(6*'V06 Calend 01'!E5))),('V06 Calend 01'!H5-('V06 Calend 01'!I5*('V06 Calend 01'!E5-1))),'V06 Calend 01'!I5),0))+IF((1='V06 Calend 01'!D5),'V06 Calend 01'!J5,0)) -> 138000 | N5: =((IF((2='V06 Calend 01'!C5),('V06 Calend 01'!F5+'V06 Calend 01'!G5),0)+IF(AND(('V06 Calend 01'!E5>0),(2>'V06 Calend 01'!C5),(2<'V06 Calend 01'!D5),(MOD((2-'V06 Calend 01'!C5),6)=0),(((2-'V06 Calend 01'!C5)/6)<='V06 Calend 01'!E5)),IF((2=('V06 Calend 01'!C5+(6*'V06 Calend 01'!E5))),('V06 Calend 01'!H5-('V06 Calend 01'!I5*('V06 Calend 01'!E5-1))),'V06 Calend 01'!I5),0))+IF((2='V06 Calend 01'!D5),'V06 Calend 01'!J5,0)) -> 0 | O5: =((IF((3='V06 Calend 01'!C5),('V06 Calend 01'!F5+'V06 Calend 01'!G5),0)+IF(AND(('V06 Calend 01'!E5>0),(3>'V06 Calend 01'!C5),(3<'V06 Calend 01'!D5),(MOD((3-'V06 Calend 01'!C5),6)=0),(((3-'V06 Calend 01'!C5)/6)<='V06 Calend 01'!E5)),IF((3=('V06 Calend 01'!C5+(6*'V06 Calend 01'!E5))),('V06 Calend 01'!H5-('V06 Calend 01'!I5*('V06 Calend 01'!E5-1))),'V06 Calend 01'!I5),0))+IF((3='V06 Calend 01'!D5),'V06 Calend 01'!J5,0)) -> 0 | P5: =((IF((4='V06 Calend 01'!C5),('V06 Calend 01'!F5+'V06 Calend 01'!G5),0)+IF(AND(('V06 Calend 01'!E5>0),(4>'V06 Calend 01'!C5),(4<'V06 Calend 01'!D5),(MOD((4-'V06 Calend 01'!C5),6)=0),(((4-'V06 Calend 01'!C5)/6)<='V06 Calend 01'!E5)),IF((4=('V06 Calend 01'!C5+(6*'V06 Calend 01'!E5))),('V06 Calend 01'!H5-('V06 Calend 01'!I5*('V06 Calend 01'!E5-1))),'V06 Calend 01'!I5),0))+IF((4='V06 Calend 01'!D5),'V06 Calend 01'!J5,0)) -> 0 | Q5: =((IF((5='V06 Calend 01'!C5),('V06 Calend 01'!F5+'V06 Calend 01'!G5),0)+IF(AND(('V06 Calend 01'!E5>0),(5>'V06 Calend 01'!C5),(5<'V06 Calend 01'!D5),(MOD((5-'V06 Calend 01'!C5),6)=0),(((5-'V06 Calend 01'!C5)/6)<='V06 Calend 01'!E5)),IF((5=('V06 Calend 01'!C5+(6*'V06 Calend 01'!E5))),('V06 Calend 01'!H5-('V06 Calend 01'!I5*('V06 Calend 01'!E5-1))),'V06 Calend 01'!I5),0))+IF((5='V06 Calend 01'!D5),'V06 Calend 01'!J5,0)) -> 0 | R5: =((IF((6='V06 Calend 01'!C5),('V06 Calend 01'!F5+'V06 Calend 01'!G5),0)+IF(AND(('V06 Calend 01'!E5>0),(6>'V06 Calend 01'!C5),(6<'V06 Calend 01'!D5),(MOD((6-'V06 Calend 01'!C5),6)=0),(((6-'V06 Calend 01'!C5)/6)<='V06 Calend 01'!E5)),IF((6=('V06 Calend 01'!C5+(6*'V06 Calend 01'!E5))),('V06 Calend 01'!H5-('V06 Calend 01'!I5*('V06 Calend 01'!E5-1))),'V06 Calend 01'!I5),0))+IF((6='V06 Calend 01'!D5),'V06 Calend 01'!J5,0)) -> 0 | S5: =((IF((7='V06 Calend 01'!C5),('V06 Calend 01'!F5+'V06 Calend 01'!G5),0)+IF(AND(('V06 Calend 01'!E5>0),(7>'V06 Calend 01'!C5),(7<'V06 Calend 01'!D5),(MOD((7-'V06 Calend 01'!C5),6)=0),(((7-'V06 Calend 01'!C5)/6)<='V06 Calend 01'!E5)),IF((7=('V06 Calend 01'!C5+(6*'V06 Calend 01'!E5))),('V06 Calend 01'!H5-('V06 Calend 01'!I5*('V06 Calend 01'!E5-1))),'V06 Calend 01'!I5),0))+IF((7='V06 Calend 01'!D5),'V06 Calend 01'!J5,0)) -> 75900 | T5: =((IF((8='V06 Calend 01'!C5),('V06 Calend 01'!F5+'V06 Calend 01'!G5),0)+IF(AND(('V06 Calend 01'!E5>0),(8>'V06 Calend 01'!C5),(8<'V06 Calend 01'!D5),(MOD((8-'V06 Calend 01'!C5),6)=0),(((8-'V06 Calend 01'!C5)/6)<='V06 Calend 01'!E5)),IF((8=('V06 Calend 01'!C5+(6*'V06 Calend 01'!E5))),('V06 Calend 01'!H5-('V06 Calend 01'!I5*('V06 Calend 01'!E5-1))),'V06 Calend 01'!I5),0))+IF((8='V06 Calend 01'!D5),'V06 Calend 01'!J5,0)) -> 0 | U5: =((IF((9='V06 Calend 01'!C5),('V06 Calend 01'!F5+'V06 Calend 01'!G5),0)+IF(AND(('V06 Calend 01'!E5>0),(9>'V06 Calend 01'!C5),(9<'V06 Calend 01'!D5),(MOD((9-'V06 Calend 01'!C5),6)=0),(((9-'V06 Calend 01'!C5)/6)<='V06 Calend 01'!E5)),IF((9=('V06 Calend 01'!C5+(6*'V06 Calend 01'!E5))),('V06 Calend 01'!H5-('V06 Calend 01'!I5*('V06 Calend 01'!E5-1))),'V06 Calend 01'!I5),0))+IF((9='V06 Calend 01'!D5),'V06 Calend 01'!J5,0)) -> 0 | V5: =((IF((10='V06 Calend 01'!C5),('V06 Calend 01'!F5+'V06 Calend 01'!G5),0)+IF(AND(('V06 Calend 01'!E5>0),(10>'V06 Calend 01'!C5),(10<'V06 Calend 01'!D5),(MOD((10-'V06 Calend 01'!C5),6)=0),(((10-'V06 Calend 01'!C5)/6)<='V06 Calend 01'!E5)),IF((10=('V06 Calend 01'!C5+(6*'V06 Calend 01'!E5))),('V06 Calend 01'!H5-('V06 Calend 01'!I5*('V06 Calend 01'!E5-1))),'V06 Calend 01'!I5),0))+IF((10='V06 Calend 01'!D5),'V06 Calend 01'!J5,0)) -> 0 | W5: =((IF((11='V06 Calend 01'!C5),('V06 Calend 01'!F5+'V06 Calend 01'!G5),0)+IF(AND(('V06 Calend 01'!E5>0),(11>'V06 Calend 01'!C5),(11<'V06 Calend 01'!D5),(MOD((11-'V06 Calend 01'!C5),6)=0),(((11-'V06 Calend 01'!C5)/6)<='V06 Calend 01'!E5)),IF((11=('V06 Calend 01'!C5+(6*'V06 Calend 01'!E5))),('V06 Calend 01'!H5-('V06 Calend 01'!I5*('V06 Calend 01'!E5-1))),'V06 Calend 01'!I5),0))+IF((11='V06 Calend 01'!D5),'V06 Calend 01'!J5,0)) -> 0 | X5: =((IF((12='V06 Calend 01'!C5),('V06 Calend 01'!F5+'V06 Calend 01'!G5),0)+IF(AND(('V06 Calend 01'!E5>0),(12>'V06 Calend 01'!C5),(12<'V06 Calend 01'!D5),(MOD((12-'V06 Calend 01'!C5),6)=0),(((12-'V06 Calend 01'!C5)/6)<='V06 Calend 01'!E5)),IF((12=('V06 Calend 01'!C5+(6*'V06 Calend 01'!E5))),('V06 Calend 01'!H5-('V06 Calend 01'!I5*('V06 Calend 01'!E5-1))),'V06 Calend 01'!I5),0))+IF((12='V06 Calend 01'!D5),'V06 Calend 01'!J5,0)) -> 0 | Y5: =((IF((13='V06 Calend 01'!C5),('V06 Calend 01'!F5+'V06 Calend 01'!G5),0)+IF(AND(('V06 Calend 01'!E5>0),(13>'V06 Calend 01'!C5),(13<'V06 Calend 01'!D5),(MOD((13-'V06 Calend 01'!C5),6)=0),(((13-'V06 Calend 01'!C5)/6)<='V06 Calend 01'!E5)),IF((13=('V06 Calend 01'!C5+(6*'V06 Calend 01'!E5))),('V06 Calend 01'!H5-('V06 Calend 01'!I5*('V06 Calend 01'!E5-1))),'V06 Calend 01'!I5),0))+IF((13='V06 Calend 01'!D5),'V06 Calend 01'!J5,0)) -> 75900 | Z5: =((IF((14='V06 Calend 01'!C5),('V06 Calend 01'!F5+'V06 Calend 01'!G5),0)+IF(AND(('V06 Calend 01'!E5>0),(14>'V06 Calend 01'!C5),(14<'V06 Calend 01'!D5),(MOD((14-'V06 Calend 01'!C5),6)=0),(((14-'V06 Calend 01'!C5)/6)<='V06 Calend 01'!E5)),IF((14=('V06 Calend 01'!C5+(6*'V06 Calend 01'!E5))),('V06 Calend 01'!H5-('V06 Calend 01'!I5*('V06 Calend 01'!E5-1))),'V06 Calend 01'!I5),0))+IF((14='V06 Calend 01'!D5),'V06 Calend 01'!J5,0)) -> 0 | AA5: =((IF((15='V06 Calend 01'!C5),('V06 Calend 01'!F5+'V06 Calend 01'!G5),0)+IF(AND(('V06 Calend 01'!E5>0),(15>'V06 Calend 01'!C5),(15<'V06 Calend 01'!D5),(MOD((15-'V06 Calend 01'!C5),6)=0),(((15-'V06 Calend 01'!C5)/6)<='V06 Calend 01'!E5)),IF((15=('V06 Calend 01'!C5+(6*'V06 Calend 01'!E5))),('V06 Calend 01'!H5-('V06 Calend 01'!I5*('V06 Calend 01'!E5-1))),'V06 Calend 01'!I5),0))+IF((15='V06 Calend 01'!D5),'V06 Calend 01'!J5,0)) -> 0 | AB5: =((IF((16='V06 Calend 01'!C5),('V06 Calend 01'!F5+'V06 Calend 01'!G5),0)+IF(AND(('V06 Calend 01'!E5>0),(16>'V06 Calend 01'!C5),(16<'V06 Calend 01'!D5),(MOD((16-'V06 Calend 01'!C5),6)=0),(((16-'V06 Calend 01'!C5)/6)<='V06 Calend 01'!E5)),IF((16=('V06 Calend 01'!C5+(6*'V06 Calend 01'!E5))),('V06 Calend 01'!H5-('V06 Calend 01'!I5*('V06 Calend 01'!E5-1))),'V06 Calend 01'!I5),0))+IF((16='V06 Calend 01'!D5),'V06 Calend 01'!J5,0)) -> 0 | AC5: =((IF((17='V06 Calend 01'!C5),('V06 Calend 01'!F5+'V06 Calend 01'!G5),0)+IF(AND(('V06 Calend 01'!E5>0),(17>'V06 Calend 01'!C5),(17<'V06 Calend 01'!D5),(MOD((17-'V06 Calend 01'!C5),6)=0),(((17-'V06 Calend 01'!C5)/6)<='V06 Calend 01'!E5)),IF((17=('V06 Calend 01'!C5+(6*'V06 Calend 01'!E5))),('V06 Calend 01'!H5-('V06 Calend 01'!I5*('V06 Calend 01'!E5-1))),'V06 Calend 01'!I5),0))+IF((17='V06 Calend 01'!D5),'V06 Calend 01'!J5,0)) -> 0 | AD5: =((IF((18='V06 Calend 01'!C5),('V06 Calend 01'!F5+'V06 Calend 01'!G5),0)+IF(AND(('V06 Calend 01'!E5>0),(18>'V06 Calend 01'!C5),(18<'V06 Calend 01'!D5),(MOD((18-'V06 Calend 01'!C5),6)=0),(((18-'V06 Calend 01'!C5)/6)<='V06 Calend 01'!E5)),IF((18=('V06 Calend 01'!C5+(6*'V06 Calend 01'!E5))),('V06 Calend 01'!H5-('V06 Calend 01'!I5*('V06 Calend 01'!E5-1))),'V06 Calend 01'!I5),0))+IF((18='V06 Calend 01'!D5),'V06 Calend 01'!J5,0)) -> 0 | AE5: =((IF((19='V06 Calend 01'!C5),('V06 Calend 01'!F5+'V06 Calend 01'!G5),0)+IF(AND(('V06 Calend 01'!E5>0),(19>'V06 Calend 01'!C5),(19<'V06 Calend 01'!D5),(MOD((19-'V06 Calend 01'!C5),6)=0),(((19-'V06 Calend 01'!C5)/6)<='V06 Calend 01'!E5)),IF((19=('V06 Calend 01'!C5+(6*'V06 Calend 01'!E5))),('V06 Calend 01'!H5-('V06 Calend 01'!I5*('V06 Calend 01'!E5-1))),'V06 Calend 01'!I5),0))+IF((19='V06 Calend 01'!D5),'V06 Calend 01'!J5,0)) -> 75900 | AF5: =((IF((20='V06 Calend 01'!C5),('V06 Calend 01'!F5+'V06 Calend 01'!G5),0)+IF(AND(('V06 Calend 01'!E5>0),(20>'V06 Calend 01'!C5),(20<'V06 Calend 01'!D5),(MOD((20-'V06 Calend 01'!C5),6)=0),(((20-'V06 Calend 01'!C5)/6)<='V06 Calend 01'!E5)),IF((20=('V06 Calend 01'!C5+(6*'V06 Calend 01'!E5))),('V06 Calend 01'!H5-('V06 Calend 01'!I5*('V06 Calend 01'!E5-1))),'V06 Calend 01'!I5),0))+IF((20='V06 Calend 01'!D5),'V06 Calend 01'!J5,0)) -> 0 | AG5: =((IF((21='V06 Calend 01'!C5),('V06 Calend 01'!F5+'V06 Calend 01'!G5),0)+IF(AND(('V06 Calend 01'!E5>0),(21>'V06 Calend 01'!C5),(21<'V06 Calend 01'!D5),(MOD((21-'V06 Calend 01'!C5),6)=0),(((21-'V06 Calend 01'!C5)/6)<='V06 Calend 01'!E5)),IF((21=('V06 Calend 01'!C5+(6*'V06 Calend 01'!E5))),('V06 Calend 01'!H5-('V06 Calend 01'!I5*('V06 Calend 01'!E5-1))),'V06 Calend 01'!I5),0))+IF((21='V06 Calend 01'!D5),'V06 Calend 01'!J5,0)) -> 0 | AH5: =((IF((22='V06 Calend 01'!C5),('V06 Calend 01'!F5+'V06 Calend 01'!G5),0)+IF(AND(('V06 Calend 01'!E5>0),(22>'V06 Calend 01'!C5),(22<'V06 Calend 01'!D5),(MOD((22-'V06 Calend 01'!C5),6)=0),(((22-'V06 Calend 01'!C5)/6)<='V06 Calend 01'!E5)),IF((22=('V06 Calend 01'!C5+(6*'V06 Calend 01'!E5))),('V06 Calend 01'!H5-('V06 Calend 01'!I5*('V06 Calend 01'!E5-1))),'V06 Calend 01'!I5),0))+IF((22='V06 Calend 01'!D5),'V06 Calend 01'!J5,0)) -> 0 | AI5: =((IF((23='V06 Calend 01'!C5),('V06 Calend 01'!F5+'V06 Calend 01'!G5),0)+IF(AND(('V06 Calend 01'!E5>0),(23>'V06 Calend 01'!C5),(23<'V06 Calend 01'!D5),(MOD((23-'V06 Calend 01'!C5),6)=0),(((23-'V06 Calend 01'!C5)/6)<='V06 Calend 01'!E5)),IF((23=('V06 Calend 01'!C5+(6*'V06 Calend 01'!E5))),('V06 Calend 01'!H5-('V06 Calend 01'!I5*('V06 Calend 01'!E5-1))),'V06 Calend 01'!I5),0))+IF((23='V06 Calend 01'!D5),'V06 Calend 01'!J5,0)) -> 0 | AJ5: =((IF((24='V06 Calend 01'!C5),('V06 Calend 01'!F5+'V06 Calend 01'!G5),0)+IF(AND(('V06 Calend 01'!E5>0),(24>'V06 Calend 01'!C5),(24<'V06 Calend 01'!D5),(MOD((24-'V06 Calend 01'!C5),6)=0),(((24-'V06 Calend 01'!C5)/6)<='V06 Calend 01'!E5)),IF((24=('V06 Calend 01'!C5+(6*'V06 Calend 01'!E5))),('V06 Calend 01'!H5-('V06 Calend 01'!I5*('V06 Calend 01'!E5-1))),'V06 Calend 01'!I5),0))+IF((24='V06 Calend 01'!D5),'V06 Calend 01'!J5,0)) -> 0 | AK5: =((IF((25='V06 Calend 01'!C5),('V06 Calend 01'!F5+'V06 Calend 01'!G5),0)+IF(AND(('V06 Calend 01'!E5>0),(25>'V06 Calend 01'!C5),(25<'V06 Calend 01'!D5),(MOD((25-'V06 Calend 01'!C5),6)=0),(((25-'V06 Calend 01'!C5)/6)<='V06 Calend 01'!E5)),IF((25=('V06 Calend 01'!C5+(6*'V06 Calend 01'!E5))),('V06 Calend 01'!H5-('V06 Calend 01'!I5*('V06 Calend 01'!E5-1))),'V06 Calend 01'!I5),0))+IF((25='V06 Calend 01'!D5),'V06 Calend 01'!J5,0)) -> 75900 | AL5: =((IF((26='V06 Calend 01'!C5),('V06 Calend 01'!F5+'V06 Calend 01'!G5),0)+IF(AND(('V06 Calend 01'!E5>0),(26>'V06 Calend 01'!C5),(26<'V06 Calend 01'!D5),(MOD((26-'V06 Calend 01'!C5),6)=0),(((26-'V06 Calend 01'!C5)/6)<='V06 Calend 01'!E5)),IF((26=('V06 Calend 01'!C5+(6*'V06 Calend 01'!E5))),('V06 Calend 01'!H5-('V06 Calend 01'!I5*('V06 Calend 01'!E5-1))),'V06 Calend 01'!I5),0))+IF((26='V06 Calend 01'!D5),'V06 Calend 01'!J5,0)) -> 0 | AM5: =((IF((27='V06 Calend 01'!C5),('V06 Calend 01'!F5+'V06 Calend 01'!G5),0)+IF(AND(('V06 Calend 01'!E5>0),(27>'V06 Calend 01'!C5),(27<'V06 Calend 01'!D5),(MOD((27-'V06 Calend 01'!C5),6)=0),(((27-'V06 Calend 01'!C5)/6)<='V06 Calend 01'!E5)),IF((27=('V06 Calend 01'!C5+(6*'V06 Calend 01'!E5))),('V06 Calend 01'!H5-('V06 Calend 01'!I5*('V06 Calend 01'!E5-1))),'V06 Calend 01'!I5),0))+IF((27='V06 Calend 01'!D5),'V06 Calend 01'!J5,0)) -> 0 | AN5: =((IF((28='V06 Calend 01'!C5),('V06 Calend 01'!F5+'V06 Calend 01'!G5),0)+IF(AND(('V06 Calend 01'!E5>0),(28>'V06 Calend 01'!C5),(28<'V06 Calend 01'!D5),(MOD((28-'V06 Calend 01'!C5),6)=0),(((28-'V06 Calend 01'!C5)/6)<='V06 Calend 01'!E5)),IF((28=('V06 Calend 01'!C5+(6*'V06 Calend 01'!E5))),('V06 Calend 01'!H5-('V06 Calend 01'!I5*('V06 Calend 01'!E5-1))),'V06 Calend 01'!I5),0))+IF((28='V06 Calend 01'!D5),'V06 Calend 01'!J5,0)) -> 110400 | AO5: =((IF((29='V06 Calend 01'!C5),('V06 Calend 01'!F5+'V06 Calend 01'!G5),0)+IF(AND(('V06 Calend 01'!E5>0),(29>'V06 Calend 01'!C5),(29<'V06 Calend 01'!D5),(MOD((29-'V06 Calend 01'!C5),6)=0),(((29-'V06 Calend 01'!C5)/6)<='V06 Calend 01'!E5)),IF((29=('V06 Calend 01'!C5+(6*'V06 Calend 01'!E5))),('V06 Calend 01'!H5-('V06 Calend 01'!I5*('V06 Calend 01'!E5-1))),'V06 Calend 01'!I5),0))+IF((29='V06 Calend 01'!D5),'V06 Calend 01'!J5,0)) -> 0 | AP5: =((IF((30='V06 Calend 01'!C5),('V06 Calend 01'!F5+'V06 Calend 01'!G5),0)+IF(AND(('V06 Calend 01'!E5>0),(30>'V06 Calend 01'!C5),(30<'V06 Calend 01'!D5),(MOD((30-'V06 Calend 01'!C5),6)=0),(((30-'V06 Calend 01'!C5)/6)<='V06 Calend 01'!E5)),IF((30=('V06 Calend 01'!C5+(6*'V06 Calend 01'!E5))),('V06 Calend 01'!H5-('V06 Calend 01'!I5*('V06 Calend 01'!E5-1))),'V06 Calend 01'!I5),0))+IF((30='V06 Calend 01'!D5),'V06 Calend 01'!J5,0)) -> 0 | AQ5: =((IF((31='V06 Calend 01'!C5),('V06 Calend 01'!F5+'V06 Calend 01'!G5),0)+IF(AND(('V06 Calend 01'!E5>0),(31>'V06 Calend 01'!C5),(31<'V06 Calend 01'!D5),(MOD((31-'V06 Calend 01'!C5),6)=0),(((31-'V06 Calend 01'!C5)/6)<='V06 Calend 01'!E5)),IF((31=('V06 Calend 01'!C5+(6*'V06 Calend 01'!E5))),('V06 Calend 01'!H5-('V06 Calend 01'!I5*('V06 Calend 01'!E5-1))),'V06 Calend 01'!I5),0))+IF((31='V06 Calend 01'!D5),'V06 Calend 01'!J5,0)) -> 0 | AR5: =((IF((32='V06 Calend 01'!C5),('V06 Calend 01'!F5+'V06 Calend 01'!G5),0)+IF(AND(('V06 Calend 01'!E5>0),(32>'V06 Calend 01'!C5),(32<'V06 Calend 01'!D5),(MOD((32-'V06 Calend 01'!C5),6)=0),(((32-'V06 Calend 01'!C5)/6)<='V06 Calend 01'!E5)),IF((32=('V06 Calend 01'!C5+(6*'V06 Calend 01'!E5))),('V06 Calend 01'!H5-('V06 Calend 01'!I5*('V06 Calend 01'!E5-1))),'V06 Calend 01'!I5),0))+IF((32='V06 Calend 01'!D5),'V06 Calend 01'!J5,0)) -> 0 | AS5: =((IF((33='V06 Calend 01'!C5),('V06 Calend 01'!F5+'V06 Calend 01'!G5),0)+IF(AND(('V06 Calend 01'!E5>0),(33>'V06 Calend 01'!C5),(33<'V06 Calend 01'!D5),(MOD((33-'V06 Calend 01'!C5),6)=0),(((33-'V06 Calend 01'!C5)/6)<='V06 Calend 01'!E5)),IF((33=('V06 Calend 01'!C5+(6*'V06 Calend 01'!E5))),('V06 Calend 01'!H5-('V06 Calend 01'!I5*('V06 Calend 01'!E5-1))),'V06 Calend 01'!I5),0))+IF((33='V06 Calend 01'!D5),'V06 Calend 01'!J5,0)) -> 0 | AT5: =((IF((34='V06 Calend 01'!C5),('V06 Calend 01'!F5+'V06 Calend 01'!G5),0)+IF(AND(('V06 Calend 01'!E5>0),(34>'V06 Calend 01'!C5),(34<'V06 Calend 01'!D5),(MOD((34-'V06 Calend 01'!C5),6)=0),(((34-'V06 Calend 01'!C5)/6)<='V06 Calend 01'!E5)),IF((34=('V06 Calend 01'!C5+(6*'V06 Calend 01'!E5))),('V06 Calend 01'!H5-('V06 Calend 01'!I5*('V06 Calend 01'!E5-1))),'V06 Calend 01'!I5),0))+IF((34='V06 Calend 01'!D5),'V06 Calend 01'!J5,0)) -> 0 | AU5: =((IF((35='V06 Calend 01'!C5),('V06 Calend 01'!F5+'V06 Calend 01'!G5),0)+IF(AND(('V06 Calend 01'!E5>0),(35>'V06 Calend 01'!C5),(35<'V06 Calend 01'!D5),(MOD((35-'V06 Calend 01'!C5),6)=0),(((35-'V06 Calend 01'!C5)/6)<='V06 Calend 01'!E5)),IF((35=('V06 Calend 01'!C5+(6*'V06 Calend 01'!E5))),('V06 Calend 01'!H5-('V06 Calend 01'!I5*('V06 Calend 01'!E5-1))),'V06 Calend 01'!I5),0))+IF((35='V06 Calend 01'!D5),'V06 Calend 01'!J5,0)) -> 0 | AV5: =((IF((36='V06 Calend 01'!C5),('V06 Calend 01'!F5+'V06 Calend 01'!G5),0)+IF(AND(('V06 Calend 01'!E5>0),(36>'V06 Calend 01'!C5),(36<'V06 Calend 01'!D5),(MOD((36-'V06 Calend 01'!C5),6)=0),(((36-'V06 Calend 01'!C5)/6)<='V06 Calend 01'!E5)),IF((36=('V06 Calend 01'!C5+(6*'V06 Calend 01'!E5))),('V06 Calend 01'!H5-('V06 Calend 01'!I5*('V06 Calend 01'!E5-1))),'V06 Calend 01'!I5),0))+IF((36='V06 Calend 01'!D5),'V06 Calend 01'!J5,0)) -> 0 | AW5: =((IF((37='V06 Calend 01'!C5),('V06 Calend 01'!F5+'V06 Calend 01'!G5),0)+IF(AND(('V06 Calend 01'!E5>0),(37>'V06 Calend 01'!C5),(37<'V06 Calend 01'!D5),(MOD((37-'V06 Calend 01'!C5),6)=0),(((37-'V06 Calend 01'!C5)/6)<='V06 Calend 01'!E5)),IF((37=('V06 Calend 01'!C5+(6*'V06 Calend 01'!E5))),('V06 Calend 01'!H5-('V06 Calend 01'!I5*('V06 Calend 01'!E5-1))),'V06 Calend 01'!I5),0))+IF((37='V06 Calend 01'!D5),'V06 Calend 01'!J5,0)) -> 0 | AX5: =((IF((38='V06 Calend 01'!C5),('V06 Calend 01'!F5+'V06 Calend 01'!G5),0)+IF(AND(('V06 Calend 01'!E5>0),(38>'V06 Calend 01'!C5),(38<'V06 Calend 01'!D5),(MOD((38-'V06 Calend 01'!C5),6)=0),(((38-'V06 Calend 01'!C5)/6)<='V06 Calend 01'!E5)),IF((38=('V06 Calend 01'!C5+(6*'V06 Calend 01'!E5))),('V06 Calend 01'!H5-('V06 Calend 01'!I5*('V06 Calend 01'!E5-1))),'V06 Calend 01'!I5),0))+IF((38='V06 Calend 01'!D5),'V06 Calend 01'!J5,0)) -> 0 | AY5: =((IF((39='V06 Calend 01'!C5),('V06 Calend 01'!F5+'V06 Calend 01'!G5),0)+IF(AND(('V06 Calend 01'!E5>0),(39>'V06 Calend 01'!C5),(39<'V06 Calend 01'!D5),(MOD((39-'V06 Calend 01'!C5),6)=0),(((39-'V06 Calend 01'!C5)/6)<='V06 Calend 01'!E5)),IF((39=('V06 Calend 01'!C5+(6*'V06 Calend 01'!E5))),('V06 Calend 01'!H5-('V06 Calend 01'!I5*('V06 Calend 01'!E5-1))),'V06 Calend 01'!I5),0))+IF((39='V06 Calend 01'!D5),'V06 Calend 01'!J5,0)) -> 0 | AZ5: =((IF((40='V06 Calend 01'!C5),('V06 Calend 01'!F5+'V06 Calend 01'!G5),0)+IF(AND(('V06 Calend 01'!E5>0),(40>'V06 Calend 01'!C5),(40<'V06 Calend 01'!D5),(MOD((40-'V06 Calend 01'!C5),6)=0),(((40-'V06 Calend 01'!C5)/6)<='V06 Calend 01'!E5)),IF((40=('V06 Calend 01'!C5+(6*'V06 Calend 01'!E5))),('V06 Calend 01'!H5-('V06 Calend 01'!I5*('V06 Calend 01'!E5-1))),'V06 Calend 01'!I5),0))+IF((40='V06 Calend 01'!D5),'V06 Calend 01'!J5,0)) -> 0 | BA5: =((IF((41='V06 Calend 01'!C5),('V06 Calend 01'!F5+'V06 Calend 01'!G5),0)+IF(AND(('V06 Calend 01'!E5>0),(41>'V06 Calend 01'!C5),(41<'V06 Calend 01'!D5),(MOD((41-'V06 Calend 01'!C5),6)=0),(((41-'V06 Calend 01'!C5)/6)<='V06 Calend 01'!E5)),IF((41=('V06 Calend 01'!C5+(6*'V06 Calend 01'!E5))),('V06 Calend 01'!H5-('V06 Calend 01'!I5*('V06 Calend 01'!E5-1))),'V06 Calend 01'!I5),0))+IF((41='V06 Calend 01'!D5),'V06 Calend 01'!J5,0)) -> 0 | BB5: =((IF((42='V06 Calend 01'!C5),('V06 Calend 01'!F5+'V06 Calend 01'!G5),0)+IF(AND(('V06 Calend 01'!E5>0),(42>'V06 Calend 01'!C5),(42<'V06 Calend 01'!D5),(MOD((42-'V06 Calend 01'!C5),6)=0),(((42-'V06 Calend 01'!C5)/6)<='V06 Calend 01'!E5)),IF((42=('V06 Calend 01'!C5+(6*'V06 Calend 01'!E5))),('V06 Calend 01'!H5-('V06 Calend 01'!I5*('V06 Calend 01'!E5-1))),'V06 Calend 01'!I5),0))+IF((42='V06 Calend 01'!D5),'V06 Calend 01'!J5,0)) -> 0 | BC5: =((IF((43='V06 Calend 01'!C5),('V06 Calend 01'!F5+'V06 Calend 01'!G5),0)+IF(AND(('V06 Calend 01'!E5>0),(43>'V06 Calend 01'!C5),(43<'V06 Calend 01'!D5),(MOD((43-'V06 Calend 01'!C5),6)=0),(((43-'V06 Calend 01'!C5)/6)<='V06 Calend 01'!E5)),IF((43=('V06 Calend 01'!C5+(6*'V06 Calend 01'!E5))),('V06 Calend 01'!H5-('V06 Calend 01'!I5*('V06 Calend 01'!E5-1))),'V06 Calend 01'!I5),0))+IF((43='V06 Calend 01'!D5),'V06 Calend 01'!J5,0)) -> 0 | BD5: =((IF((44='V06 Calend 01'!C5),('V06 Calend 01'!F5+'V06 Calend 01'!G5),0)+IF(AND(('V06 Calend 01'!E5>0),(44>'V06 Calend 01'!C5),(44<'V06 Calend 01'!D5),(MOD((44-'V06 Calend 01'!C5),6)=0),(((44-'V06 Calend 01'!C5)/6)<='V06 Calend 01'!E5)),IF((44=('V06 Calend 01'!C5+(6*'V06 Calend 01'!E5))),('V06 Calend 01'!H5-('V06 Calend 01'!I5*('V06 Calend 01'!E5-1))),'V06 Calend 01'!I5),0))+IF((44='V06 Calend 01'!D5),'V06 Calend 01'!J5,0)) -> 0 | BE5: =((IF((45='V06 Calend 01'!C5),('V06 Calend 01'!F5+'V06 Calend 01'!G5),0)+IF(AND(('V06 Calend 01'!E5>0),(45>'V06 Calend 01'!C5),(45<'V06 Calend 01'!D5),(MOD((45-'V06 Calend 01'!C5),6)=0),(((45-'V06 Calend 01'!C5)/6)<='V06 Calend 01'!E5)),IF((45=('V06 Calend 01'!C5+(6*'V06 Calend 01'!E5))),('V06 Calend 01'!H5-('V06 Calend 01'!I5*('V06 Calend 01'!E5-1))),'V06 Calend 01'!I5),0))+IF((45='V06 Calend 01'!D5),'V06 Calend 01'!J5,0)) -> 0 | BF5: =((IF((46='V06 Calend 01'!C5),('V06 Calend 01'!F5+'V06 Calend 01'!G5),0)+IF(AND(('V06 Calend 01'!E5>0),(46>'V06 Calend 01'!C5),(46<'V06 Calend 01'!D5),(MOD((46-'V06 Calend 01'!C5),6)=0),(((46-'V06 Calend 01'!C5)/6)<='V06 Calend 01'!E5)),IF((46=('V06 Calend 01'!C5+(6*'V06 Calend 01'!E5))),('V06 Calend 01'!H5-('V06 Calend 01'!I5*('V06 Calend 01'!E5-1))),'V06 Calend 01'!I5),0))+IF((46='V06 Calend 01'!D5),'V06 Calend 01'!J5,0)) -> 0 | BG5: =((IF((47='V06 Calend 01'!C5),('V06 Calend 01'!F5+'V06 Calend 01'!G5),0)+IF(AND(('V06 Calend 01'!E5>0),(47>'V06 Calend 01'!C5),(47<'V06 Calend 01'!D5),(MOD((47-'V06 Calend 01'!C5),6)=0),(((47-'V06 Calend 01'!C5)/6)<='V06 Calend 01'!E5)),IF((47=('V06 Calend 01'!C5+(6*'V06 Calend 01'!E5))),('V06 Calend 01'!H5-('V06 Calend 01'!I5*('V06 Calend 01'!E5-1))),'V06 Calend 01'!I5),0))+IF((47='V06 Calend 01'!D5),'V06 Calend 01'!J5,0)) -> 0 | BH5: =((IF((48='V06 Calend 01'!C5),('V06 Calend 01'!F5+'V06 Calend 01'!G5),0)+IF(AND(('V06 Calend 01'!E5>0),(48>'V06 Calend 01'!C5),(48<'V06 Calend 01'!D5),(MOD((48-'V06 Calend 01'!C5),6)=0),(((48-'V06 Calend 01'!C5)/6)<='V06 Calend 01'!E5)),IF((48=('V06 Calend 01'!C5+(6*'V06 Calend 01'!E5))),('V06 Calend 01'!H5-('V06 Calend 01'!I5*('V06 Calend 01'!E5-1))),'V06 Calend 01'!I5),0))+IF((48='V06 Calend 01'!D5),'V06 Calend 01'!J5,0)) -> 0 | BI5: =((IF((49='V06 Calend 01'!C5),('V06 Calend 01'!F5+'V06 Calend 01'!G5),0)+IF(AND(('V06 Calend 01'!E5>0),(49>'V06 Calend 01'!C5),(49<'V06 Calend 01'!D5),(MOD((49-'V06 Calend 01'!C5),6)=0),(((49-'V06 Calend 01'!C5)/6)<='V06 Calend 01'!E5)),IF((49=('V06 Calend 01'!C5+(6*'V06 Calend 01'!E5))),('V06 Calend 01'!H5-('V06 Calend 01'!I5*('V06 Calend 01'!E5-1))),'V06 Calend 01'!I5),0))+IF((49='V06 Calend 01'!D5),'V06 Calend 01'!J5,0)) -> 0 | BJ5: =((IF((50='V06 Calend 01'!C5),('V06 Calend 01'!F5+'V06 Calend 01'!G5),0)+IF(AND(('V06 Calend 01'!E5>0),(50>'V06 Calend 01'!C5),(50<'V06 Calend 01'!D5),(MOD((50-'V06 Calend 01'!C5),6)=0),(((50-'V06 Calend 01'!C5)/6)<='V06 Calend 01'!E5)),IF((50=('V06 Calend 01'!C5+(6*'V06 Calend 01'!E5))),('V06 Calend 01'!H5-('V06 Calend 01'!I5*('V06 Calend 01'!E5-1))),'V06 Calend 01'!I5),0))+IF((50='V06 Calend 01'!D5),'V06 Calend 01'!J5,0)) -> 0 | BK5: =((IF((51='V06 Calend 01'!C5),('V06 Calend 01'!F5+'V06 Calend 01'!G5),0)+IF(AND(('V06 Calend 01'!E5>0),(51>'V06 Calend 01'!C5),(51<'V06 Calend 01'!D5),(MOD((51-'V06 Calend 01'!C5),6)=0),(((51-'V06 Calend 01'!C5)/6)<='V06 Calend 01'!E5)),IF((51=('V06 Calend 01'!C5+(6*'V06 Calend 01'!E5))),('V06 Calend 01'!H5-('V06 Calend 01'!I5*('V06 Calend 01'!E5-1))),'V06 Calend 01'!I5),0))+IF((51='V06 Calend 01'!D5),'V06 Calend 01'!J5,0)) -> 0 | BL5: =((IF((52='V06 Calend 01'!C5),('V06 Calend 01'!F5+'V06 Calend 01'!G5),0)+IF(AND(('V06 Calend 01'!E5>0),(52>'V06 Calend 01'!C5),(52<'V06 Calend 01'!D5),(MOD((52-'V06 Calend 01'!C5),6)=0),(((52-'V06 Calend 01'!C5)/6)<='V06 Calend 01'!E5)),IF((52=('V06 Calend 01'!C5+(6*'V06 Calend 01'!E5))),('V06 Calend 01'!H5-('V06 Calend 01'!I5*('V06 Calend 01'!E5-1))),'V06 Calend 01'!I5),0))+IF((52='V06 Calend 01'!D5),'V06 Calend 01'!J5,0)) -> 0 | BM5: =((IF((53='V06 Calend 01'!C5),('V06 Calend 01'!F5+'V06 Calend 01'!G5),0)+IF(AND(('V06 Calend 01'!E5>0),(53>'V06 Calend 01'!C5),(53<'V06 Calend 01'!D5),(MOD((53-'V06 Calend 01'!C5),6)=0),(((53-'V06 Calend 01'!C5)/6)<='V06 Calend 01'!E5)),IF((53=('V06 Calend 01'!C5+(6*'V06 Calend 01'!E5))),('V06 Calend 01'!H5-('V06 Calend 01'!I5*('V06 Calend 01'!E5-1))),'V06 Calend 01'!I5),0))+IF((53='V06 Calend 01'!D5),'V06 Calend 01'!J5,0)) -> 0 | BN5: =((IF((54='V06 Calend 01'!C5),('V06 Calend 01'!F5+'V06 Calend 01'!G5),0)+IF(AND(('V06 Calend 01'!E5>0),(54>'V06 Calend 01'!C5),(54<'V06 Calend 01'!D5),(MOD((54-'V06 Calend 01'!C5),6)=0),(((54-'V06 Calend 01'!C5)/6)<='V06 Calend 01'!E5)),IF((54=('V06 Calend 01'!C5+(6*'V06 Calend 01'!E5))),('V06 Calend 01'!H5-('V06 Calend 01'!I5*('V06 Calend 01'!E5-1))),'V06 Calend 01'!I5),0))+IF((54='V06 Calend 01'!D5),'V06 Calend 01'!J5,0)) -> 0 | BO5: =((IF((55='V06 Calend 01'!C5),('V06 Calend 01'!F5+'V06 Calend 01'!G5),0)+IF(AND(('V06 Calend 01'!E5>0),(55>'V06 Calend 01'!C5),(55<'V06 Calend 01'!D5),(MOD((55-'V06 Calend 01'!C5),6)=0),(((55-'V06 Calend 01'!C5)/6)<='V06 Calend 01'!E5)),IF((55=('V06 Calend 01'!C5+(6*'V06 Calend 01'!E5))),('V06 Calend 01'!H5-('V06 Calend 01'!I5*('V06 Calend 01'!E5-1))),'V06 Calend 01'!I5),0))+IF((55='V06 Calend 01'!D5),'V06 Calend 01'!J5,0)) -> 0 | BP5: =((IF((56='V06 Calend 01'!C5),('V06 Calend 01'!F5+'V06 Calend 01'!G5),0)+IF(AND(('V06 Calend 01'!E5>0),(56>'V06 Calend 01'!C5),(56<'V06 Calend 01'!D5),(MOD((56-'V06 Calend 01'!C5),6)=0),(((56-'V06 Calend 01'!C5)/6)<='V06 Calend 01'!E5)),IF((56=('V06 Calend 01'!C5+(6*'V06 Calend 01'!E5))),('V06 Calend 01'!H5-('V06 Calend 01'!I5*('V06 Calend 01'!E5-1))),'V06 Calend 01'!I5),0))+IF((56='V06 Calend 01'!D5),'V06 Calend 01'!J5,0)) -> 0 | BQ5: =((IF((57='V06 Calend 01'!C5),('V06 Calend 01'!F5+'V06 Calend 01'!G5),0)+IF(AND(('V06 Calend 01'!E5>0),(57>'V06 Calend 01'!C5),(57<'V06 Calend 01'!D5),(MOD((57-'V06 Calend 01'!C5),6)=0),(((57-'V06 Calend 01'!C5)/6)<='V06 Calend 01'!E5)),IF((57=('V06 Calend 01'!C5+(6*'V06 Calend 01'!E5))),('V06 Calend 01'!H5-('V06 Calend 01'!I5*('V06 Calend 01'!E5-1))),'V06 Calend 01'!I5),0))+IF((57='V06 Calend 01'!D5),'V06 Calend 01'!J5,0)) -> 0 | BR5: =((IF((58='V06 Calend 01'!C5),('V06 Calend 01'!F5+'V06 Calend 01'!G5),0)+IF(AND(('V06 Calend 01'!E5>0),(58>'V06 Calend 01'!C5),(58<'V06 Calend 01'!D5),(MOD((58-'V06 Calend 01'!C5),6)=0),(((58-'V06 Calend 01'!C5)/6)<='V06 Calend 01'!E5)),IF((58=('V06 Calend 01'!C5+(6*'V06 Calend 01'!E5))),('V06 Calend 01'!H5-('V06 Calend 01'!I5*('V06 Calend 01'!E5-1))),'V06 Calend 01'!I5),0))+IF((58='V06 Calend 01'!D5),'V06 Calend 01'!J5,0)) -> 0 | BS5: =((IF((59='V06 Calend 01'!C5),('V06 Calend 01'!F5+'V06 Calend 01'!G5),0)+IF(AND(('V06 Calend 01'!E5>0),(59>'V06 Calend 01'!C5),(59<'V06 Calend 01'!D5),(MOD((59-'V06 Calend 01'!C5),6)=0),(((59-'V06 Calend 01'!C5)/6)<='V06 Calend 01'!E5)),IF((59=('V06 Calend 01'!C5+(6*'V06 Calend 01'!E5))),('V06 Calend 01'!H5-('V06 Calend 01'!I5*('V06 Calend 01'!E5-1))),'V06 Calend 01'!I5),0))+IF((59='V06 Calend 01'!D5),'V06 Calend 01'!J5,0)) -> 0 | BT5: =((IF((60='V06 Calend 01'!C5),('V06 Calend 01'!F5+'V06 Calend 01'!G5),0)+IF(AND(('V06 Calend 01'!E5>0),(60>'V06 Calend 01'!C5),(60<'V06 Calend 01'!D5),(MOD((60-'V06 Calend 01'!C5),6)=0),(((60-'V06 Calend 01'!C5)/6)<='V06 Calend 01'!E5)),IF((60=('V06 Calend 01'!C5+(6*'V06 Calend 01'!E5))),('V06 Calend 01'!H5-('V06 Calend 01'!I5*('V06 Calend 01'!E5-1))),'V06 Calend 01'!I5),0))+IF((60='V06 Calend 01'!D5),'V06 Calend 01'!J5,0)) -> 0 | BU5: =((IF((61='V06 Calend 01'!C5),('V06 Calend 01'!F5+'V06 Calend 01'!G5),0)+IF(AND(('V06 Calend 01'!E5>0),(61>'V06 Calend 01'!C5),(61<'V06 Calend 01'!D5),(MOD((61-'V06 Calend 01'!C5),6)=0),(((61-'V06 Calend 01'!C5)/6)<='V06 Calend 01'!E5)),IF((61=('V06 Calend 01'!C5+(6*'V06 Calend 01'!E5))),('V06 Calend 01'!H5-('V06 Calend 01'!I5*('V06 Calend 01'!E5-1))),'V06 Calend 01'!I5),0))+IF((61='V06 Calend 01'!D5),'V06 Calend 01'!J5,0)) -> 0 | BV5: =((IF((62='V06 Calend 01'!C5),('V06 Calend 01'!F5+'V06 Calend 01'!G5),0)+IF(AND(('V06 Calend 01'!E5>0),(62>'V06 Calend 01'!C5),(62<'V06 Calend 01'!D5),(MOD((62-'V06 Calend 01'!C5),6)=0),(((62-'V06 Calend 01'!C5)/6)<='V06 Calend 01'!E5)),IF((62=('V06 Calend 01'!C5+(6*'V06 Calend 01'!E5))),('V06 Calend 01'!H5-('V06 Calend 01'!I5*('V06 Calend 01'!E5-1))),'V06 Calend 01'!I5),0))+IF((62='V06 Calend 01'!D5),'V06 Calend 01'!J5,0)) -> 0 | BW5: =((IF((63='V06 Calend 01'!C5),('V06 Calend 01'!F5+'V06 Calend 01'!G5),0)+IF(AND(('V06 Calend 01'!E5>0),(63>'V06 Calend 01'!C5),(63<'V06 Calend 01'!D5),(MOD((63-'V06 Calend 01'!C5),6)=0),(((63-'V06 Calend 01'!C5)/6)<='V06 Calend 01'!E5)),IF((63=('V06 Calend 01'!C5+(6*'V06 Calend 01'!E5))),('V06 Calend 01'!H5-('V06 Calend 01'!I5*('V06 Calend 01'!E5-1))),'V06 Calend 01'!I5),0))+IF((63='V06 Calend 01'!D5),'V06 Calend 01'!J5,0)) -> 0 | BX5: =((IF((64='V06 Calend 01'!C5),('V06 Calend 01'!F5+'V06 Calend 01'!G5),0)+IF(AND(('V06 Calend 01'!E5>0),(64>'V06 Calend 01'!C5),(64<'V06 Calend 01'!D5),(MOD((64-'V06 Calend 01'!C5),6)=0),(((64-'V06 Calend 01'!C5)/6)<='V06 Calend 01'!E5)),IF((64=('V06 Calend 01'!C5+(6*'V06 Calend 01'!E5))),('V06 Calend 01'!H5-('V06 Calend 01'!I5*('V06 Calend 01'!E5-1))),'V06 Calend 01'!I5),0))+IF((64='V06 Calend 01'!D5),'V06 Calend 01'!J5,0)) -> 0 | BY5: =((IF((65='V06 Calend 01'!C5),('V06 Calend 01'!F5+'V06 Calend 01'!G5),0)+IF(AND(('V06 Calend 01'!E5>0),(65>'V06 Calend 01'!C5),(65<'V06 Calend 01'!D5),(MOD((65-'V06 Calend 01'!C5),6)=0),(((65-'V06 Calend 01'!C5)/6)<='V06 Calend 01'!E5)),IF((65=('V06 Calend 01'!C5+(6*'V06 Calend 01'!E5))),('V06 Calend 01'!H5-('V06 Calend 01'!I5*('V06 Calend 01'!E5-1))),'V06 Calend 01'!I5),0))+IF((65='V06 Calend 01'!D5),'V06 Calend 01'!J5,0)) -> 0 | BZ5: =((IF((66='V06 Calend 01'!C5),('V06 Calend 01'!F5+'V06 Calend 01'!G5),0)+IF(AND(('V06 Calend 01'!E5>0),(66>'V06 Calend 01'!C5),(66<'V06 Calend 01'!D5),(MOD((66-'V06 Calend 01'!C5),6)=0),(((66-'V06 Calend 01'!C5)/6)<='V06 Calend 01'!E5)),IF((66=('V06 Calend 01'!C5+(6*'V06 Calend 01'!E5))),('V06 Calend 01'!H5-('V06 Calend 01'!I5*('V06 Calend 01'!E5-1))),'V06 Calend 01'!I5),0))+IF((66='V06 Calend 01'!D5),'V06 Calend 01'!J5,0)) -> 0 | CA5: =((IF((67='V06 Calend 01'!C5),('V06 Calend 01'!F5+'V06 Calend 01'!G5),0)+IF(AND(('V06 Calend 01'!E5>0),(67>'V06 Calend 01'!C5),(67<'V06 Calend 01'!D5),(MOD((67-'V06 Calend 01'!C5),6)=0),(((67-'V06 Calend 01'!C5)/6)<='V06 Calend 01'!E5)),IF((67=('V06 Calend 01'!C5+(6*'V06 Calend 01'!E5))),('V06 Calend 01'!H5-('V06 Calend 01'!I5*('V06 Calend 01'!E5-1))),'V06 Calend 01'!I5),0))+IF((67='V06 Calend 01'!D5),'V06 Calend 01'!J5,0)) -> 0 | CB5: =((IF((68='V06 Calend 01'!C5),('V06 Calend 01'!F5+'V06 Calend 01'!G5),0)+IF(AND(('V06 Calend 01'!E5>0),(68>'V06 Calend 01'!C5),(68<'V06 Calend 01'!D5),(MOD((68-'V06 Calend 01'!C5),6)=0),(((68-'V06 Calend 01'!C5)/6)<='V06 Calend 01'!E5)),IF((68=('V06 Calend 01'!C5+(6*'V06 Calend 01'!E5))),('V06 Calend 01'!H5-('V06 Calend 01'!I5*('V06 Calend 01'!E5-1))),'V06 Calend 01'!I5),0))+IF((68='V06 Calend 01'!D5),'V06 Calend 01'!J5,0)) -> 0 | CC5: =((IF((69='V06 Calend 01'!C5),('V06 Calend 01'!F5+'V06 Calend 01'!G5),0)+IF(AND(('V06 Calend 01'!E5>0),(69>'V06 Calend 01'!C5),(69<'V06 Calend 01'!D5),(MOD((69-'V06 Calend 01'!C5),6)=0),(((69-'V06 Calend 01'!C5)/6)<='V06 Calend 01'!E5)),IF((69=('V06 Calend 01'!C5+(6*'V06 Calend 01'!E5))),('V06 Calend 01'!H5-('V06 Calend 01'!I5*('V06 Calend 01'!E5-1))),'V06 Calend 01'!I5),0))+IF((69='V06 Calend 01'!D5),'V06 Calend 01'!J5,0)) -> 0 | CD5: =((IF((70='V06 Calend 01'!C5),('V06 Calend 01'!F5+'V06 Calend 01'!G5),0)+IF(AND(('V06 Calend 01'!E5>0),(70>'V06 Calend 01'!C5),(70<'V06 Calend 01'!D5),(MOD((70-'V06 Calend 01'!C5),6)=0),(((70-'V06 Calend 01'!C5)/6)<='V06 Calend 01'!E5)),IF((70=('V06 Calend 01'!C5+(6*'V06 Calend 01'!E5))),('V06 Calend 01'!H5-('V06 Calend 01'!I5*('V06 Calend 01'!E5-1))),'V06 Calend 01'!I5),0))+IF((70='V06 Calend 01'!D5),'V06 Calend 01'!J5,0)) -> 0 | CE5: =((IF((71='V06 Calend 01'!C5),('V06 Calend 01'!F5+'V06 Calend 01'!G5),0)+IF(AND(('V06 Calend 01'!E5>0),(71>'V06 Calend 01'!C5),(71<'V06 Calend 01'!D5),(MOD((71-'V06 Calend 01'!C5),6)=0),(((71-'V06 Calend 01'!C5)/6)<='V06 Calend 01'!E5)),IF((71=('V06 Calend 01'!C5+(6*'V06 Calend 01'!E5))),('V06 Calend 01'!H5-('V06 Calend 01'!I5*('V06 Calend 01'!E5-1))),'V06 Calend 01'!I5),0))+IF((71='V06 Calend 01'!D5),'V06 Calend 01'!J5,0)) -> 0 | CF5: =((IF((72='V06 Calend 01'!C5),('V06 Calend 01'!F5+'V06 Calend 01'!G5),0)+IF(AND(('V06 Calend 01'!E5>0),(72>'V06 Calend 01'!C5),(72<'V06 Calend 01'!D5),(MOD((72-'V06 Calend 01'!C5),6)=0),(((72-'V06 Calend 01'!C5)/6)<='V06 Calend 01'!E5)),IF((72=('V06 Calend 01'!C5+(6*'V06 Calend 01'!E5))),('V06 Calend 01'!H5-('V06 Calend 01'!I5*('V06 Calend 01'!E5-1))),'V06 Calend 01'!I5),0))+IF((72='V06 Calend 01'!D5),'V06 Calend 01'!J5,0)) -> 0 | CG5: =((IF((73='V06 Calend 01'!C5),('V06 Calend 01'!F5+'V06 Calend 01'!G5),0)+IF(AND(('V06 Calend 01'!E5>0),(73>'V06 Calend 01'!C5),(73<'V06 Calend 01'!D5),(MOD((73-'V06 Calend 01'!C5),6)=0),(((73-'V06 Calend 01'!C5)/6)<='V06 Calend 01'!E5)),IF((73=('V06 Calend 01'!C5+(6*'V06 Calend 01'!E5))),('V06 Calend 01'!H5-('V06 Calend 01'!I5*('V06 Calend 01'!E5-1))),'V06 Calend 01'!I5),0))+IF((73='V06 Calend 01'!D5),'V06 Calend 01'!J5,0)) -> 0 | CH5: =((IF((74='V06 Calend 01'!C5),('V06 Calend 01'!F5+'V06 Calend 01'!G5),0)+IF(AND(('V06 Calend 01'!E5>0),(74>'V06 Calend 01'!C5),(74<'V06 Calend 01'!D5),(MOD((74-'V06 Calend 01'!C5),6)=0),(((74-'V06 Calend 01'!C5)/6)<='V06 Calend 01'!E5)),IF((74=('V06 Calend 01'!C5+(6*'V06 Calend 01'!E5))),('V06 Calend 01'!H5-('V06 Calend 01'!I5*('V06 Calend 01'!E5-1))),'V06 Calend 01'!I5),0))+IF((74='V06 Calend 01'!D5),'V06 Calend 01'!J5,0)) -> 0 | CI5: =((IF((75='V06 Calend 01'!C5),('V06 Calend 01'!F5+'V06 Calend 01'!G5),0)+IF(AND(('V06 Calend 01'!E5>0),(75>'V06 Calend 01'!C5),(75<'V06 Calend 01'!D5),(MOD((75-'V06 Calend 01'!C5),6)=0),(((75-'V06 Calend 01'!C5)/6)<='V06 Calend 01'!E5)),IF((75=('V06 Calend 01'!C5+(6*'V06 Calend 01'!E5))),('V06 Calend 01'!H5-('V06 Calend 01'!I5*('V06 Calend 01'!E5-1))),'V06 Calend 01'!I5),0))+IF((75='V06 Calend 01'!D5),'V06 Calend 01'!J5,0)) -> 0 | CJ5: =((IF((76='V06 Calend 01'!C5),('V06 Calend 01'!F5+'V06 Calend 01'!G5),0)+IF(AND(('V06 Calend 01'!E5>0),(76>'V06 Calend 01'!C5),(76<'V06 Calend 01'!D5),(MOD((76-'V06 Calend 01'!C5),6)=0),(((76-'V06 Calend 01'!C5)/6)<='V06 Calend 01'!E5)),IF((76=('V06 Calend 01'!C5+(6*'V06 Calend 01'!E5))),('V06 Calend 01'!H5-('V06 Calend 01'!I5*('V06 Calend 01'!E5-1))),'V06 Calend 01'!I5),0))+IF((76='V06 Calend 01'!D5),'V06 Calend 01'!J5,0)) -> 0 | CK5: =((IF((77='V06 Calend 01'!C5),('V06 Calend 01'!F5+'V06 Calend 01'!G5),0)+IF(AND(('V06 Calend 01'!E5>0),(77>'V06 Calend 01'!C5),(77<'V06 Calend 01'!D5),(MOD((77-'V06 Calend 01'!C5),6)=0),(((77-'V06 Calend 01'!C5)/6)<='V06 Calend 01'!E5)),IF((77=('V06 Calend 01'!C5+(6*'V06 Calend 01'!E5))),('V06 Calend 01'!H5-('V06 Calend 01'!I5*('V06 Calend 01'!E5-1))),'V06 Calend 01'!I5),0))+IF((77='V06 Calend 01'!D5),'V06 Calend 01'!J5,0)) -> 0 | CL5: =((IF((78='V06 Calend 01'!C5),('V06 Calend 01'!F5+'V06 Calend 01'!G5),0)+IF(AND(('V06 Calend 01'!E5>0),(78>'V06 Calend 01'!C5),(78<'V06 Calend 01'!D5),(MOD((78-'V06 Calend 01'!C5),6)=0),(((78-'V06 Calend 01'!C5)/6)<='V06 Calend 01'!E5)),IF((78=('V06 Calend 01'!C5+(6*'V06 Calend 01'!E5))),('V06 Calend 01'!H5-('V06 Calend 01'!I5*('V06 Calend 01'!E5-1))),'V06 Calend 01'!I5),0))+IF((78='V06 Calend 01'!D5),'V06 Calend 01'!J5,0)) -> 0 | CM5: =((IF((79='V06 Calend 01'!C5),('V06 Calend 01'!F5+'V06 Calend 01'!G5),0)+IF(AND(('V06 Calend 01'!E5>0),(79>'V06 Calend 01'!C5),(79<'V06 Calend 01'!D5),(MOD((79-'V06 Calend 01'!C5),6)=0),(((79-'V06 Calend 01'!C5)/6)<='V06 Calend 01'!E5)),IF((79=('V06 Calend 01'!C5+(6*'V06 Calend 01'!E5))),('V06 Calend 01'!H5-('V06 Calend 01'!I5*('V06 Calend 01'!E5-1))),'V06 Calend 01'!I5),0))+IF((79='V06 Calend 01'!D5),'V06 Calend 01'!J5,0)) -> 0 | CN5: =((IF((80='V06 Calend 01'!C5),('V06 Calend 01'!F5+'V06 Calend 01'!G5),0)+IF(AND(('V06 Calend 01'!E5>0),(80>'V06 Calend 01'!C5),(80<'V06 Calend 01'!D5),(MOD((80-'V06 Calend 01'!C5),6)=0),(((80-'V06 Calend 01'!C5)/6)<='V06 Calend 01'!E5)),IF((80=('V06 Calend 01'!C5+(6*'V06 Calend 01'!E5))),('V06 Calend 01'!H5-('V06 Calend 01'!I5*('V06 Calend 01'!E5-1))),'V06 Calend 01'!I5),0))+IF((80='V06 Calend 01'!D5),'V06 Calend 01'!J5,0)) -> 0 | CO5: =((IF((81='V06 Calend 01'!C5),('V06 Calend 01'!F5+'V06 Calend 01'!G5),0)+IF(AND(('V06 Calend 01'!E5>0),(81>'V06 Calend 01'!C5),(81<'V06 Calend 01'!D5),(MOD((81-'V06 Calend 01'!C5),6)=0),(((81-'V06 Calend 01'!C5)/6)<='V06 Calend 01'!E5)),IF((81=('V06 Calend 01'!C5+(6*'V06 Calend 01'!E5))),('V06 Calend 01'!H5-('V06 Calend 01'!I5*('V06 Calend 01'!E5-1))),'V06 Calend 01'!I5),0))+IF((81='V06 Calend 01'!D5),'V06 Calend 01'!J5,0)) -> 0 | CP5: =((IF((82='V06 Calend 01'!C5),('V06 Calend 01'!F5+'V06 Calend 01'!G5),0)+IF(AND(('V06 Calend 01'!E5>0),(82>'V06 Calend 01'!C5),(82<'V06 Calend 01'!D5),(MOD((82-'V06 Calend 01'!C5),6)=0),(((82-'V06 Calend 01'!C5)/6)<='V06 Calend 01'!E5)),IF((82=('V06 Calend 01'!C5+(6*'V06 Calend 01'!E5))),('V06 Calend 01'!H5-('V06 Calend 01'!I5*('V06 Calend 01'!E5-1))),'V06 Calend 01'!I5),0))+IF((82='V06 Calend 01'!D5),'V06 Calend 01'!J5,0)) -> 0 | CQ5: =((IF((83='V06 Calend 01'!C5),('V06 Calend 01'!F5+'V06 Calend 01'!G5),0)+IF(AND(('V06 Calend 01'!E5>0),(83>'V06 Calend 01'!C5),(83<'V06 Calend 01'!D5),(MOD((83-'V06 Calend 01'!C5),6)=0),(((83-'V06 Calend 01'!C5)/6)<='V06 Calend 01'!E5)),IF((83=('V06 Calend 01'!C5+(6*'V06 Calend 01'!E5))),('V06 Calend 01'!H5-('V06 Calend 01'!I5*('V06 Calend 01'!E5-1))),'V06 Calend 01'!I5),0))+IF((83='V06 Calend 01'!D5),'V06 Calend 01'!J5,0)) -> 0 | CR5: =((IF((84='V06 Calend 01'!C5),('V06 Calend 01'!F5+'V06 Calend 01'!G5),0)+IF(AND(('V06 Calend 01'!E5>0),(84>'V06 Calend 01'!C5),(84<'V06 Calend 01'!D5),(MOD((84-'V06 Calend 01'!C5),6)=0),(((84-'V06 Calend 01'!C5)/6)<='V06 Calend 01'!E5)),IF((84=('V06 Calend 01'!C5+(6*'V06 Calend 01'!E5))),('V06 Calend 01'!H5-('V06 Calend 01'!I5*('V06 Calend 01'!E5-1))),'V06 Calend 01'!I5),0))+IF((84='V06 Calend 01'!D5),'V06 Calend 01'!J5,0)) -> 0 | CS5: =((IF((85='V06 Calend 01'!C5),('V06 Calend 01'!F5+'V06 Calend 01'!G5),0)+IF(AND(('V06 Calend 01'!E5>0),(85>'V06 Calend 01'!C5),(85<'V06 Calend 01'!D5),(MOD((85-'V06 Calend 01'!C5),6)=0),(((85-'V06 Calend 01'!C5)/6)<='V06 Calend 01'!E5)),IF((85=('V06 Calend 01'!C5+(6*'V06 Calend 01'!E5))),('V06 Calend 01'!H5-('V06 Calend 01'!I5*('V06 Calend 01'!E5-1))),'V06 Calend 01'!I5),0))+IF((85='V06 Calend 01'!D5),'V06 Calend 01'!J5,0)) -> 0 | CT5: =((IF((86='V06 Calend 01'!C5),('V06 Calend 01'!F5+'V06 Calend 01'!G5),0)+IF(AND(('V06 Calend 01'!E5>0),(86>'V06 Calend 01'!C5),(86<'V06 Calend 01'!D5),(MOD((86-'V06 Calend 01'!C5),6)=0),(((86-'V06 Calend 01'!C5)/6)<='V06 Calend 01'!E5)),IF((86=('V06 Calend 01'!C5+(6*'V06 Calend 01'!E5))),('V06 Calend 01'!H5-('V06 Calend 01'!I5*('V06 Calend 01'!E5-1))),'V06 Calend 01'!I5),0))+IF((86='V06 Calend 01'!D5),'V06 Calend 01'!J5,0)) -> 0 | CU5: =((IF((87='V06 Calend 01'!C5),('V06 Calend 01'!F5+'V06 Calend 01'!G5),0)+IF(AND(('V06 Calend 01'!E5>0),(87>'V06 Calend 01'!C5),(87<'V06 Calend 01'!D5),(MOD((87-'V06 Calend 01'!C5),6)=0),(((87-'V06 Calend 01'!C5)/6)<='V06 Calend 01'!E5)),IF((87=('V06 Calend 01'!C5+(6*'V06 Calend 01'!E5))),('V06 Calend 01'!H5-('V06 Calend 01'!I5*('V06 Calend 01'!E5-1))),'V06 Calend 01'!I5),0))+IF((87='V06 Calend 01'!D5),'V06 Calend 01'!J5,0)) -> 0 | CV5: =((IF((88='V06 Calend 01'!C5),('V06 Calend 01'!F5+'V06 Calend 01'!G5),0)+IF(AND(('V06 Calend 01'!E5>0),(88>'V06 Calend 01'!C5),(88<'V06 Calend 01'!D5),(MOD((88-'V06 Calend 01'!C5),6)=0),(((88-'V06 Calend 01'!C5)/6)<='V06 Calend 01'!E5)),IF((88=('V06 Calend 01'!C5+(6*'V06 Calend 01'!E5))),('V06 Calend 01'!H5-('V06 Calend 01'!I5*('V06 Calend 01'!E5-1))),'V06 Calend 01'!I5),0))+IF((88='V06 Calend 01'!D5),'V06 Calend 01'!J5,0)) -> 0 | CW5: =((IF((89='V06 Calend 01'!C5),('V06 Calend 01'!F5+'V06 Calend 01'!G5),0)+IF(AND(('V06 Calend 01'!E5>0),(89>'V06 Calend 01'!C5),(89<'V06 Calend 01'!D5),(MOD((89-'V06 Calend 01'!C5),6)=0),(((89-'V06 Calend 01'!C5)/6)<='V06 Calend 01'!E5)),IF((89=('V06 Calend 01'!C5+(6*'V06 Calend 01'!E5))),('V06 Calend 01'!H5-('V06 Calend 01'!I5*('V06 Calend 01'!E5-1))),'V06 Calend 01'!I5),0))+IF((89='V06 Calend 01'!D5),'V06 Calend 01'!J5,0)) -> 0 | CX5: =((IF((90='V06 Calend 01'!C5),('V06 Calend 01'!F5+'V06 Calend 01'!G5),0)+IF(AND(('V06 Calend 01'!E5>0),(90>'V06 Calend 01'!C5),(90<'V06 Calend 01'!D5),(MOD((90-'V06 Calend 01'!C5),6)=0),(((90-'V06 Calend 01'!C5)/6)<='V06 Calend 01'!E5)),IF((90=('V06 Calend 01'!C5+(6*'V06 Calend 01'!E5))),('V06 Calend 01'!H5-('V06 Calend 01'!I5*('V06 Calend 01'!E5-1))),'V06 Calend 01'!I5),0))+IF((90='V06 Calend 01'!D5),'V06 Calend 01'!J5,0)) -> 0 | CY5: =((IF((91='V06 Calend 01'!C5),('V06 Calend 01'!F5+'V06 Calend 01'!G5),0)+IF(AND(('V06 Calend 01'!E5>0),(91>'V06 Calend 01'!C5),(91<'V06 Calend 01'!D5),(MOD((91-'V06 Calend 01'!C5),6)=0),(((91-'V06 Calend 01'!C5)/6)<='V06 Calend 01'!E5)),IF((91=('V06 Calend 01'!C5+(6*'V06 Calend 01'!E5))),('V06 Calend 01'!H5-('V06 Calend 01'!I5*('V06 Calend 01'!E5-1))),'V06 Calend 01'!I5),0))+IF((91='V06 Calend 01'!D5),'V06 Calend 01'!J5,0)) -> 0 | CZ5: =((IF((92='V06 Calend 01'!C5),('V06 Calend 01'!F5+'V06 Calend 01'!G5),0)+IF(AND(('V06 Calend 01'!E5>0),(92>'V06 Calend 01'!C5),(92<'V06 Calend 01'!D5),(MOD((92-'V06 Calend 01'!C5),6)=0),(((92-'V06 Calend 01'!C5)/6)<='V06 Calend 01'!E5)),IF((92=('V06 Calend 01'!C5+(6*'V06 Calend 01'!E5))),('V06 Calend 01'!H5-('V06 Calend 01'!I5*('V06 Calend 01'!E5-1))),'V06 Calend 01'!I5),0))+IF((92='V06 Calend 01'!D5),'V06 Calend 01'!J5,0)) -> 0 | DA5: =((IF((93='V06 Calend 01'!C5),('V06 Calend 01'!F5+'V06 Calend 01'!G5),0)+IF(AND(('V06 Calend 01'!E5>0),(93>'V06 Calend 01'!C5),(93<'V06 Calend 01'!D5),(MOD((93-'V06 Calend 01'!C5),6)=0),(((93-'V06 Calend 01'!C5)/6)<='V06 Calend 01'!E5)),IF((93=('V06 Calend 01'!C5+(6*'V06 Calend 01'!E5))),('V06 Calend 01'!H5-('V06 Calend 01'!I5*('V06 Calend 01'!E5-1))),'V06 Calend 01'!I5),0))+IF((93='V06 Calend 01'!D5),'V06 Calend 01'!J5,0)) -> 0 | DB5: =((IF((94='V06 Calend 01'!C5),('V06 Calend 01'!F5+'V06 Calend 01'!G5),0)+IF(AND(('V06 Calend 01'!E5>0),(94>'V06 Calend 01'!C5),(94<'V06 Calend 01'!D5),(MOD((94-'V06 Calend 01'!C5),6)=0),(((94-'V06 Calend 01'!C5)/6)<='V06 Calend 01'!E5)),IF((94=('V06 Calend 01'!C5+(6*'V06 Calend 01'!E5))),('V06 Calend 01'!H5-('V06 Calend 01'!I5*('V06 Calend 01'!E5-1))),'V06 Calend 01'!I5),0))+IF((94='V06 Calend 01'!D5),'V06 Calend 01'!J5,0)) -> 0 | DC5: =((IF((95='V06 Calend 01'!C5),('V06 Calend 01'!F5+'V06 Calend 01'!G5),0)+IF(AND(('V06 Calend 01'!E5>0),(95>'V06 Calend 01'!C5),(95<'V06 Calend 01'!D5),(MOD((95-'V06 Calend 01'!C5),6)=0),(((95-'V06 Calend 01'!C5)/6)<='V06 Calend 01'!E5)),IF((95=('V06 Calend 01'!C5+(6*'V06 Calend 01'!E5))),('V06 Calend 01'!H5-('V06 Calend 01'!I5*('V06 Calend 01'!E5-1))),'V06 Calend 01'!I5),0))+IF((95='V06 Calend 01'!D5),'V06 Calend 01'!J5,0)) -> 0 | DD5: =((IF((96='V06 Calend 01'!C5),('V06 Calend 01'!F5+'V06 Calend 01'!G5),0)+IF(AND(('V06 Calend 01'!E5>0),(96>'V06 Calend 01'!C5),(96<'V06 Calend 01'!D5),(MOD((96-'V06 Calend 01'!C5),6)=0),(((96-'V06 Calend 01'!C5)/6)<='V06 Calend 01'!E5)),IF((96=('V06 Calend 01'!C5+(6*'V06 Calend 01'!E5))),('V06 Calend 01'!H5-('V06 Calend 01'!I5*('V06 Calend 01'!E5-1))),'V06 Calend 01'!I5),0))+IF((96='V06 Calend 01'!D5),'V06 Calend 01'!J5,0)) -> 0 | DE5: =((IF((97='V06 Calend 01'!C5),('V06 Calend 01'!F5+'V06 Calend 01'!G5),0)+IF(AND(('V06 Calend 01'!E5>0),(97>'V06 Calend 01'!C5),(97<'V06 Calend 01'!D5),(MOD((97-'V06 Calend 01'!C5),6)=0),(((97-'V06 Calend 01'!C5)/6)<='V06 Calend 01'!E5)),IF((97=('V06 Calend 01'!C5+(6*'V06 Calend 01'!E5))),('V06 Calend 01'!H5-('V06 Calend 01'!I5*('V06 Calend 01'!E5-1))),'V06 Calend 01'!I5),0))+IF((97='V06 Calend 01'!D5),'V06 Calend 01'!J5,0)) -> 0 | DF5: =((IF((98='V06 Calend 01'!C5),('V06 Calend 01'!F5+'V06 Calend 01'!G5),0)+IF(AND(('V06 Calend 01'!E5>0),(98>'V06 Calend 01'!C5),(98<'V06 Calend 01'!D5),(MOD((98-'V06 Calend 01'!C5),6)=0),(((98-'V06 Calend 01'!C5)/6)<='V06 Calend 01'!E5)),IF((98=('V06 Calend 01'!C5+(6*'V06 Calend 01'!E5))),('V06 Calend 01'!H5-('V06 Calend 01'!I5*('V06 Calend 01'!E5-1))),'V06 Calend 01'!I5),0))+IF((98='V06 Calend 01'!D5),'V06 Calend 01'!J5,0)) -> 0 | DG5: =((IF((99='V06 Calend 01'!C5),('V06 Calend 01'!F5+'V06 Calend 01'!G5),0)+IF(AND(('V06 Calend 01'!E5>0),(99>'V06 Calend 01'!C5),(99<'V06 Calend 01'!D5),(MOD((99-'V06 Calend 01'!C5),6)=0),(((99-'V06 Calend 01'!C5)/6)<='V06 Calend 01'!E5)),IF((99=('V06 Calend 01'!C5+(6*'V06 Calend 01'!E5))),('V06 Calend 01'!H5-('V06 Calend 01'!I5*('V06 Calend 01'!E5-1))),'V06 Calend 01'!I5),0))+IF((99='V06 Calend 01'!D5),'V06 Calend 01'!J5,0)) -> 0 | DH5: =((IF((100='V06 Calend 01'!C5),('V06 Calend 01'!F5+'V06 Calend 01'!G5),0)+IF(AND(('V06 Calend 01'!E5>0),(100>'V06 Calend 01'!C5),(100<'V06 Calend 01'!D5),(MOD((100-'V06 Calend 01'!C5),6)=0),(((100-'V06 Calend 01'!C5)/6)<='V06 Calend 01'!E5)),IF((100=('V06 Calend 01'!C5+(6*'V06 Calend 01'!E5))),('V06 Calend 01'!H5-('V06 Calend 01'!I5*('V06 Calend 01'!E5-1))),'V06 Calend 01'!I5),0))+IF((100='V06 Calend 01'!D5),'V06 Calend 01'!J5,0)) -> 0 | DI5: =((IF((101='V06 Calend 01'!C5),('V06 Calend 01'!F5+'V06 Calend 01'!G5),0)+IF(AND(('V06 Calend 01'!E5>0),(101>'V06 Calend 01'!C5),(101<'V06 Calend 01'!D5),(MOD((101-'V06 Calend 01'!C5),6)=0),(((101-'V06 Calend 01'!C5)/6)<='V06 Calend 01'!E5)),IF((101=('V06 Calend 01'!C5+(6*'V06 Calend 01'!E5))),('V06 Calend 01'!H5-('V06 Calend 01'!I5*('V06 Calend 01'!E5-1))),'V06 Calend 01'!I5),0))+IF((101='V06 Calend 01'!D5),'V06 Calend 01'!J5,0)) -> 0 | DJ5: =((IF((102='V06 Calend 01'!C5),('V06 Calend 01'!F5+'V06 Calend 01'!G5),0)+IF(AND(('V06 Calend 01'!E5>0),(102>'V06 Calend 01'!C5),(102<'V06 Calend 01'!D5),(MOD((102-'V06 Calend 01'!C5),6)=0),(((102-'V06 Calend 01'!C5)/6)<='V06 Calend 01'!E5)),IF((102=('V06 Calend 01'!C5+(6*'V06 Calend 01'!E5))),('V06 Calend 01'!H5-('V06 Calend 01'!I5*('V06 Calend 01'!E5-1))),'V06 Calend 01'!I5),0))+IF((102='V06 Calend 01'!D5),'V06 Calend 01'!J5,0)) -> 0 | DK5: =((IF((103='V06 Calend 01'!C5),('V06 Calend 01'!F5+'V06 Calend 01'!G5),0)+IF(AND(('V06 Calend 01'!E5>0),(103>'V06 Calend 01'!C5),(103<'V06 Calend 01'!D5),(MOD((103-'V06 Calend 01'!C5),6)=0),(((103-'V06 Calend 01'!C5)/6)<='V06 Calend 01'!E5)),IF((103=('V06 Calend 01'!C5+(6*'V06 Calend 01'!E5))),('V06 Calend 01'!H5-('V06 Calend 01'!I5*('V06 Calend 01'!E5-1))),'V06 Calend 01'!I5),0))+IF((103='V06 Calend 01'!D5),'V06 Calend 01'!J5,0)) -> 0 | DL5: =((IF((104='V06 Calend 01'!C5),('V06 Calend 01'!F5+'V06 Calend 01'!G5),0)+IF(AND(('V06 Calend 01'!E5>0),(104>'V06 Calend 01'!C5),(104<'V06 Calend 01'!D5),(MOD((104-'V06 Calend 01'!C5),6)=0),(((104-'V06 Calend 01'!C5)/6)<='V06 Calend 01'!E5)),IF((104=('V06 Calend 01'!C5+(6*'V06 Calend 01'!E5))),('V06 Calend 01'!H5-('V06 Calend 01'!I5*('V06 Calend 01'!E5-1))),'V06 Calend 01'!I5),0))+IF((104='V06 Calend 01'!D5),'V06 Calend 01'!J5,0)) -> 0 | DM5: =((IF((105='V06 Calend 01'!C5),('V06 Calend 01'!F5+'V06 Calend 01'!G5),0)+IF(AND(('V06 Calend 01'!E5>0),(105>'V06 Calend 01'!C5),(105<'V06 Calend 01'!D5),(MOD((105-'V06 Calend 01'!C5),6)=0),(((105-'V06 Calend 01'!C5)/6)<='V06 Calend 01'!E5)),IF((105=('V06 Calend 01'!C5+(6*'V06 Calend 01'!E5))),('V06 Calend 01'!H5-('V06 Calend 01'!I5*('V06 Calend 01'!E5-1))),'V06 Calend 01'!I5),0))+IF((105='V06 Calend 01'!D5),'V06 Calend 01'!J5,0)) -> 0 | DN5: =((IF((106='V06 Calend 01'!C5),('V06 Calend 01'!F5+'V06 Calend 01'!G5),0)+IF(AND(('V06 Calend 01'!E5>0),(106>'V06 Calend 01'!C5),(106<'V06 Calend 01'!D5),(MOD((106-'V06 Calend 01'!C5),6)=0),(((106-'V06 Calend 01'!C5)/6)<='V06 Calend 01'!E5)),IF((106=('V06 Calend 01'!C5+(6*'V06 Calend 01'!E5))),('V06 Calend 01'!H5-('V06 Calend 01'!I5*('V06 Calend 01'!E5-1))),'V06 Calend 01'!I5),0))+IF((106='V06 Calend 01'!D5),'V06 Calend 01'!J5,0)) -> 0 | DO5: =((IF((107='V06 Calend 01'!C5),('V06 Calend 01'!F5+'V06 Calend 01'!G5),0)+IF(AND(('V06 Calend 01'!E5>0),(107>'V06 Calend 01'!C5),(107<'V06 Calend 01'!D5),(MOD((107-'V06 Calend 01'!C5),6)=0),(((107-'V06 Calend 01'!C5)/6)<='V06 Calend 01'!E5)),IF((107=('V06 Calend 01'!C5+(6*'V06 Calend 01'!E5))),('V06 Calend 01'!H5-('V06 Calend 01'!I5*('V06 Calend 01'!E5-1))),'V06 Calend 01'!I5),0))+IF((107='V06 Calend 01'!D5),'V06 Calend 01'!J5,0)) -> 0 | DP5: =((IF((108='V06 Calend 01'!C5),('V06 Calend 01'!F5+'V06 Calend 01'!G5),0)+IF(AND(('V06 Calend 01'!E5>0),(108>'V06 Calend 01'!C5),(108<'V06 Calend 01'!D5),(MOD((108-'V06 Calend 01'!C5),6)=0),(((108-'V06 Calend 01'!C5)/6)<='V06 Calend 01'!E5)),IF((108=('V06 Calend 01'!C5+(6*'V06 Calend 01'!E5))),('V06 Calend 01'!H5-('V06 Calend 01'!I5*('V06 Calend 01'!E5-1))),'V06 Calend 01'!I5),0))+IF((108='V06 Calend 01'!D5),'V06 Calend 01'!J5,0)) -> 0 | DQ5: =((IF((109='V06 Calend 01'!C5),('V06 Calend 01'!F5+'V06 Calend 01'!G5),0)+IF(AND(('V06 Calend 01'!E5>0),(109>'V06 Calend 01'!C5),(109<'V06 Calend 01'!D5),(MOD((109-'V06 Calend 01'!C5),6)=0),(((109-'V06 Calend 01'!C5)/6)<='V06 Calend 01'!E5)),IF((109=('V06 Calend 01'!C5+(6*'V06 Calend 01'!E5))),('V06 Calend 01'!H5-('V06 Calend 01'!I5*('V06 Calend 01'!E5-1))),'V06 Calend 01'!I5),0))+IF((109='V06 Calend 01'!D5),'V06 Calend 01'!J5,0)) -> 0 | DR5: =((IF((110='V06 Calend 01'!C5),('V06 Calend 01'!F5+'V06 Calend 01'!G5),0)+IF(AND(('V06 Calend 01'!E5>0),(110>'V06 Calend 01'!C5),(110<'V06 Calend 01'!D5),(MOD((110-'V06 Calend 01'!C5),6)=0),(((110-'V06 Calend 01'!C5)/6)<='V06 Calend 01'!E5)),IF((110=('V06 Calend 01'!C5+(6*'V06 Calend 01'!E5))),('V06 Calend 01'!H5-('V06 Calend 01'!I5*('V06 Calend 01'!E5-1))),'V06 Calend 01'!I5),0))+IF((110='V06 Calend 01'!D5),'V06 Calend 01'!J5,0)) -> 0 | DS5: =((IF((111='V06 Calend 01'!C5),('V06 Calend 01'!F5+'V06 Calend 01'!G5),0)+IF(AND(('V06 Calend 01'!E5>0),(111>'V06 Calend 01'!C5),(111<'V06 Calend 01'!D5),(MOD((111-'V06 Calend 01'!C5),6)=0),(((111-'V06 Calend 01'!C5)/6)<='V06 Calend 01'!E5)),IF((111=('V06 Calend 01'!C5+(6*'V06 Calend 01'!E5))),('V06 Calend 01'!H5-('V06 Calend 01'!I5*('V06 Calend 01'!E5-1))),'V06 Calend 01'!I5),0))+IF((111='V06 Calend 01'!D5),'V06 Calend 01'!J5,0)) -> 0 | DT5: =((IF((112='V06 Calend 01'!C5),('V06 Calend 01'!F5+'V06 Calend 01'!G5),0)+IF(AND(('V06 Calend 01'!E5>0),(112>'V06 Calend 01'!C5),(112<'V06 Calend 01'!D5),(MOD((112-'V06 Calend 01'!C5),6)=0),(((112-'V06 Calend 01'!C5)/6)<='V06 Calend 01'!E5)),IF((112=('V06 Calend 01'!C5+(6*'V06 Calend 01'!E5))),('V06 Calend 01'!H5-('V06 Calend 01'!I5*('V06 Calend 01'!E5-1))),'V06 Calend 01'!I5),0))+IF((112='V06 Calend 01'!D5),'V06 Calend 01'!J5,0)) -> 0 | DU5: =((IF((113='V06 Calend 01'!C5),('V06 Calend 01'!F5+'V06 Calend 01'!G5),0)+IF(AND(('V06 Calend 01'!E5>0),(113>'V06 Calend 01'!C5),(113<'V06 Calend 01'!D5),(MOD((113-'V06 Calend 01'!C5),6)=0),(((113-'V06 Calend 01'!C5)/6)<='V06 Calend 01'!E5)),IF((113=('V06 Calend 01'!C5+(6*'V06 Calend 01'!E5))),('V06 Calend 01'!H5-('V06 Calend 01'!I5*('V06 Calend 01'!E5-1))),'V06 Calend 01'!I5),0))+IF((113='V06 Calend 01'!D5),'V06 Calend 01'!J5,0)) -> 0 | DV5: =((IF((114='V06 Calend 01'!C5),('V06 Calend 01'!F5+'V06 Calend 01'!G5),0)+IF(AND(('V06 Calend 01'!E5>0),(114>'V06 Calend 01'!C5),(114<'V06 Calend 01'!D5),(MOD((114-'V06 Calend 01'!C5),6)=0),(((114-'V06 Calend 01'!C5)/6)<='V06 Calend 01'!E5)),IF((114=('V06 Calend 01'!C5+(6*'V06 Calend 01'!E5))),('V06 Calend 01'!H5-('V06 Calend 01'!I5*('V06 Calend 01'!E5-1))),'V06 Calend 01'!I5),0))+IF((114='V06 Calend 01'!D5),'V06 Calend 01'!J5,0)) -> 0 | DW5: =((IF((115='V06 Calend 01'!C5),('V06 Calend 01'!F5+'V06 Calend 01'!G5),0)+IF(AND(('V06 Calend 01'!E5>0),(115>'V06 Calend 01'!C5),(115<'V06 Calend 01'!D5),(MOD((115-'V06 Calend 01'!C5),6)=0),(((115-'V06 Calend 01'!C5)/6)<='V06 Calend 01'!E5)),IF((115=('V06 Calend 01'!C5+(6*'V06 Calend 01'!E5))),('V06 Calend 01'!H5-('V06 Calend 01'!I5*('V06 Calend 01'!E5-1))),'V06 Calend 01'!I5),0))+IF((115='V06 Calend 01'!D5),'V06 Calend 01'!J5,0)) -> 0 | DX5: =((IF((116='V06 Calend 01'!C5),('V06 Calend 01'!F5+'V06 Calend 01'!G5),0)+IF(AND(('V06 Calend 01'!E5>0),(116>'V06 Calend 01'!C5),(116<'V06 Calend 01'!D5),(MOD((116-'V06 Calend 01'!C5),6)=0),(((116-'V06 Calend 01'!C5)/6)<='V06 Calend 01'!E5)),IF((116=('V06 Calend 01'!C5+(6*'V06 Calend 01'!E5))),('V06 Calend 01'!H5-('V06 Calend 01'!I5*('V06 Calend 01'!E5-1))),'V06 Calend 01'!I5),0))+IF((116='V06 Calend 01'!D5),'V06 Calend 01'!J5,0)) -> 0 | DY5: =((IF((117='V06 Calend 01'!C5),('V06 Calend 01'!F5+'V06 Calend 01'!G5),0)+IF(AND(('V06 Calend 01'!E5>0),(117>'V06 Calend 01'!C5),(117<'V06 Calend 01'!D5),(MOD((117-'V06 Calend 01'!C5),6)=0),(((117-'V06 Calend 01'!C5)/6)<='V06 Calend 01'!E5)),IF((117=('V06 Calend 01'!C5+(6*'V06 Calend 01'!E5))),('V06 Calend 01'!H5-('V06 Calend 01'!I5*('V06 Calend 01'!E5-1))),'V06 Calend 01'!I5),0))+IF((117='V06 Calend 01'!D5),'V06 Calend 01'!J5,0)) -> 0 | DZ5: =((IF((118='V06 Calend 01'!C5),('V06 Calend 01'!F5+'V06 Calend 01'!G5),0)+IF(AND(('V06 Calend 01'!E5>0),(118>'V06 Calend 01'!C5),(118<'V06 Calend 01'!D5),(MOD((118-'V06 Calend 01'!C5),6)=0),(((118-'V06 Calend 01'!C5)/6)<='V06 Calend 01'!E5)),IF((118=('V06 Calend 01'!C5+(6*'V06 Calend 01'!E5))),('V06 Calend 01'!H5-('V06 Calend 01'!I5*('V06 Calend 01'!E5-1))),'V06 Calend 01'!I5),0))+IF((118='V06 Calend 01'!D5),'V06 Calend 01'!J5,0)) -> 0 | EA5: =((IF((119='V06 Calend 01'!C5),('V06 Calend 01'!F5+'V06 Calend 01'!G5),0)+IF(AND(('V06 Calend 01'!E5>0),(119>'V06 Calend 01'!C5),(119<'V06 Calend 01'!D5),(MOD((119-'V06 Calend 01'!C5),6)=0),(((119-'V06 Calend 01'!C5)/6)<='V06 Calend 01'!E5)),IF((119=('V06 Calend 01'!C5+(6*'V06 Calend 01'!E5))),('V06 Calend 01'!H5-('V06 Calend 01'!I5*('V06 Calend 01'!E5-1))),'V06 Calend 01'!I5),0))+IF((119='V06 Calend 01'!D5),'V06 Calend 01'!J5,0)) -> 0 | EB5: =((IF((120='V06 Calend 01'!C5),('V06 Calend 01'!F5+'V06 Calend 01'!G5),0)+IF(AND(('V06 Calend 01'!E5>0),(120>'V06 Calend 01'!C5),(120<'V06 Calend 01'!D5),(MOD((120-'V06 Calend 01'!C5),6)=0),(((120-'V06 Calend 01'!C5)/6)<='V06 Calend 01'!E5)),IF((120=('V06 Calend 01'!C5+(6*'V06 Calend 01'!E5))),('V06 Calend 01'!H5-('V06 Calend 01'!I5*('V06 Calend 01'!E5-1))),'V06 Calend 01'!I5),0))+IF((120='V06 Calend 01'!D5),'V06 Calend 01'!J5,0)) -> 0 | EC5: =((IF((121='V06 Calend 01'!C5),('V06 Calend 01'!F5+'V06 Calend 01'!G5),0)+IF(AND(('V06 Calend 01'!E5>0),(121>'V06 Calend 01'!C5),(121<'V06 Calend 01'!D5),(MOD((121-'V06 Calend 01'!C5),6)=0),(((121-'V06 Calend 01'!C5)/6)<='V06 Calend 01'!E5)),IF((121=('V06 Calend 01'!C5+(6*'V06 Calend 01'!E5))),('V06 Calend 01'!H5-('V06 Calend 01'!I5*('V06 Calend 01'!E5-1))),'V06 Calend 01'!I5),0))+IF((121='V06 Calend 01'!D5),'V06 Calend 01'!J5,0)) -> 0 | ED5: =((IF((122='V06 Calend 01'!C5),('V06 Calend 01'!F5+'V06 Calend 01'!G5),0)+IF(AND(('V06 Calend 01'!E5>0),(122>'V06 Calend 01'!C5),(122<'V06 Calend 01'!D5),(MOD((122-'V06 Calend 01'!C5),6)=0),(((122-'V06 Calend 01'!C5)/6)<='V06 Calend 01'!E5)),IF((122=('V06 Calend 01'!C5+(6*'V06 Calend 01'!E5))),('V06 Calend 01'!H5-('V06 Calend 01'!I5*('V06 Calend 01'!E5-1))),'V06 Calend 01'!I5),0))+IF((122='V06 Calend 01'!D5),'V06 Calend 01'!J5,0)) -> 0 | EE5: =((IF((123='V06 Calend 01'!C5),('V06 Calend 01'!F5+'V06 Calend 01'!G5),0)+IF(AND(('V06 Calend 01'!E5>0),(123>'V06 Calend 01'!C5),(123<'V06 Calend 01'!D5),(MOD((123-'V06 Calend 01'!C5),6)=0),(((123-'V06 Calend 01'!C5)/6)<='V06 Calend 01'!E5)),IF((123=('V06 Calend 01'!C5+(6*'V06 Calend 01'!E5))),('V06 Calend 01'!H5-('V06 Calend 01'!I5*('V06 Calend 01'!E5-1))),'V06 Calend 01'!I5),0))+IF((123='V06 Calend 01'!D5),'V06 Calend 01'!J5,0)) -> 0 | EF5: =((IF((124='V06 Calend 01'!C5),('V06 Calend 01'!F5+'V06 Calend 01'!G5),0)+IF(AND(('V06 Calend 01'!E5>0),(124>'V06 Calend 01'!C5),(124<'V06 Calend 01'!D5),(MOD((124-'V06 Calend 01'!C5),6)=0),(((124-'V06 Calend 01'!C5)/6)<='V06 Calend 01'!E5)),IF((124=('V06 Calend 01'!C5+(6*'V06 Calend 01'!E5))),('V06 Calend 01'!H5-('V06 Calend 01'!I5*('V06 Calend 01'!E5-1))),'V06 Calend 01'!I5),0))+IF((124='V06 Calend 01'!D5),'V06 Calend 01'!J5,0)) -> 0 | EG5: =((IF((125='V06 Calend 01'!C5),('V06 Calend 01'!F5+'V06 Calend 01'!G5),0)+IF(AND(('V06 Calend 01'!E5>0),(125>'V06 Calend 01'!C5),(125<'V06 Calend 01'!D5),(MOD((125-'V06 Calend 01'!C5),6)=0),(((125-'V06 Calend 01'!C5)/6)<='V06 Calend 01'!E5)),IF((125=('V06 Calend 01'!C5+(6*'V06 Calend 01'!E5))),('V06 Calend 01'!H5-('V06 Calend 01'!I5*('V06 Calend 01'!E5-1))),'V06 Calend 01'!I5),0))+IF((125='V06 Calend 01'!D5),'V06 Calend 01'!J5,0)) -> 0 | EH5: =((IF((126='V06 Calend 01'!C5),('V06 Calend 01'!F5+'V06 Calend 01'!G5),0)+IF(AND(('V06 Calend 01'!E5>0),(126>'V06 Calend 01'!C5),(126<'V06 Calend 01'!D5),(MOD((126-'V06 Calend 01'!C5),6)=0),(((126-'V06 Calend 01'!C5)/6)<='V06 Calend 01'!E5)),IF((126=('V06 Calend 01'!C5+(6*'V06 Calend 01'!E5))),('V06 Calend 01'!H5-('V06 Calend 01'!I5*('V06 Calend 01'!E5-1))),'V06 Calend 01'!I5),0))+IF((126='V06 Calend 01'!D5),'V06 Calend 01'!J5,0)) -> 0 | EI5: =((IF((127='V06 Calend 01'!C5),('V06 Calend 01'!F5+'V06 Calend 01'!G5),0)+IF(AND(('V06 Calend 01'!E5>0),(127>'V06 Calend 01'!C5),(127<'V06 Calend 01'!D5),(MOD((127-'V06 Calend 01'!C5),6)=0),(((127-'V06 Calend 01'!C5)/6)<='V06 Calend 01'!E5)),IF((127=('V06 Calend 01'!C5+(6*'V06 Calend 01'!E5))),('V06 Calend 01'!H5-('V06 Calend 01'!I5*('V06 Calend 01'!E5-1))),'V06 Calend 01'!I5),0))+IF((127='V06 Calend 01'!D5),'V06 Calend 01'!J5,0)) -> 0 | EJ5: =((IF((128='V06 Calend 01'!C5),('V06 Calend 01'!F5+'V06 Calend 01'!G5),0)+IF(AND(('V06 Calend 01'!E5>0),(128>'V06 Calend 01'!C5),(128<'V06 Calend 01'!D5),(MOD((128-'V06 Calend 01'!C5),6)=0),(((128-'V06 Calend 01'!C5)/6)<='V06 Calend 01'!E5)),IF((128=('V06 Calend 01'!C5+(6*'V06 Calend 01'!E5))),('V06 Calend 01'!H5-('V06 Calend 01'!I5*('V06 Calend 01'!E5-1))),'V06 Calend 01'!I5),0))+IF((128='V06 Calend 01'!D5),'V06 Calend 01'!J5,0)) -> 0 | EK5: =((IF((129='V06 Calend 01'!C5),('V06 Calend 01'!F5+'V06 Calend 01'!G5),0)+IF(AND(('V06 Calend 01'!E5>0),(129>'V06 Calend 01'!C5),(129<'V06 Calend 01'!D5),(MOD((129-'V06 Calend 01'!C5),6)=0),(((129-'V06 Calend 01'!C5)/6)<='V06 Calend 01'!E5)),IF((129=('V06 Calend 01'!C5+(6*'V06 Calend 01'!E5))),('V06 Calend 01'!H5-('V06 Calend 01'!I5*('V06 Calend 01'!E5-1))),'V06 Calend 01'!I5),0))+IF((129='V06 Calend 01'!D5),'V06 Calend 01'!J5,0)) -> 0 | EL5: =((IF((130='V06 Calend 01'!C5),('V06 Calend 01'!F5+'V06 Calend 01'!G5),0)+IF(AND(('V06 Calend 01'!E5>0),(130>'V06 Calend 01'!C5),(130<'V06 Calend 01'!D5),(MOD((130-'V06 Calend 01'!C5),6)=0),(((130-'V06 Calend 01'!C5)/6)<='V06 Calend 01'!E5)),IF((130=('V06 Calend 01'!C5+(6*'V06 Calend 01'!E5))),('V06 Calend 01'!H5-('V06 Calend 01'!I5*('V06 Calend 01'!E5-1))),'V06 Calend 01'!I5),0))+IF((130='V06 Calend 01'!D5),'V06 Calend 01'!J5,0)) -> 0 | EM5: =((IF((131='V06 Calend 01'!C5),('V06 Calend 01'!F5+'V06 Calend 01'!G5),0)+IF(AND(('V06 Calend 01'!E5>0),(131>'V06 Calend 01'!C5),(131<'V06 Calend 01'!D5),(MOD((131-'V06 Calend 01'!C5),6)=0),(((131-'V06 Calend 01'!C5)/6)<='V06 Calend 01'!E5)),IF((131=('V06 Calend 01'!C5+(6*'V06 Calend 01'!E5))),('V06 Calend 01'!H5-('V06 Calend 01'!I5*('V06 Calend 01'!E5-1))),'V06 Calend 01'!I5),0))+IF((131='V06 Calend 01'!D5),'V06 Calend 01'!J5,0)) -> 0 | EN5: =((IF((132='V06 Calend 01'!C5),('V06 Calend 01'!F5+'V06 Calend 01'!G5),0)+IF(AND(('V06 Calend 01'!E5>0),(132>'V06 Calend 01'!C5),(132<'V06 Calend 01'!D5),(MOD((132-'V06 Calend 01'!C5),6)=0),(((132-'V06 Calend 01'!C5)/6)<='V06 Calend 01'!E5)),IF((132=('V06 Calend 01'!C5+(6*'V06 Calend 01'!E5))),('V06 Calend 01'!H5-('V06 Calend 01'!I5*('V06 Calend 01'!E5-1))),'V06 Calend 01'!I5),0))+IF((132='V06 Calend 01'!D5),'V06 Calend 01'!J5,0)) -> 0 | EO5: =((IF((133='V06 Calend 01'!C5),('V06 Calend 01'!F5+'V06 Calend 01'!G5),0)+IF(AND(('V06 Calend 01'!E5>0),(133>'V06 Calend 01'!C5),(133<'V06 Calend 01'!D5),(MOD((133-'V06 Calend 01'!C5),6)=0),(((133-'V06 Calend 01'!C5)/6)<='V06 Calend 01'!E5)),IF((133=('V06 Calend 01'!C5+(6*'V06 Calend 01'!E5))),('V06 Calend 01'!H5-('V06 Calend 01'!I5*('V06 Calend 01'!E5-1))),'V06 Calend 01'!I5),0))+IF((133='V06 Calend 01'!D5),'V06 Calend 01'!J5,0)) -> 0 | EP5: =((IF((134='V06 Calend 01'!C5),('V06 Calend 01'!F5+'V06 Calend 01'!G5),0)+IF(AND(('V06 Calend 01'!E5>0),(134>'V06 Calend 01'!C5),(134<'V06 Calend 01'!D5),(MOD((134-'V06 Calend 01'!C5),6)=0),(((134-'V06 Calend 01'!C5)/6)<='V06 Calend 01'!E5)),IF((134=('V06 Calend 01'!C5+(6*'V06 Calend 01'!E5))),('V06 Calend 01'!H5-('V06 Calend 01'!I5*('V06 Calend 01'!E5-1))),'V06 Calend 01'!I5),0))+IF((134='V06 Calend 01'!D5),'V06 Calend 01'!J5,0)) -> 0 | EQ5: =((IF((135='V06 Calend 01'!C5),('V06 Calend 01'!F5+'V06 Calend 01'!G5),0)+IF(AND(('V06 Calend 01'!E5>0),(135>'V06 Calend 01'!C5),(135<'V06 Calend 01'!D5),(MOD((135-'V06 Calend 01'!C5),6)=0),(((135-'V06 Calend 01'!C5)/6)<='V06 Calend 01'!E5)),IF((135=('V06 Calend 01'!C5+(6*'V06 Calend 01'!E5))),('V06 Calend 01'!H5-('V06 Calend 01'!I5*('V06 Calend 01'!E5-1))),'V06 Calend 01'!I5),0))+IF((135='V06 Calend 01'!D5),'V06 Calend 01'!J5,0)) -> 0 | ER5: =((IF((136='V06 Calend 01'!C5),('V06 Calend 01'!F5+'V06 Calend 01'!G5),0)+IF(AND(('V06 Calend 01'!E5>0),(136>'V06 Calend 01'!C5),(136<'V06 Calend 01'!D5),(MOD((136-'V06 Calend 01'!C5),6)=0),(((136-'V06 Calend 01'!C5)/6)<='V06 Calend 01'!E5)),IF((136=('V06 Calend 01'!C5+(6*'V06 Calend 01'!E5))),('V06 Calend 01'!H5-('V06 Calend 01'!I5*('V06 Calend 01'!E5-1))),'V06 Calend 01'!I5),0))+IF((136='V06 Calend 01'!D5),'V06 Calend 01'!J5,0)) -> 0 | ES5: =((IF((137='V06 Calend 01'!C5),('V06 Calend 01'!F5+'V06 Calend 01'!G5),0)+IF(AND(('V06 Calend 01'!E5>0),(137>'V06 Calend 01'!C5),(137<'V06 Calend 01'!D5),(MOD((137-'V06 Calend 01'!C5),6)=0),(((137-'V06 Calend 01'!C5)/6)<='V06 Calend 01'!E5)),IF((137=('V06 Calend 01'!C5+(6*'V06 Calend 01'!E5))),('V06 Calend 01'!H5-('V06 Calend 01'!I5*('V06 Calend 01'!E5-1))),'V06 Calend 01'!I5),0))+IF((137='V06 Calend 01'!D5),'V06 Calend 01'!J5,0)) -> 0 | ET5: =((IF((138='V06 Calend 01'!C5),('V06 Calend 01'!F5+'V06 Calend 01'!G5),0)+IF(AND(('V06 Calend 01'!E5>0),(138>'V06 Calend 01'!C5),(138<'V06 Calend 01'!D5),(MOD((138-'V06 Calend 01'!C5),6)=0),(((138-'V06 Calend 01'!C5)/6)<='V06 Calend 01'!E5)),IF((138=('V06 Calend 01'!C5+(6*'V06 Calend 01'!E5))),('V06 Calend 01'!H5-('V06 Calend 01'!I5*('V06 Calend 01'!E5-1))),'V06 Calend 01'!I5),0))+IF((138='V06 Calend 01'!D5),'V06 Calend 01'!J5,0)) -> 0 | EU5: =((IF((139='V06 Calend 01'!C5),('V06 Calend 01'!F5+'V06 Calend 01'!G5),0)+IF(AND(('V06 Calend 01'!E5>0),(139>'V06 Calend 01'!C5),(139<'V06 Calend 01'!D5),(MOD((139-'V06 Calend 01'!C5),6)=0),(((139-'V06 Calend 01'!C5)/6)<='V06 Calend 01'!E5)),IF((139=('V06 Calend 01'!C5+(6*'V06 Calend 01'!E5))),('V06 Calend 01'!H5-('V06 Calend 01'!I5*('V06 Calend 01'!E5-1))),'V06 Calend 01'!I5),0))+IF((139='V06 Calend 01'!D5),'V06 Calend 01'!J5,0)) -> 0 | EV5: =((IF((140='V06 Calend 01'!C5),('V06 Calend 01'!F5+'V06 Calend 01'!G5),0)+IF(AND(('V06 Calend 01'!E5>0),(140>'V06 Calend 01'!C5),(140<'V06 Calend 01'!D5),(MOD((140-'V06 Calend 01'!C5),6)=0),(((140-'V06 Calend 01'!C5)/6)<='V06 Calend 01'!E5)),IF((140=('V06 Calend 01'!C5+(6*'V06 Calend 01'!E5))),('V06 Calend 01'!H5-('V06 Calend 01'!I5*('V06 Calend 01'!E5-1))),'V06 Calend 01'!I5),0))+IF((140='V06 Calend 01'!D5),'V06 Calend 01'!J5,0)) -> 0 | EW5: =((IF((141='V06 Calend 01'!C5),('V06 Calend 01'!F5+'V06 Calend 01'!G5),0)+IF(AND(('V06 Calend 01'!E5>0),(141>'V06 Calend 01'!C5),(141<'V06 Calend 01'!D5),(MOD((141-'V06 Calend 01'!C5),6)=0),(((141-'V06 Calend 01'!C5)/6)<='V06 Calend 01'!E5)),IF((141=('V06 Calend 01'!C5+(6*'V06 Calend 01'!E5))),('V06 Calend 01'!H5-('V06 Calend 01'!I5*('V06 Calend 01'!E5-1))),'V06 Calend 01'!I5),0))+IF((141='V06 Calend 01'!D5),'V06 Calend 01'!J5,0)) -> 0 | EX5: =((IF((142='V06 Calend 01'!C5),('V06 Calend 01'!F5+'V06 Calend 01'!G5),0)+IF(AND(('V06 Calend 01'!E5>0),(142>'V06 Calend 01'!C5),(142<'V06 Calend 01'!D5),(MOD((142-'V06 Calend 01'!C5),6)=0),(((142-'V06 Calend 01'!C5)/6)<='V06 Calend 01'!E5)),IF((142=('V06 Calend 01'!C5+(6*'V06 Calend 01'!E5))),('V06 Calend 01'!H5-('V06 Calend 01'!I5*('V06 Calend 01'!E5-1))),'V06 Calend 01'!I5),0))+IF((142='V06 Calend 01'!D5),'V06 Calend 01'!J5,0)) -> 0 | EY5: =((IF((143='V06 Calend 01'!C5),('V06 Calend 01'!F5+'V06 Calend 01'!G5),0)+IF(AND(('V06 Calend 01'!E5>0),(143>'V06 Calend 01'!C5),(143<'V06 Calend 01'!D5),(MOD((143-'V06 Calend 01'!C5),6)=0),(((143-'V06 Calend 01'!C5)/6)<='V06 Calend 01'!E5)),IF((143=('V06 Calend 01'!C5+(6*'V06 Calend 01'!E5))),('V06 Calend 01'!H5-('V06 Calend 01'!I5*('V06 Calend 01'!E5-1))),'V06 Calend 01'!I5),0))+IF((143='V06 Calend 01'!D5),'V06 Calend 01'!J5,0)) -> 0 | EZ5: =((IF((144='V06 Calend 01'!C5),('V06 Calend 01'!F5+'V06 Calend 01'!G5),0)+IF(AND(('V06 Calend 01'!E5>0),(144>'V06 Calend 01'!C5),(144<'V06 Calend 01'!D5),(MOD((144-'V06 Calend 01'!C5),6)=0),(((144-'V06 Calend 01'!C5)/6)<='V06 Calend 01'!E5)),IF((144=('V06 Calend 01'!C5+(6*'V06 Calend 01'!E5))),('V06 Calend 01'!H5-('V06 Calend 01'!I5*('V06 Calend 01'!E5-1))),'V06 Calend 01'!I5),0))+IF((144='V06 Calend 01'!D5),'V06 Calend 01'!J5,0)) -> 0 | FA5: =((IF((145='V06 Calend 01'!C5),('V06 Calend 01'!F5+'V06 Calend 01'!G5),0)+IF(AND(('V06 Calend 01'!E5>0),(145>'V06 Calend 01'!C5),(145<'V06 Calend 01'!D5),(MOD((145-'V06 Calend 01'!C5),6)=0),(((145-'V06 Calend 01'!C5)/6)<='V06 Calend 01'!E5)),IF((145=('V06 Calend 01'!C5+(6*'V06 Calend 01'!E5))),('V06 Calend 01'!H5-('V06 Calend 01'!I5*('V06 Calend 01'!E5-1))),'V06 Calend 01'!I5),0))+IF((145='V06 Calend 01'!D5),'V06 Calend 01'!J5,0)) -> 0 | FB5: =((IF((146='V06 Calend 01'!C5),('V06 Calend 01'!F5+'V06 Calend 01'!G5),0)+IF(AND(('V06 Calend 01'!E5>0),(146>'V06 Calend 01'!C5),(146<'V06 Calend 01'!D5),(MOD((146-'V06 Calend 01'!C5),6)=0),(((146-'V06 Calend 01'!C5)/6)<='V06 Calend 01'!E5)),IF((146=('V06 Calend 01'!C5+(6*'V06 Calend 01'!E5))),('V06 Calend 01'!H5-('V06 Calend 01'!I5*('V06 Calend 01'!E5-1))),'V06 Calend 01'!I5),0))+IF((146='V06 Calend 01'!D5),'V06 Calend 01'!J5,0)) -> 0 | FC5: =((IF((147='V06 Calend 01'!C5),('V06 Calend 01'!F5+'V06 Calend 01'!G5),0)+IF(AND(('V06 Calend 01'!E5>0),(147>'V06 Calend 01'!C5),(147<'V06 Calend 01'!D5),(MOD((147-'V06 Calend 01'!C5),6)=0),(((147-'V06 Calend 01'!C5)/6)<='V06 Calend 01'!E5)),IF((147=('V06 Calend 01'!C5+(6*'V06 Calend 01'!E5))),('V06 Calend 01'!H5-('V06 Calend 01'!I5*('V06 Calend 01'!E5-1))),'V06 Calend 01'!I5),0))+IF((147='V06 Calend 01'!D5),'V06 Calend 01'!J5,0)) -> 0 | FD5: =((IF((148='V06 Calend 01'!C5),('V06 Calend 01'!F5+'V06 Calend 01'!G5),0)+IF(AND(('V06 Calend 01'!E5>0),(148>'V06 Calend 01'!C5),(148<'V06 Calend 01'!D5),(MOD((148-'V06 Calend 01'!C5),6)=0),(((148-'V06 Calend 01'!C5)/6)<='V06 Calend 01'!E5)),IF((148=('V06 Calend 01'!C5+(6*'V06 Calend 01'!E5))),('V06 Calend 01'!H5-('V06 Calend 01'!I5*('V06 Calend 01'!E5-1))),'V06 Calend 01'!I5),0))+IF((148='V06 Calend 01'!D5),'V06 Calend 01'!J5,0)) -> 0 | FE5: =((IF((149='V06 Calend 01'!C5),('V06 Calend 01'!F5+'V06 Calend 01'!G5),0)+IF(AND(('V06 Calend 01'!E5>0),(149>'V06 Calend 01'!C5),(149<'V06 Calend 01'!D5),(MOD((149-'V06 Calend 01'!C5),6)=0),(((149-'V06 Calend 01'!C5)/6)<='V06 Calend 01'!E5)),IF((149=('V06 Calend 01'!C5+(6*'V06 Calend 01'!E5))),('V06 Calend 01'!H5-('V06 Calend 01'!I5*('V06 Calend 01'!E5-1))),'V06 Calend 01'!I5),0))+IF((149='V06 Calend 01'!D5),'V06 Calend 01'!J5,0)) -> 0 | FF5: =((IF((150='V06 Calend 01'!C5),('V06 Calend 01'!F5+'V06 Calend 01'!G5),0)+IF(AND(('V06 Calend 01'!E5>0),(150>'V06 Calend 01'!C5),(150<'V06 Calend 01'!D5),(MOD((150-'V06 Calend 01'!C5),6)=0),(((150-'V06 Calend 01'!C5)/6)<='V06 Calend 01'!E5)),IF((150=('V06 Calend 01'!C5+(6*'V06 Calend 01'!E5))),('V06 Calend 01'!H5-('V06 Calend 01'!I5*('V06 Calend 01'!E5-1))),'V06 Calend 01'!I5),0))+IF((150='V06 Calend 01'!D5),'V06 Calend 01'!J5,0)) -> 0 | FG5: =((IF((151='V06 Calend 01'!C5),('V06 Calend 01'!F5+'V06 Calend 01'!G5),0)+IF(AND(('V06 Calend 01'!E5>0),(151>'V06 Calend 01'!C5),(151<'V06 Calend 01'!D5),(MOD((151-'V06 Calend 01'!C5),6)=0),(((151-'V06 Calend 01'!C5)/6)<='V06 Calend 01'!E5)),IF((151=('V06 Calend 01'!C5+(6*'V06 Calend 01'!E5))),('V06 Calend 01'!H5-('V06 Calend 01'!I5*('V06 Calend 01'!E5-1))),'V06 Calend 01'!I5),0))+IF((151='V06 Calend 01'!D5),'V06 Calend 01'!J5,0)) -> 0 | FH5: =((IF((152='V06 Calend 01'!C5),('V06 Calend 01'!F5+'V06 Calend 01'!G5),0)+IF(AND(('V06 Calend 01'!E5>0),(152>'V06 Calend 01'!C5),(152<'V06 Calend 01'!D5),(MOD((152-'V06 Calend 01'!C5),6)=0),(((152-'V06 Calend 01'!C5)/6)<='V06 Calend 01'!E5)),IF((152=('V06 Calend 01'!C5+(6*'V06 Calend 01'!E5))),('V06 Calend 01'!H5-('V06 Calend 01'!I5*('V06 Calend 01'!E5-1))),'V06 Calend 01'!I5),0))+IF((152='V06 Calend 01'!D5),'V06 Calend 01'!J5,0)) -> 0 | FI5: =((IF((153='V06 Calend 01'!C5),('V06 Calend 01'!F5+'V06 Calend 01'!G5),0)+IF(AND(('V06 Calend 01'!E5>0),(153>'V06 Calend 01'!C5),(153<'V06 Calend 01'!D5),(MOD((153-'V06 Calend 01'!C5),6)=0),(((153-'V06 Calend 01'!C5)/6)<='V06 Calend 01'!E5)),IF((153=('V06 Calend 01'!C5+(6*'V06 Calend 01'!E5))),('V06 Calend 01'!H5-('V06 Calend 01'!I5*('V06 Calend 01'!E5-1))),'V06 Calend 01'!I5),0))+IF((153='V06 Calend 01'!D5),'V06 Calend 01'!J5,0)) -> 0 | FJ5: =((IF((154='V06 Calend 01'!C5),('V06 Calend 01'!F5+'V06 Calend 01'!G5),0)+IF(AND(('V06 Calend 01'!E5>0),(154>'V06 Calend 01'!C5),(154<'V06 Calend 01'!D5),(MOD((154-'V06 Calend 01'!C5),6)=0),(((154-'V06 Calend 01'!C5)/6)<='V06 Calend 01'!E5)),IF((154=('V06 Calend 01'!C5+(6*'V06 Calend 01'!E5))),('V06 Calend 01'!H5-('V06 Calend 01'!I5*('V06 Calend 01'!E5-1))),'V06 Calend 01'!I5),0))+IF((154='V06 Calend 01'!D5),'V06 Calend 01'!J5,0)) -> 0 | FK5: =((IF((155='V06 Calend 01'!C5),('V06 Calend 01'!F5+'V06 Calend 01'!G5),0)+IF(AND(('V06 Calend 01'!E5>0),(155>'V06 Calend 01'!C5),(155<'V06 Calend 01'!D5),(MOD((155-'V06 Calend 01'!C5),6)=0),(((155-'V06 Calend 01'!C5)/6)<='V06 Calend 01'!E5)),IF((155=('V06 Calend 01'!C5+(6*'V06 Calend 01'!E5))),('V06 Calend 01'!H5-('V06 Calend 01'!I5*('V06 Calend 01'!E5-1))),'V06 Calend 01'!I5),0))+IF((155='V06 Calend 01'!D5),'V06 Calend 01'!J5,0)) -> 0 | FL5: =((IF((156='V06 Calend 01'!C5),('V06 Calend 01'!F5+'V06 Calend 01'!G5),0)+IF(AND(('V06 Calend 01'!E5>0),(156>'V06 Calend 01'!C5),(156<'V06 Calend 01'!D5),(MOD((156-'V06 Calend 01'!C5),6)=0),(((156-'V06 Calend 01'!C5)/6)<='V06 Calend 01'!E5)),IF((156=('V06 Calend 01'!C5+(6*'V06 Calend 01'!E5))),('V06 Calend 01'!H5-('V06 Calend 01'!I5*('V06 Calend 01'!E5-1))),'V06 Calend 01'!I5),0))+IF((156='V06 Calend 01'!D5),'V06 Calend 01'!J5,0)) -> 0 | FM5: =((IF((157='V06 Calend 01'!C5),('V06 Calend 01'!F5+'V06 Calend 01'!G5),0)+IF(AND(('V06 Calend 01'!E5>0),(157>'V06 Calend 01'!C5),(157<'V06 Calend 01'!D5),(MOD((157-'V06 Calend 01'!C5),6)=0),(((157-'V06 Calend 01'!C5)/6)<='V06 Calend 01'!E5)),IF((157=('V06 Calend 01'!C5+(6*'V06 Calend 01'!E5))),('V06 Calend 01'!H5-('V06 Calend 01'!I5*('V06 Calend 01'!E5-1))),'V06 Calend 01'!I5),0))+IF((157='V06 Calend 01'!D5),'V06 Calend 01'!J5,0)) -> 0 | FN5: =((IF((158='V06 Calend 01'!C5),('V06 Calend 01'!F5+'V06 Calend 01'!G5),0)+IF(AND(('V06 Calend 01'!E5>0),(158>'V06 Calend 01'!C5),(158<'V06 Calend 01'!D5),(MOD((158-'V06 Calend 01'!C5),6)=0),(((158-'V06 Calend 01'!C5)/6)<='V06 Calend 01'!E5)),IF((158=('V06 Calend 01'!C5+(6*'V06 Calend 01'!E5))),('V06 Calend 01'!H5-('V06 Calend 01'!I5*('V06 Calend 01'!E5-1))),'V06 Calend 01'!I5),0))+IF((158='V06 Calend 01'!D5),'V06 Calend 01'!J5,0)) -> 0 | FO5: =((IF((159='V06 Calend 01'!C5),('V06 Calend 01'!F5+'V06 Calend 01'!G5),0)+IF(AND(('V06 Calend 01'!E5>0),(159>'V06 Calend 01'!C5),(159<'V06 Calend 01'!D5),(MOD((159-'V06 Calend 01'!C5),6)=0),(((159-'V06 Calend 01'!C5)/6)<='V06 Calend 01'!E5)),IF((159=('V06 Calend 01'!C5+(6*'V06 Calend 01'!E5))),('V06 Calend 01'!H5-('V06 Calend 01'!I5*('V06 Calend 01'!E5-1))),'V06 Calend 01'!I5),0))+IF((159='V06 Calend 01'!D5),'V06 Calend 01'!J5,0)) -> 0 | FP5: =((IF((160='V06 Calend 01'!C5),('V06 Calend 01'!F5+'V06 Calend 01'!G5),0)+IF(AND(('V06 Calend 01'!E5>0),(160>'V06 Calend 01'!C5),(160<'V06 Calend 01'!D5),(MOD((160-'V06 Calend 01'!C5),6)=0),(((160-'V06 Calend 01'!C5)/6)<='V06 Calend 01'!E5)),IF((160=('V06 Calend 01'!C5+(6*'V06 Calend 01'!E5))),('V06 Calend 01'!H5-('V06 Calend 01'!I5*('V06 Calend 01'!E5-1))),'V06 Calend 01'!I5),0))+IF((160='V06 Calend 01'!D5),'V06 Calend 01'!J5,0)) -> 0 | FQ5: =((IF((161='V06 Calend 01'!C5),('V06 Calend 01'!F5+'V06 Calend 01'!G5),0)+IF(AND(('V06 Calend 01'!E5>0),(161>'V06 Calend 01'!C5),(161<'V06 Calend 01'!D5),(MOD((161-'V06 Calend 01'!C5),6)=0),(((161-'V06 Calend 01'!C5)/6)<='V06 Calend 01'!E5)),IF((161=('V06 Calend 01'!C5+(6*'V06 Calend 01'!E5))),('V06 Calend 01'!H5-('V06 Calend 01'!I5*('V06 Calend 01'!E5-1))),'V06 Calend 01'!I5),0))+IF((161='V06 Calend 01'!D5),'V06 Calend 01'!J5,0)) -> 0 | FR5: =((IF((162='V06 Calend 01'!C5),('V06 Calend 01'!F5+'V06 Calend 01'!G5),0)+IF(AND(('V06 Calend 01'!E5>0),(162>'V06 Calend 01'!C5),(162<'V06 Calend 01'!D5),(MOD((162-'V06 Calend 01'!C5),6)=0),(((162-'V06 Calend 01'!C5)/6)<='V06 Calend 01'!E5)),IF((162=('V06 Calend 01'!C5+(6*'V06 Calend 01'!E5))),('V06 Calend 01'!H5-('V06 Calend 01'!I5*('V06 Calend 01'!E5-1))),'V06 Calend 01'!I5),0))+IF((162='V06 Calend 01'!D5),'V06 Calend 01'!J5,0)) -> 0 | FS5: =((IF((163='V06 Calend 01'!C5),('V06 Calend 01'!F5+'V06 Calend 01'!G5),0)+IF(AND(('V06 Calend 01'!E5>0),(163>'V06 Calend 01'!C5),(163<'V06 Calend 01'!D5),(MOD((163-'V06 Calend 01'!C5),6)=0),(((163-'V06 Calend 01'!C5)/6)<='V06 Calend 01'!E5)),IF((163=('V06 Calend 01'!C5+(6*'V06 Calend 01'!E5))),('V06 Calend 01'!H5-('V06 Calend 01'!I5*('V06 Calend 01'!E5-1))),'V06 Calend 01'!I5),0))+IF((163='V06 Calend 01'!D5),'V06 Calend 01'!J5,0)) -> 0 | FT5: =((IF((164='V06 Calend 01'!C5),('V06 Calend 01'!F5+'V06 Calend 01'!G5),0)+IF(AND(('V06 Calend 01'!E5>0),(164>'V06 Calend 01'!C5),(164<'V06 Calend 01'!D5),(MOD((164-'V06 Calend 01'!C5),6)=0),(((164-'V06 Calend 01'!C5)/6)<='V06 Calend 01'!E5)),IF((164=('V06 Calend 01'!C5+(6*'V06 Calend 01'!E5))),('V06 Calend 01'!H5-('V06 Calend 01'!I5*('V06 Calend 01'!E5-1))),'V06 Calend 01'!I5),0))+IF((164='V06 Calend 01'!D5),'V06 Calend 01'!J5,0)) -> 0 | FU5: =((IF((165='V06 Calend 01'!C5),('V06 Calend 01'!F5+'V06 Calend 01'!G5),0)+IF(AND(('V06 Calend 01'!E5>0),(165>'V06 Calend 01'!C5),(165<'V06 Calend 01'!D5),(MOD((165-'V06 Calend 01'!C5),6)=0),(((165-'V06 Calend 01'!C5)/6)<='V06 Calend 01'!E5)),IF((165=('V06 Calend 01'!C5+(6*'V06 Calend 01'!E5))),('V06 Calend 01'!H5-('V06 Calend 01'!I5*('V06 Calend 01'!E5-1))),'V06 Calend 01'!I5),0))+IF((165='V06 Calend 01'!D5),'V06 Calend 01'!J5,0)) -> 0 | FV5: =((IF((166='V06 Calend 01'!C5),('V06 Calend 01'!F5+'V06 Calend 01'!G5),0)+IF(AND(('V06 Calend 01'!E5>0),(166>'V06 Calend 01'!C5),(166<'V06 Calend 01'!D5),(MOD((166-'V06 Calend 01'!C5),6)=0),(((166-'V06 Calend 01'!C5)/6)<='V06 Calend 01'!E5)),IF((166=('V06 Calend 01'!C5+(6*'V06 Calend 01'!E5))),('V06 Calend 01'!H5-('V06 Calend 01'!I5*('V06 Calend 01'!E5-1))),'V06 Calend 01'!I5),0))+IF((166='V06 Calend 01'!D5),'V06 Calend 01'!J5,0)) -> 0 | FW5: =((IF((167='V06 Calend 01'!C5),('V06 Calend 01'!F5+'V06 Calend 01'!G5),0)+IF(AND(('V06 Calend 01'!E5>0),(167>'V06 Calend 01'!C5),(167<'V06 Calend 01'!D5),(MOD((167-'V06 Calend 01'!C5),6)=0),(((167-'V06 Calend 01'!C5)/6)<='V06 Calend 01'!E5)),IF((167=('V06 Calend 01'!C5+(6*'V06 Calend 01'!E5))),('V06 Calend 01'!H5-('V06 Calend 01'!I5*('V06 Calend 01'!E5-1))),'V06 Calend 01'!I5),0))+IF((167='V06 Calend 01'!D5),'V06 Calend 01'!J5,0)) -> 0 | FX5: =((IF((168='V06 Calend 01'!C5),('V06 Calend 01'!F5+'V06 Calend 01'!G5),0)+IF(AND(('V06 Calend 01'!E5>0),(168>'V06 Calend 01'!C5),(168<'V06 Calend 01'!D5),(MOD((168-'V06 Calend 01'!C5),6)=0),(((168-'V06 Calend 01'!C5)/6)<='V06 Calend 01'!E5)),IF((168=('V06 Calend 01'!C5+(6*'V06 Calend 01'!E5))),('V06 Calend 01'!H5-('V06 Calend 01'!I5*('V06 Calend 01'!E5-1))),'V06 Calend 01'!I5),0))+IF((168='V06 Calend 01'!D5),'V06 Calend 01'!J5,0)) -> 0 | FY5: =((IF((169='V06 Calend 01'!C5),('V06 Calend 01'!F5+'V06 Calend 01'!G5),0)+IF(AND(('V06 Calend 01'!E5>0),(169>'V06 Calend 01'!C5),(169<'V06 Calend 01'!D5),(MOD((169-'V06 Calend 01'!C5),6)=0),(((169-'V06 Calend 01'!C5)/6)<='V06 Calend 01'!E5)),IF((169=('V06 Calend 01'!C5+(6*'V06 Calend 01'!E5))),('V06 Calend 01'!H5-('V06 Calend 01'!I5*('V06 Calend 01'!E5-1))),'V06 Calend 01'!I5),0))+IF((169='V06 Calend 01'!D5),'V06 Calend 01'!J5,0)) -> 0 | FZ5: =((IF((170='V06 Calend 01'!C5),('V06 Calend 01'!F5+'V06 Calend 01'!G5),0)+IF(AND(('V06 Calend 01'!E5>0),(170>'V06 Calend 01'!C5),(170<'V06 Calend 01'!D5),(MOD((170-'V06 Calend 01'!C5),6)=0),(((170-'V06 Calend 01'!C5)/6)<='V06 Calend 01'!E5)),IF((170=('V06 Calend 01'!C5+(6*'V06 Calend 01'!E5))),('V06 Calend 01'!H5-('V06 Calend 01'!I5*('V06 Calend 01'!E5-1))),'V06 Calend 01'!I5),0))+IF((170='V06 Calend 01'!D5),'V06 Calend 01'!J5,0)) -> 0 | GA5: =((IF((171='V06 Calend 01'!C5),('V06 Calend 01'!F5+'V06 Calend 01'!G5),0)+IF(AND(('V06 Calend 01'!E5>0),(171>'V06 Calend 01'!C5),(171<'V06 Calend 01'!D5),(MOD((171-'V06 Calend 01'!C5),6)=0),(((171-'V06 Calend 01'!C5)/6)<='V06 Calend 01'!E5)),IF((171=('V06 Calend 01'!C5+(6*'V06 Calend 01'!E5))),('V06 Calend 01'!H5-('V06 Calend 01'!I5*('V06 Calend 01'!E5-1))),'V06 Calend 01'!I5),0))+IF((171='V06 Calend 01'!D5),'V06 Calend 01'!J5,0)) -> 0 | GB5: =((IF((172='V06 Calend 01'!C5),('V06 Calend 01'!F5+'V06 Calend 01'!G5),0)+IF(AND(('V06 Calend 01'!E5>0),(172>'V06 Calend 01'!C5),(172<'V06 Calend 01'!D5),(MOD((172-'V06 Calend 01'!C5),6)=0),(((172-'V06 Calend 01'!C5)/6)<='V06 Calend 01'!E5)),IF((172=('V06 Calend 01'!C5+(6*'V06 Calend 01'!E5))),('V06 Calend 01'!H5-('V06 Calend 01'!I5*('V06 Calend 01'!E5-1))),'V06 Calend 01'!I5),0))+IF((172='V06 Calend 01'!D5),'V06 Calend 01'!J5,0)) -> 0 | GC5: =((IF((173='V06 Calend 01'!C5),('V06 Calend 01'!F5+'V06 Calend 01'!G5),0)+IF(AND(('V06 Calend 01'!E5>0),(173>'V06 Calend 01'!C5),(173<'V06 Calend 01'!D5),(MOD((173-'V06 Calend 01'!C5),6)=0),(((173-'V06 Calend 01'!C5)/6)<='V06 Calend 01'!E5)),IF((173=('V06 Calend 01'!C5+(6*'V06 Calend 01'!E5))),('V06 Calend 01'!H5-('V06 Calend 01'!I5*('V06 Calend 01'!E5-1))),'V06 Calend 01'!I5),0))+IF((173='V06 Calend 01'!D5),'V06 Calend 01'!J5,0)) -> 0 | GD5: =((IF((174='V06 Calend 01'!C5),('V06 Calend 01'!F5+'V06 Calend 01'!G5),0)+IF(AND(('V06 Calend 01'!E5>0),(174>'V06 Calend 01'!C5),(174<'V06 Calend 01'!D5),(MOD((174-'V06 Calend 01'!C5),6)=0),(((174-'V06 Calend 01'!C5)/6)<='V06 Calend 01'!E5)),IF((174=('V06 Calend 01'!C5+(6*'V06 Calend 01'!E5))),('V06 Calend 01'!H5-('V06 Calend 01'!I5*('V06 Calend 01'!E5-1))),'V06 Calend 01'!I5),0))+IF((174='V06 Calend 01'!D5),'V06 Calend 01'!J5,0)) -> 0 | GE5: =((IF((175='V06 Calend 01'!C5),('V06 Calend 01'!F5+'V06 Calend 01'!G5),0)+IF(AND(('V06 Calend 01'!E5>0),(175>'V06 Calend 01'!C5),(175<'V06 Calend 01'!D5),(MOD((175-'V06 Calend 01'!C5),6)=0),(((175-'V06 Calend 01'!C5)/6)<='V06 Calend 01'!E5)),IF((175=('V06 Calend 01'!C5+(6*'V06 Calend 01'!E5))),('V06 Calend 01'!H5-('V06 Calend 01'!I5*('V06 Calend 01'!E5-1))),'V06 Calend 01'!I5),0))+IF((175='V06 Calend 01'!D5),'V06 Calend 01'!J5,0)) -> 0 | GF5: =((IF((176='V06 Calend 01'!C5),('V06 Calend 01'!F5+'V06 Calend 01'!G5),0)+IF(AND(('V06 Calend 01'!E5>0),(176>'V06 Calend 01'!C5),(176<'V06 Calend 01'!D5),(MOD((176-'V06 Calend 01'!C5),6)=0),(((176-'V06 Calend 01'!C5)/6)<='V06 Calend 01'!E5)),IF((176=('V06 Calend 01'!C5+(6*'V06 Calend 01'!E5))),('V06 Calend 01'!H5-('V06 Calend 01'!I5*('V06 Calend 01'!E5-1))),'V06 Calend 01'!I5),0))+IF((176='V06 Calend 01'!D5),'V06 Calend 01'!J5,0)) -> 0 | GG5: =((IF((177='V06 Calend 01'!C5),('V06 Calend 01'!F5+'V06 Calend 01'!G5),0)+IF(AND(('V06 Calend 01'!E5>0),(177>'V06 Calend 01'!C5),(177<'V06 Calend 01'!D5),(MOD((177-'V06 Calend 01'!C5),6)=0),(((177-'V06 Calend 01'!C5)/6)<='V06 Calend 01'!E5)),IF((177=('V06 Calend 01'!C5+(6*'V06 Calend 01'!E5))),('V06 Calend 01'!H5-('V06 Calend 01'!I5*('V06 Calend 01'!E5-1))),'V06 Calend 01'!I5),0))+IF((177='V06 Calend 01'!D5),'V06 Calend 01'!J5,0)) -> 0 | GH5: =((IF((178='V06 Calend 01'!C5),('V06 Calend 01'!F5+'V06 Calend 01'!G5),0)+IF(AND(('V06 Calend 01'!E5>0),(178>'V06 Calend 01'!C5),(178<'V06 Calend 01'!D5),(MOD((178-'V06 Calend 01'!C5),6)=0),(((178-'V06 Calend 01'!C5)/6)<='V06 Calend 01'!E5)),IF((178=('V06 Calend 01'!C5+(6*'V06 Calend 01'!E5))),('V06 Calend 01'!H5-('V06 Calend 01'!I5*('V06 Calend 01'!E5-1))),'V06 Calend 01'!I5),0))+IF((178='V06 Calend 01'!D5),'V06 Calend 01'!J5,0)) -> 0 | GI5: =((IF((179='V06 Calend 01'!C5),('V06 Calend 01'!F5+'V06 Calend 01'!G5),0)+IF(AND(('V06 Calend 01'!E5>0),(179>'V06 Calend 01'!C5),(179<'V06 Calend 01'!D5),(MOD((179-'V06 Calend 01'!C5),6)=0),(((179-'V06 Calend 01'!C5)/6)<='V06 Calend 01'!E5)),IF((179=('V06 Calend 01'!C5+(6*'V06 Calend 01'!E5))),('V06 Calend 01'!H5-('V06 Calend 01'!I5*('V06 Calend 01'!E5-1))),'V06 Calend 01'!I5),0))+IF((179='V06 Calend 01'!D5),'V06 Calend 01'!J5,0)) -> 0 | GJ5: =((IF((180='V06 Calend 01'!C5),('V06 Calend 01'!F5+'V06 Calend 01'!G5),0)+IF(AND(('V06 Calend 01'!E5>0),(180>'V06 Calend 01'!C5),(180<'V06 Calend 01'!D5),(MOD((180-'V06 Calend 01'!C5),6)=0),(((180-'V06 Calend 01'!C5)/6)<='V06 Calend 01'!E5)),IF((180=('V06 Calend 01'!C5+(6*'V06 Calend 01'!E5))),('V06 Calend 01'!H5-('V06 Calend 01'!I5*('V06 Calend 01'!E5-1))),'V06 Calend 01'!I5),0))+IF((180='V06 Calend 01'!D5),'V06 Calend 01'!J5,0)) -> 0
A6: ='V06 Unidades'!$A$6 -> 202 | B6: ='V06 Unidades'!$H$6 -> 402500 | C6: =('V06 Unidades'!$I$6+'V06 Controlos'!$B$37) -> 1 | D6: =IF(('V06 Controlos'!$B$38>0),MAX(('V06 Unidades'!$L$6+'V06 Controlos'!$B$37),(30+'V06 Controlos'!$B$38)),('V06 Unidades'!$L$6+'V06 Controlos'!$B$37)) -> 29 | E6: =MAX(0,INT(((('V06 Calend 01'!D6-'V06 Calend 01'!C6)-1)/6))) -> 4 | F6: =ROUND(('V06 Calend 01'!B6*0.05),2) -> 20125 | G6: =ROUND(('V06 Calend 01'!B6*0.2),2) -> 80500 | H6: =ROUND(('V06 Calend 01'!B6*0.55),2) -> 221375 | I6: =ROUND(('V06 Calend 01'!H6/MAX(1,'V06 Calend 01'!E6)),2) -> 55343.75 | J6: =((('V06 Calend 01'!B6-'V06 Calend 01'!F6)-'V06 Calend 01'!G6)-'V06 Calend 01'!H6) -> 80500 | K6: =('V06 Calend 01'!B6*0.025) -> 10062.5 | L6: Forecast; actual receipts are separate | M6: =((IF((1='V06 Calend 01'!C6),('V06 Calend 01'!F6+'V06 Calend 01'!G6),0)+IF(AND(('V06 Calend 01'!E6>0),(1>'V06 Calend 01'!C6),(1<'V06 Calend 01'!D6),(MOD((1-'V06 Calend 01'!C6),6)=0),(((1-'V06 Calend 01'!C6)/6)<='V06 Calend 01'!E6)),IF((1=('V06 Calend 01'!C6+(6*'V06 Calend 01'!E6))),('V06 Calend 01'!H6-('V06 Calend 01'!I6*('V06 Calend 01'!E6-1))),'V06 Calend 01'!I6),0))+IF((1='V06 Calend 01'!D6),'V06 Calend 01'!J6,0)) -> 100625 | N6: =((IF((2='V06 Calend 01'!C6),('V06 Calend 01'!F6+'V06 Calend 01'!G6),0)+IF(AND(('V06 Calend 01'!E6>0),(2>'V06 Calend 01'!C6),(2<'V06 Calend 01'!D6),(MOD((2-'V06 Calend 01'!C6),6)=0),(((2-'V06 Calend 01'!C6)/6)<='V06 Calend 01'!E6)),IF((2=('V06 Calend 01'!C6+(6*'V06 Calend 01'!E6))),('V06 Calend 01'!H6-('V06 Calend 01'!I6*('V06 Calend 01'!E6-1))),'V06 Calend 01'!I6),0))+IF((2='V06 Calend 01'!D6),'V06 Calend 01'!J6,0)) -> 0 | O6: =((IF((3='V06 Calend 01'!C6),('V06 Calend 01'!F6+'V06 Calend 01'!G6),0)+IF(AND(('V06 Calend 01'!E6>0),(3>'V06 Calend 01'!C6),(3<'V06 Calend 01'!D6),(MOD((3-'V06 Calend 01'!C6),6)=0),(((3-'V06 Calend 01'!C6)/6)<='V06 Calend 01'!E6)),IF((3=('V06 Calend 01'!C6+(6*'V06 Calend 01'!E6))),('V06 Calend 01'!H6-('V06 Calend 01'!I6*('V06 Calend 01'!E6-1))),'V06 Calend 01'!I6),0))+IF((3='V06 Calend 01'!D6),'V06 Calend 01'!J6,0)) -> 0 | P6: =((IF((4='V06 Calend 01'!C6),('V06 Calend 01'!F6+'V06 Calend 01'!G6),0)+IF(AND(('V06 Calend 01'!E6>0),(4>'V06 Calend 01'!C6),(4<'V06 Calend 01'!D6),(MOD((4-'V06 Calend 01'!C6),6)=0),(((4-'V06 Calend 01'!C6)/6)<='V06 Calend 01'!E6)),IF((4=('V06 Calend 01'!C6+(6*'V06 Calend 01'!E6))),('V06 Calend 01'!H6-('V06 Calend 01'!I6*('V06 Calend 01'!E6-1))),'V06 Calend 01'!I6),0))+IF((4='V06 Calend 01'!D6),'V06 Calend 01'!J6,0)) -> 0 | Q6: =((IF((5='V06 Calend 01'!C6),('V06 Calend 01'!F6+'V06 Calend 01'!G6),0)+IF(AND(('V06 Calend 01'!E6>0),(5>'V06 Calend 01'!C6),(5<'V06 Calend 01'!D6),(MOD((5-'V06 Calend 01'!C6),6)=0),(((5-'V06 Calend 01'!C6)/6)<='V06 Calend 01'!E6)),IF((5=('V06 Calend 01'!C6+(6*'V06 Calend 01'!E6))),('V06 Calend 01'!H6-('V06 Calend 01'!I6*('V06 Calend 01'!E6-1))),'V06 Calend 01'!I6),0))+IF((5='V06 Calend 01'!D6),'V06 Calend 01'!J6,0)) -> 0 | R6: =((IF((6='V06 Calend 01'!C6),('V06 Calend 01'!F6+'V06 Calend 01'!G6),0)+IF(AND(('V06 Calend 01'!E6>0),(6>'V06 Calend 01'!C6),(6<'V06 Calend 01'!D6),(MOD((6-'V06 Calend 01'!C6),6)=0),(((6-'V06 Calend 01'!C6)/6)<='V06 Calend 01'!E6)),IF((6=('V06 Calend 01'!C6+(6*'V06 Calend 01'!E6))),('V06 Calend 01'!H6-('V06 Calend 01'!I6*('V06 Calend 01'!E6-1))),'V06 Calend 01'!I6),0))+IF((6='V06 Calend 01'!D6),'V06 Calend 01'!J6,0)) -> 0 | S6: =((IF((7='V06 Calend 01'!C6),('V06 Calend 01'!F6+'V06 Calend 01'!G6),0)+IF(AND(('V06 Calend 01'!E6>0),(7>'V06 Calend 01'!C6),(7<'V06 Calend 01'!D6),(MOD((7-'V06 Calend 01'!C6),6)=0),(((7-'V06 Calend 01'!C6)/6)<='V06 Calend 01'!E6)),IF((7=('V06 Calend 01'!C6+(6*'V06 Calend 01'!E6))),('V06 Calend 01'!H6-('V06 Calend 01'!I6*('V06 Calend 01'!E6-1))),'V06 Calend 01'!I6),0))+IF((7='V06 Calend 01'!D6),'V06 Calend 01'!J6,0)) -> 55343.75 | T6: =((IF((8='V06 Calend 01'!C6),('V06 Calend 01'!F6+'V06 Calend 01'!G6),0)+IF(AND(('V06 Calend 01'!E6>0),(8>'V06 Calend 01'!C6),(8<'V06 Calend 01'!D6),(MOD((8-'V06 Calend 01'!C6),6)=0),(((8-'V06 Calend 01'!C6)/6)<='V06 Calend 01'!E6)),IF((8=('V06 Calend 01'!C6+(6*'V06 Calend 01'!E6))),('V06 Calend 01'!H6-('V06 Calend 01'!I6*('V06 Calend 01'!E6-1))),'V06 Calend 01'!I6),0))+IF((8='V06 Calend 01'!D6),'V06 Calend 01'!J6,0)) -> 0 | U6: =((IF((9='V06 Calend 01'!C6),('V06 Calend 01'!F6+'V06 Calend 01'!G6),0)+IF(AND(('V06 Calend 01'!E6>0),(9>'V06 Calend 01'!C6),(9<'V06 Calend 01'!D6),(MOD((9-'V06 Calend 01'!C6),6)=0),(((9-'V06 Calend 01'!C6)/6)<='V06 Calend 01'!E6)),IF((9=('V06 Calend 01'!C6+(6*'V06 Calend 01'!E6))),('V06 Calend 01'!H6-('V06 Calend 01'!I6*('V06 Calend 01'!E6-1))),'V06 Calend 01'!I6),0))+IF((9='V06 Calend 01'!D6),'V06 Calend 01'!J6,0)) -> 0 | V6: =((IF((10='V06 Calend 01'!C6),('V06 Calend 01'!F6+'V06 Calend 01'!G6),0)+IF(AND(('V06 Calend 01'!E6>0),(10>'V06 Calend 01'!C6),(10<'V06 Calend 01'!D6),(MOD((10-'V06 Calend 01'!C6),6)=0),(((10-'V06 Calend 01'!C6)/6)<='V06 Calend 01'!E6)),IF((10=('V06 Calend 01'!C6+(6*'V06 Calend 01'!E6))),('V06 Calend 01'!H6-('V06 Calend 01'!I6*('V06 Calend 01'!E6-1))),'V06 Calend 01'!I6),0))+IF((10='V06 Calend 01'!D6),'V06 Calend 01'!J6,0)) -> 0 | W6: =((IF((11='V06 Calend 01'!C6),('V06 Calend 01'!F6+'V06 Calend 01'!G6),0)+IF(AND(('V06 Calend 01'!E6>0),(11>'V06 Calend 01'!C6),(11<'V06 Calend 01'!D6),(MOD((11-'V06 Calend 01'!C6),6)=0),(((11-'V06 Calend 01'!C6)/6)<='V06 Calend 01'!E6)),IF((11=('V06 Calend 01'!C6+(6*'V06 Calend 01'!E6))),('V06 Calend 01'!H6-('V06 Calend 01'!I6*('V06 Calend 01'!E6-1))),'V06 Calend 01'!I6),0))+IF((11='V06 Calend 01'!D6),'V06 Calend 01'!J6,0)) -> 0 | X6: =((IF((12='V06 Calend 01'!C6),('V06 Calend 01'!F6+'V06 Calend 01'!G6),0)+IF(AND(('V06 Calend 01'!E6>0),(12>'V06 Calend 01'!C6),(12<'V06 Calend 01'!D6),(MOD((12-'V06 Calend 01'!C6),6)=0),(((12-'V06 Calend 01'!C6)/6)<='V06 Calend 01'!E6)),IF((12=('V06 Calend 01'!C6+(6*'V06 Calend 01'!E6))),('V06 Calend 01'!H6-('V06 Calend 01'!I6*('V06 Calend 01'!E6-1))),'V06 Calend 01'!I6),0))+IF((12='V06 Calend 01'!D6),'V06 Calend 01'!J6,0)) -> 0 | Y6: =((IF((13='V06 Calend 01'!C6),('V06 Calend 01'!F6+'V06 Calend 01'!G6),0)+IF(AND(('V06 Calend 01'!E6>0),(13>'V06 Calend 01'!C6),(13<'V06 Calend 01'!D6),(MOD((13-'V06 Calend 01'!C6),6)=0),(((13-'V06 Calend 01'!C6)/6)<='V06 Calend 01'!E6)),IF((13=('V06 Calend 01'!C6+(6*'V06 Calend 01'!E6))),('V06 Calend 01'!H6-('V06 Calend 01'!I6*('V06 Calend 01'!E6-1))),'V06 Calend 01'!I6),0))+IF((13='V06 Calend 01'!D6),'V06 Calend 01'!J6,0)) -> 55343.75 | Z6: =((IF((14='V06 Calend 01'!C6),('V06 Calend 01'!F6+'V06 Calend 01'!G6),0)+IF(AND(('V06 Calend 01'!E6>0),(14>'V06 Calend 01'!C6),(14<'V06 Calend 01'!D6),(MOD((14-'V06 Calend 01'!C6),6)=0),(((14-'V06 Calend 01'!C6)/6)<='V06 Calend 01'!E6)),IF((14=('V06 Calend 01'!C6+(6*'V06 Calend 01'!E6))),('V06 Calend 01'!H6-('V06 Calend 01'!I6*('V06 Calend 01'!E6-1))),'V06 Calend 01'!I6),0))+IF((14='V06 Calend 01'!D6),'V06 Calend 01'!J6,0)) -> 0 | AA6: =((IF((15='V06 Calend 01'!C6),('V06 Calend 01'!F6+'V06 Calend 01'!G6),0)+IF(AND(('V06 Calend 01'!E6>0),(15>'V06 Calend 01'!C6),(15<'V06 Calend 01'!D6),(MOD((15-'V06 Calend 01'!C6),6)=0),(((15-'V06 Calend 01'!C6)/6)<='V06 Calend 01'!E6)),IF((15=('V06 Calend 01'!C6+(6*'V06 Calend 01'!E6))),('V06 Calend 01'!H6-('V06 Calend 01'!I6*('V06 Calend 01'!E6-1))),'V06 Calend 01'!I6),0))+IF((15='V06 Calend 01'!D6),'V06 Calend 01'!J6,0)) -> 0 | AB6: =((IF((16='V06 Calend 01'!C6),('V06 Calend 01'!F6+'V06 Calend 01'!G6),0)+IF(AND(('V06 Calend 01'!E6>0),(16>'V06 Calend 01'!C6),(16<'V06 Calend 01'!D6),(MOD((16-'V06 Calend 01'!C6),6)=0),(((16-'V06 Calend 01'!C6)/6)<='V06 Calend 01'!E6)),IF((16=('V06 Calend 01'!C6+(6*'V06 Calend 01'!E6))),('V06 Calend 01'!H6-('V06 Calend 01'!I6*('V06 Calend 01'!E6-1))),'V06 Calend 01'!I6),0))+IF((16='V06 Calend 01'!D6),'V06 Calend 01'!J6,0)) -> 0 | AC6: =((IF((17='V06 Calend 01'!C6),('V06 Calend 01'!F6+'V06 Calend 01'!G6),0)+IF(AND(('V06 Calend 01'!E6>0),(17>'V06 Calend 01'!C6),(17<'V06 Calend 01'!D6),(MOD((17-'V06 Calend 01'!C6),6)=0),(((17-'V06 Calend 01'!C6)/6)<='V06 Calend 01'!E6)),IF((17=('V06 Calend 01'!C6+(6*'V06 Calend 01'!E6))),('V06 Calend 01'!H6-('V06 Calend 01'!I6*('V06 Calend 01'!E6-1))),'V06 Calend 01'!I6),0))+IF((17='V06 Calend 01'!D6),'V06 Calend 01'!J6,0)) -> 0 | AD6: =((IF((18='V06 Calend 01'!C6),('V06 Calend 01'!F6+'V06 Calend 01'!G6),0)+IF(AND(('V06 Calend 01'!E6>0),(18>'V06 Calend 01'!C6),(18<'V06 Calend 01'!D6),(MOD((18-'V06 Calend 01'!C6),6)=0),(((18-'V06 Calend 01'!C6)/6)<='V06 Calend 01'!E6)),IF((18=('V06 Calend 01'!C6+(6*'V06 Calend 01'!E6))),('V06 Calend 01'!H6-('V06 Calend 01'!I6*('V06 Calend 01'!E6-1))),'V06 Calend 01'!I6),0))+IF((18='V06 Calend 01'!D6),'V06 Calend 01'!J6,0)) -> 0 | AE6: =((IF((19='V06 Calend 01'!C6),('V06 Calend 01'!F6+'V06 Calend 01'!G6),0)+IF(AND(('V06 Calend 01'!E6>0),(19>'V06 Calend 01'!C6),(19<'V06 Calend 01'!D6),(MOD((19-'V06 Calend 01'!C6),6)=0),(((19-'V06 Calend 01'!C6)/6)<='V06 Calend 01'!E6)),IF((19=('V06 Calend 01'!C6+(6*'V06 Calend 01'!E6))),('V06 Calend 01'!H6-('V06 Calend 01'!I6*('V06 Calend 01'!E6-1))),'V06 Calend 01'!I6),0))+IF((19='V06 Calend 01'!D6),'V06 Calend 01'!J6,0)) -> 55343.75 | AF6: =((IF((20='V06 Calend 01'!C6),('V06 Calend 01'!F6+'V06 Calend 01'!G6),0)+IF(AND(('V06 Calend 01'!E6>0),(20>'V06 Calend 01'!C6),(20<'V06 Calend 01'!D6),(MOD((20-'V06 Calend 01'!C6),6)=0),(((20-'V06 Calend 01'!C6)/6)<='V06 Calend 01'!E6)),IF((20=('V06 Calend 01'!C6+(6*'V06 Calend 01'!E6))),('V06 Calend 01'!H6-('V06 Calend 01'!I6*('V06 Calend 01'!E6-1))),'V06 Calend 01'!I6),0))+IF((20='V06 Calend 01'!D6),'V06 Calend 01'!J6,0)) -> 0 | AG6: =((IF((21='V06 Calend 01'!C6),('V06 Calend 01'!F6+'V06 Calend 01'!G6),0)+IF(AND(('V06 Calend 01'!E6>0),(21>'V06 Calend 01'!C6),(21<'V06 Calend 01'!D6),(MOD((21-'V06 Calend 01'!C6),6)=0),(((21-'V06 Calend 01'!C6)/6)<='V06 Calend 01'!E6)),IF((21=('V06 Calend 01'!C6+(6*'V06 Calend 01'!E6))),('V06 Calend 01'!H6-('V06 Calend 01'!I6*('V06 Calend 01'!E6-1))),'V06 Calend 01'!I6),0))+IF((21='V06 Calend 01'!D6),'V06 Calend 01'!J6,0)) -> 0 | AH6: =((IF((22='V06 Calend 01'!C6),('V06 Calend 01'!F6+'V06 Calend 01'!G6),0)+IF(AND(('V06 Calend 01'!E6>0),(22>'V06 Calend 01'!C6),(22<'V06 Calend 01'!D6),(MOD((22-'V06 Calend 01'!C6),6)=0),(((22-'V06 Calend 01'!C6)/6)<='V06 Calend 01'!E6)),IF((22=('V06 Calend 01'!C6+(6*'V06 Calend 01'!E6))),('V06 Calend 01'!H6-('V06 Calend 01'!I6*('V06 Calend 01'!E6-1))),'V06 Calend 01'!I6),0))+IF((22='V06 Calend 01'!D6),'V06 Calend 01'!J6,0)) -> 0 | AI6: =((IF((23='V06 Calend 01'!C6),('V06 Calend 01'!F6+'V06 Calend 01'!G6),0)+IF(AND(('V06 Calend 01'!E6>0),(23>'V06 Calend 01'!C6),(23<'V06 Calend 01'!D6),(MOD((23-'V06 Calend 01'!C6),6)=0),(((23-'V06 Calend 01'!C6)/6)<='V06 Calend 01'!E6)),IF((23=('V06 Calend 01'!C6+(6*'V06 Calend 01'!E6))),('V06 Calend 01'!H6-('V06 Calend 01'!I6*('V06 Calend 01'!E6-1))),'V06 Calend 01'!I6),0))+IF((23='V06 Calend 01'!D6),'V06 Calend 01'!J6,0)) -> 0 | AJ6: =((IF((24='V06 Calend 01'!C6),('V06 Calend 01'!F6+'V06 Calend 01'!G6),0)+IF(AND(('V06 Calend 01'!E6>0),(24>'V06 Calend 01'!C6),(24<'V06 Calend 01'!D6),(MOD((24-'V06 Calend 01'!C6),6)=0),(((24-'V06 Calend 01'!C6)/6)<='V06 Calend 01'!E6)),IF((24=('V06 Calend 01'!C6+(6*'V06 Calend 01'!E6))),('V06 Calend 01'!H6-('V06 Calend 01'!I6*('V06 Calend 01'!E6-1))),'V06 Calend 01'!I6),0))+IF((24='V06 Calend 01'!D6),'V06 Calend 01'!J6,0)) -> 0 | AK6: =((IF((25='V06 Calend 01'!C6),('V06 Calend 01'!F6+'V06 Calend 01'!G6),0)+IF(AND(('V06 Calend 01'!E6>0),(25>'V06 Calend 01'!C6),(25<'V06 Calend 01'!D6),(MOD((25-'V06 Calend 01'!C6),6)=0),(((25-'V06 Calend 01'!C6)/6)<='V06 Calend 01'!E6)),IF((25=('V06 Calend 01'!C6+(6*'V06 Calend 01'!E6))),('V06 Calend 01'!H6-('V06 Calend 01'!I6*('V06 Calend 01'!E6-1))),'V06 Calend 01'!I6),0))+IF((25='V06 Calend 01'!D6),'V06 Calend 01'!J6,0)) -> 55343.75 | AL6: =((IF((26='V06 Calend 01'!C6),('V06 Calend 01'!F6+'V06 Calend 01'!G6),0)+IF(AND(('V06 Calend 01'!E6>0),(26>'V06 Calend 01'!C6),(26<'V06 Calend 01'!D6),(MOD((26-'V06 Calend 01'!C6),6)=0),(((26-'V06 Calend 01'!C6)/6)<='V06 Calend 01'!E6)),IF((26=('V06 Calend 01'!C6+(6*'V06 Calend 01'!E6))),('V06 Calend 01'!H6-('V06 Calend 01'!I6*('V06 Calend 01'!E6-1))),'V06 Calend 01'!I6),0))+IF((26='V06 Calend 01'!D6),'V06 Calend 01'!J6,0)) -> 0 | AM6: =((IF((27='V06 Calend 01'!C6),('V06 Calend 01'!F6+'V06 Calend 01'!G6),0)+IF(AND(('V06 Calend 01'!E6>0),(27>'V06 Calend 01'!C6),(27<'V06 Calend 01'!D6),(MOD((27-'V06 Calend 01'!C6),6)=0),(((27-'V06 Calend 01'!C6)/6)<='V06 Calend 01'!E6)),IF((27=('V06 Calend 01'!C6+(6*'V06 Calend 01'!E6))),('V06 Calend 01'!H6-('V06 Calend 01'!I6*('V06 Calend 01'!E6-1))),'V06 Calend 01'!I6),0))+IF((27='V06 Calend 01'!D6),'V06 Calend 01'!J6,0)) -> 0 | AN6: =((IF((28='V06 Calend 01'!C6),('V06 Calend 01'!F6+'V06 Calend 01'!G6),0)+IF(AND(('V06 Calend 01'!E6>0),(28>'V06 Calend 01'!C6),(28<'V06 Calend 01'!D6),(MOD((28-'V06 Calend 01'!C6),6)=0),(((28-'V06 Calend 01'!C6)/6)<='V06 Calend 01'!E6)),IF((28=('V06 Calend 01'!C6+(6*'V06 Calend 01'!E6))),('V06 Calend 01'!H6-('V06 Calend 01'!I6*('V06 Calend 01'!E6-1))),'V06 Calend 01'!I6),0))+IF((28='V06 Calend 01'!D6),'V06 Calend 01'!J6,0)) -> 0 | AO6: =((IF((29='V06 Calend 01'!C6),('V06 Calend 01'!F6+'V06 Calend 01'!G6),0)+IF(AND(('V06 Calend 01'!E6>0),(29>'V06 Calend 01'!C6),(29<'V06 Calend 01'!D6),(MOD((29-'V06 Calend 01'!C6),6)=0),(((29-'V06 Calend 01'!C6)/6)<='V06 Calend 01'!E6)),IF((29=('V06 Calend 01'!C6+(6*'V06 Calend 01'!E6))),('V06 Calend 01'!H6-('V06 Calend 01'!I6*('V06 Calend 01'!E6-1))),'V06 Calend 01'!I6),0))+IF((29='V06 Calend 01'!D6),'V06 Calend 01'!J6,0)) -> 80500 | AP6: =((IF((30='V06 Calend 01'!C6),('V06 Calend 01'!F6+'V06 Calend 01'!G6),0)+IF(AND(('V06 Calend 01'!E6>0),(30>'V06 Calend 01'!C6),(30<'V06 Calend 01'!D6),(MOD((30-'V06 Calend 01'!C6),6)=0),(((30-'V06 Calend 01'!C6)/6)<='V06 Calend 01'!E6)),IF((30=('V06 Calend 01'!C6+(6*'V06 Calend 01'!E6))),('V06 Calend 01'!H6-('V06 Calend 01'!I6*('V06 Calend 01'!E6-1))),'V06 Calend 01'!I6),0))+IF((30='V06 Calend 01'!D6),'V06 Calend 01'!J6,0)) -> 0 | AQ6: =((IF((31='V06 Calend 01'!C6),('V06 Calend 01'!F6+'V06 Calend 01'!G6),0)+IF(AND(('V06 Calend 01'!E6>0),(31>'V06 Calend 01'!C6),(31<'V06 Calend 01'!D6),(MOD((31-'V06 Calend 01'!C6),6)=0),(((31-'V06 Calend 01'!C6)/6)<='V06 Calend 01'!E6)),IF((31=('V06 Calend 01'!C6+(6*'V06 Calend 01'!E6))),('V06 Calend 01'!H6-('V06 Calend 01'!I6*('V06 Calend 01'!E6-1))),'V06 Calend 01'!I6),0))+IF((31='V06 Calend 01'!D6),'V06 Calend 01'!J6,0)) -> 0 | AR6: =((IF((32='V06 Calend 01'!C6),('V06 Calend 01'!F6+'V06 Calend 01'!G6),0)+IF(AND(('V06 Calend 01'!E6>0),(32>'V06 Calend 01'!C6),(32<'V06 Calend 01'!D6),(MOD((32-'V06 Calend 01'!C6),6)=0),(((32-'V06 Calend 01'!C6)/6)<='V06 Calend 01'!E6)),IF((32=('V06 Calend 01'!C6+(6*'V06 Calend 01'!E6))),('V06 Calend 01'!H6-('V06 Calend 01'!I6*('V06 Calend 01'!E6-1))),'V06 Calend 01'!I6),0))+IF((32='V06 Calend 01'!D6),'V06 Calend 01'!J6,0)) -> 0 | AS6: =((IF((33='V06 Calend 01'!C6),('V06 Calend 01'!F6+'V06 Calend 01'!G6),0)+IF(AND(('V06 Calend 01'!E6>0),(33>'V06 Calend 01'!C6),(33<'V06 Calend 01'!D6),(MOD((33-'V06 Calend 01'!C6),6)=0),(((33-'V06 Calend 01'!C6)/6)<='V06 Calend 01'!E6)),IF((33=('V06 Calend 01'!C6+(6*'V06 Calend 01'!E6))),('V06 Calend 01'!H6-('V06 Calend 01'!I6*('V06 Calend 01'!E6-1))),'V06 Calend 01'!I6),0))+IF((33='V06 Calend 01'!D6),'V06 Calend 01'!J6,0)) -> 0 | AT6: =((IF((34='V06 Calend 01'!C6),('V06 Calend 01'!F6+'V06 Calend 01'!G6),0)+IF(AND(('V06 Calend 01'!E6>0),(34>'V06 Calend 01'!C6),(34<'V06 Calend 01'!D6),(MOD((34-'V06 Calend 01'!C6),6)=0),(((34-'V06 Calend 01'!C6)/6)<='V06 Calend 01'!E6)),IF((34=('V06 Calend 01'!C6+(6*'V06 Calend 01'!E6))),('V06 Calend 01'!H6-('V06 Calend 01'!I6*('V06 Calend 01'!E6-1))),'V06 Calend 01'!I6),0))+IF((34='V06 Calend 01'!D6),'V06 Calend 01'!J6,0)) -> 0 | AU6: =((IF((35='V06 Calend 01'!C6),('V06 Calend 01'!F6+'V06 Calend 01'!G6),0)+IF(AND(('V06 Calend 01'!E6>0),(35>'V06 Calend 01'!C6),(35<'V06 Calend 01'!D6),(MOD((35-'V06 Calend 01'!C6),6)=0),(((35-'V06 Calend 01'!C6)/6)<='V06 Calend 01'!E6)),IF((35=('V06 Calend 01'!C6+(6*'V06 Calend 01'!E6))),('V06 Calend 01'!H6-('V06 Calend 01'!I6*('V06 Calend 01'!E6-1))),'V06 Calend 01'!I6),0))+IF((35='V06 Calend 01'!D6),'V06 Calend 01'!J6,0)) -> 0 | AV6: =((IF((36='V06 Calend 01'!C6),('V06 Calend 01'!F6+'V06 Calend 01'!G6),0)+IF(AND(('V06 Calend 01'!E6>0),(36>'V06 Calend 01'!C6),(36<'V06 Calend 01'!D6),(MOD((36-'V06 Calend 01'!C6),6)=0),(((36-'V06 Calend 01'!C6)/6)<='V06 Calend 01'!E6)),IF((36=('V06 Calend 01'!C6+(6*'V06 Calend 01'!E6))),('V06 Calend 01'!H6-('V06 Calend 01'!I6*('V06 Calend 01'!E6-1))),'V06 Calend 01'!I6),0))+IF((36='V06 Calend 01'!D6),'V06 Calend 01'!J6,0)) -> 0 | AW6: =((IF((37='V06 Calend 01'!C6),('V06 Calend 01'!F6+'V06 Calend 01'!G6),0)+IF(AND(('V06 Calend 01'!E6>0),(37>'V06 Calend 01'!C6),(37<'V06 Calend 01'!D6),(MOD((37-'V06 Calend 01'!C6),6)=0),(((37-'V06 Calend 01'!C6)/6)<='V06 Calend 01'!E6)),IF((37=('V06 Calend 01'!C6+(6*'V06 Calend 01'!E6))),('V06 Calend 01'!H6-('V06 Calend 01'!I6*('V06 Calend 01'!E6-1))),'V06 Calend 01'!I6),0))+IF((37='V06 Calend 01'!D6),'V06 Calend 01'!J6,0)) -> 0 | AX6: =((IF((38='V06 Calend 01'!C6),('V06 Calend 01'!F6+'V06 Calend 01'!G6),0)+IF(AND(('V06 Calend 01'!E6>0),(38>'V06 Calend 01'!C6),(38<'V06 Calend 01'!D6),(MOD((38-'V06 Calend 01'!C6),6)=0),(((38-'V06 Calend 01'!C6)/6)<='V06 Calend 01'!E6)),IF((38=('V06 Calend 01'!C6+(6*'V06 Calend 01'!E6))),('V06 Calend 01'!H6-('V06 Calend 01'!I6*('V06 Calend 01'!E6-1))),'V06 Calend 01'!I6),0))+IF((38='V06 Calend 01'!D6),'V06 Calend 01'!J6,0)) -> 0 | AY6: =((IF((39='V06 Calend 01'!C6),('V06 Calend 01'!F6+'V06 Calend 01'!G6),0)+IF(AND(('V06 Calend 01'!E6>0),(39>'V06 Calend 01'!C6),(39<'V06 Calend 01'!D6),(MOD((39-'V06 Calend 01'!C6),6)=0),(((39-'V06 Calend 01'!C6)/6)<='V06 Calend 01'!E6)),IF((39=('V06 Calend 01'!C6+(6*'V06 Calend 01'!E6))),('V06 Calend 01'!H6-('V06 Calend 01'!I6*('V06 Calend 01'!E6-1))),'V06 Calend 01'!I6),0))+IF((39='V06 Calend 01'!D6),'V06 Calend 01'!J6,0)) -> 0 | AZ6: =((IF((40='V06 Calend 01'!C6),('V06 Calend 01'!F6+'V06 Calend 01'!G6),0)+IF(AND(('V06 Calend 01'!E6>0),(40>'V06 Calend 01'!C6),(40<'V06 Calend 01'!D6),(MOD((40-'V06 Calend 01'!C6),6)=0),(((40-'V06 Calend 01'!C6)/6)<='V06 Calend 01'!E6)),IF((40=('V06 Calend 01'!C6+(6*'V06 Calend 01'!E6))),('V06 Calend 01'!H6-('V06 Calend 01'!I6*('V06 Calend 01'!E6-1))),'V06 Calend 01'!I6),0))+IF((40='V06 Calend 01'!D6),'V06 Calend 01'!J6,0)) -> 0 | BA6: =((IF((41='V06 Calend 01'!C6),('V06 Calend 01'!F6+'V06 Calend 01'!G6),0)+IF(AND(('V06 Calend 01'!E6>0),(41>'V06 Calend 01'!C6),(41<'V06 Calend 01'!D6),(MOD((41-'V06 Calend 01'!C6),6)=0),(((41-'V06 Calend 01'!C6)/6)<='V06 Calend 01'!E6)),IF((41=('V06 Calend 01'!C6+(6*'V06 Calend 01'!E6))),('V06 Calend 01'!H6-('V06 Calend 01'!I6*('V06 Calend 01'!E6-1))),'V06 Calend 01'!I6),0))+IF((41='V06 Calend 01'!D6),'V06 Calend 01'!J6,0)) -> 0 | BB6: =((IF((42='V06 Calend 01'!C6),('V06 Calend 01'!F6+'V06 Calend 01'!G6),0)+IF(AND(('V06 Calend 01'!E6>0),(42>'V06 Calend 01'!C6),(42<'V06 Calend 01'!D6),(MOD((42-'V06 Calend 01'!C6),6)=0),(((42-'V06 Calend 01'!C6)/6)<='V06 Calend 01'!E6)),IF((42=('V06 Calend 01'!C6+(6*'V06 Calend 01'!E6))),('V06 Calend 01'!H6-('V06 Calend 01'!I6*('V06 Calend 01'!E6-1))),'V06 Calend 01'!I6),0))+IF((42='V06 Calend 01'!D6),'V06 Calend 01'!J6,0)) -> 0 | BC6: =((IF((43='V06 Calend 01'!C6),('V06 Calend 01'!F6+'V06 Calend 01'!G6),0)+IF(AND(('V06 Calend 01'!E6>0),(43>'V06 Calend 01'!C6),(43<'V06 Calend 01'!D6),(MOD((43-'V06 Calend 01'!C6),6)=0),(((43-'V06 Calend 01'!C6)/6)<='V06 Calend 01'!E6)),IF((43=('V06 Calend 01'!C6+(6*'V06 Calend 01'!E6))),('V06 Calend 01'!H6-('V06 Calend 01'!I6*('V06 Calend 01'!E6-1))),'V06 Calend 01'!I6),0))+IF((43='V06 Calend 01'!D6),'V06 Calend 01'!J6,0)) -> 0 | BD6: =((IF((44='V06 Calend 01'!C6),('V06 Calend 01'!F6+'V06 Calend 01'!G6),0)+IF(AND(('V06 Calend 01'!E6>0),(44>'V06 Calend 01'!C6),(44<'V06 Calend 01'!D6),(MOD((44-'V06 Calend 01'!C6),6)=0),(((44-'V06 Calend 01'!C6)/6)<='V06 Calend 01'!E6)),IF((44=('V06 Calend 01'!C6+(6*'V06 Calend 01'!E6))),('V06 Calend 01'!H6-('V06 Calend 01'!I6*('V06 Calend 01'!E6-1))),'V06 Calend 01'!I6),0))+IF((44='V06 Calend 01'!D6),'V06 Calend 01'!J6,0)) -> 0 | BE6: =((IF((45='V06 Calend 01'!C6),('V06 Calend 01'!F6+'V06 Calend 01'!G6),0)+IF(AND(('V06 Calend 01'!E6>0),(45>'V06 Calend 01'!C6),(45<'V06 Calend 01'!D6),(MOD((45-'V06 Calend 01'!C6),6)=0),(((45-'V06 Calend 01'!C6)/6)<='V06 Calend 01'!E6)),IF((45=('V06 Calend 01'!C6+(6*'V06 Calend 01'!E6))),('V06 Calend 01'!H6-('V06 Calend 01'!I6*('V06 Calend 01'!E6-1))),'V06 Calend 01'!I6),0))+IF((45='V06 Calend 01'!D6),'V06 Calend 01'!J6,0)) -> 0 | BF6: =((IF((46='V06 Calend 01'!C6),('V06 Calend 01'!F6+'V06 Calend 01'!G6),0)+IF(AND(('V06 Calend 01'!E6>0),(46>'V06 Calend 01'!C6),(46<'V06 Calend 01'!D6),(MOD((46-'V06 Calend 01'!C6),6)=0),(((46-'V06 Calend 01'!C6)/6)<='V06 Calend 01'!E6)),IF((46=('V06 Calend 01'!C6+(6*'V06 Calend 01'!E6))),('V06 Calend 01'!H6-('V06 Calend 01'!I6*('V06 Calend 01'!E6-1))),'V06 Calend 01'!I6),0))+IF((46='V06 Calend 01'!D6),'V06 Calend 01'!J6,0)) -> 0 | BG6: =((IF((47='V06 Calend 01'!C6),('V06 Calend 01'!F6+'V06 Calend 01'!G6),0)+IF(AND(('V06 Calend 01'!E6>0),(47>'V06 Calend 01'!C6),(47<'V06 Calend 01'!D6),(MOD((47-'V06 Calend 01'!C6),6)=0),(((47-'V06 Calend 01'!C6)/6)<='V06 Calend 01'!E6)),IF((47=('V06 Calend 01'!C6+(6*'V06 Calend 01'!E6))),('V06 Calend 01'!H6-('V06 Calend 01'!I6*('V06 Calend 01'!E6-1))),'V06 Calend 01'!I6),0))+IF((47='V06 Calend 01'!D6),'V06 Calend 01'!J6,0)) -> 0 | BH6: =((IF((48='V06 Calend 01'!C6),('V06 Calend 01'!F6+'V06 Calend 01'!G6),0)+IF(AND(('V06 Calend 01'!E6>0),(48>'V06 Calend 01'!C6),(48<'V06 Calend 01'!D6),(MOD((48-'V06 Calend 01'!C6),6)=0),(((48-'V06 Calend 01'!C6)/6)<='V06 Calend 01'!E6)),IF((48=('V06 Calend 01'!C6+(6*'V06 Calend 01'!E6))),('V06 Calend 01'!H6-('V06 Calend 01'!I6*('V06 Calend 01'!E6-1))),'V06 Calend 01'!I6),0))+IF((48='V06 Calend 01'!D6),'V06 Calend 01'!J6,0)) -> 0 | BI6: =((IF((49='V06 Calend 01'!C6),('V06 Calend 01'!F6+'V06 Calend 01'!G6),0)+IF(AND(('V06 Calend 01'!E6>0),(49>'V06 Calend 01'!C6),(49<'V06 Calend 01'!D6),(MOD((49-'V06 Calend 01'!C6),6)=0),(((49-'V06 Calend 01'!C6)/6)<='V06 Calend 01'!E6)),IF((49=('V06 Calend 01'!C6+(6*'V06 Calend 01'!E6))),('V06 Calend 01'!H6-('V06 Calend 01'!I6*('V06 Calend 01'!E6-1))),'V06 Calend 01'!I6),0))+IF((49='V06 Calend 01'!D6),'V06 Calend 01'!J6,0)) -> 0 | BJ6: =((IF((50='V06 Calend 01'!C6),('V06 Calend 01'!F6+'V06 Calend 01'!G6),0)+IF(AND(('V06 Calend 01'!E6>0),(50>'V06 Calend 01'!C6),(50<'V06 Calend 01'!D6),(MOD((50-'V06 Calend 01'!C6),6)=0),(((50-'V06 Calend 01'!C6)/6)<='V06 Calend 01'!E6)),IF((50=('V06 Calend 01'!C6+(6*'V06 Calend 01'!E6))),('V06 Calend 01'!H6-('V06 Calend 01'!I6*('V06 Calend 01'!E6-1))),'V06 Calend 01'!I6),0))+IF((50='V06 Calend 01'!D6),'V06 Calend 01'!J6,0)) -> 0 | BK6: =((IF((51='V06 Calend 01'!C6),('V06 Calend 01'!F6+'V06 Calend 01'!G6),0)+IF(AND(('V06 Calend 01'!E6>0),(51>'V06 Calend 01'!C6),(51<'V06 Calend 01'!D6),(MOD((51-'V06 Calend 01'!C6),6)=0),(((51-'V06 Calend 01'!C6)/6)<='V06 Calend 01'!E6)),IF((51=('V06 Calend 01'!C6+(6*'V06 Calend 01'!E6))),('V06 Calend 01'!H6-('V06 Calend 01'!I6*('V06 Calend 01'!E6-1))),'V06 Calend 01'!I6),0))+IF((51='V06 Calend 01'!D6),'V06 Calend 01'!J6,0)) -> 0 | BL6: =((IF((52='V06 Calend 01'!C6),('V06 Calend 01'!F6+'V06 Calend 01'!G6),0)+IF(AND(('V06 Calend 01'!E6>0),(52>'V06 Calend 01'!C6),(52<'V06 Calend 01'!D6),(MOD((52-'V06 Calend 01'!C6),6)=0),(((52-'V06 Calend 01'!C6)/6)<='V06 Calend 01'!E6)),IF((52=('V06 Calend 01'!C6+(6*'V06 Calend 01'!E6))),('V06 Calend 01'!H6-('V06 Calend 01'!I6*('V06 Calend 01'!E6-1))),'V06 Calend 01'!I6),0))+IF((52='V06 Calend 01'!D6),'V06 Calend 01'!J6,0)) -> 0 | BM6: =((IF((53='V06 Calend 01'!C6),('V06 Calend 01'!F6+'V06 Calend 01'!G6),0)+IF(AND(('V06 Calend 01'!E6>0),(53>'V06 Calend 01'!C6),(53<'V06 Calend 01'!D6),(MOD((53-'V06 Calend 01'!C6),6)=0),(((53-'V06 Calend 01'!C6)/6)<='V06 Calend 01'!E6)),IF((53=('V06 Calend 01'!C6+(6*'V06 Calend 01'!E6))),('V06 Calend 01'!H6-('V06 Calend 01'!I6*('V06 Calend 01'!E6-1))),'V06 Calend 01'!I6),0))+IF((53='V06 Calend 01'!D6),'V06 Calend 01'!J6,0)) -> 0 | BN6: =((IF((54='V06 Calend 01'!C6),('V06 Calend 01'!F6+'V06 Calend 01'!G6),0)+IF(AND(('V06 Calend 01'!E6>0),(54>'V06 Calend 01'!C6),(54<'V06 Calend 01'!D6),(MOD((54-'V06 Calend 01'!C6),6)=0),(((54-'V06 Calend 01'!C6)/6)<='V06 Calend 01'!E6)),IF((54=('V06 Calend 01'!C6+(6*'V06 Calend 01'!E6))),('V06 Calend 01'!H6-('V06 Calend 01'!I6*('V06 Calend 01'!E6-1))),'V06 Calend 01'!I6),0))+IF((54='V06 Calend 01'!D6),'V06 Calend 01'!J6,0)) -> 0 | BO6: =((IF((55='V06 Calend 01'!C6),('V06 Calend 01'!F6+'V06 Calend 01'!G6),0)+IF(AND(('V06 Calend 01'!E6>0),(55>'V06 Calend 01'!C6),(55<'V06 Calend 01'!D6),(MOD((55-'V06 Calend 01'!C6),6)=0),(((55-'V06 Calend 01'!C6)/6)<='V06 Calend 01'!E6)),IF((55=('V06 Calend 01'!C6+(6*'V06 Calend 01'!E6))),('V06 Calend 01'!H6-('V06 Calend 01'!I6*('V06 Calend 01'!E6-1))),'V06 Calend 01'!I6),0))+IF((55='V06 Calend 01'!D6),'V06 Calend 01'!J6,0)) -> 0 | BP6: =((IF((56='V06 Calend 01'!C6),('V06 Calend 01'!F6+'V06 Calend 01'!G6),0)+IF(AND(('V06 Calend 01'!E6>0),(56>'V06 Calend 01'!C6),(56<'V06 Calend 01'!D6),(MOD((56-'V06 Calend 01'!C6),6)=0),(((56-'V06 Calend 01'!C6)/6)<='V06 Calend 01'!E6)),IF((56=('V06 Calend 01'!C6+(6*'V06 Calend 01'!E6))),('V06 Calend 01'!H6-('V06 Calend 01'!I6*('V06 Calend 01'!E6-1))),'V06 Calend 01'!I6),0))+IF((56='V06 Calend 01'!D6),'V06 Calend 01'!J6,0)) -> 0 | BQ6: =((IF((57='V06 Calend 01'!C6),('V06 Calend 01'!F6+'V06 Calend 01'!G6),0)+IF(AND(('V06 Calend 01'!E6>0),(57>'V06 Calend 01'!C6),(57<'V06 Calend 01'!D6),(MOD((57-'V06 Calend 01'!C6),6)=0),(((57-'V06 Calend 01'!C6)/6)<='V06 Calend 01'!E6)),IF((57=('V06 Calend 01'!C6+(6*'V06 Calend 01'!E6))),('V06 Calend 01'!H6-('V06 Calend 01'!I6*('V06 Calend 01'!E6-1))),'V06 Calend 01'!I6),0))+IF((57='V06 Calend 01'!D6),'V06 Calend 01'!J6,0)) -> 0 | BR6: =((IF((58='V06 Calend 01'!C6),('V06 Calend 01'!F6+'V06 Calend 01'!G6),0)+IF(AND(('V06 Calend 01'!E6>0),(58>'V06 Calend 01'!C6),(58<'V06 Calend 01'!D6),(MOD((58-'V06 Calend 01'!C6),6)=0),(((58-'V06 Calend 01'!C6)/6)<='V06 Calend 01'!E6)),IF((58=('V06 Calend 01'!C6+(6*'V06 Calend 01'!E6))),('V06 Calend 01'!H6-('V06 Calend 01'!I6*('V06 Calend 01'!E6-1))),'V06 Calend 01'!I6),0))+IF((58='V06 Calend 01'!D6),'V06 Calend 01'!J6,0)) -> 0 | BS6: =((IF((59='V06 Calend 01'!C6),('V06 Calend 01'!F6+'V06 Calend 01'!G6),0)+IF(AND(('V06 Calend 01'!E6>0),(59>'V06 Calend 01'!C6),(59<'V06 Calend 01'!D6),(MOD((59-'V06 Calend 01'!C6),6)=0),(((59-'V06 Calend 01'!C6)/6)<='V06 Calend 01'!E6)),IF((59=('V06 Calend 01'!C6+(6*'V06 Calend 01'!E6))),('V06 Calend 01'!H6-('V06 Calend 01'!I6*('V06 Calend 01'!E6-1))),'V06 Calend 01'!I6),0))+IF((59='V06 Calend 01'!D6),'V06 Calend 01'!J6,0)) -> 0 | BT6: =((IF((60='V06 Calend 01'!C6),('V06 Calend 01'!F6+'V06 Calend 01'!G6),0)+IF(AND(('V06 Calend 01'!E6>0),(60>'V06 Calend 01'!C6),(60<'V06 Calend 01'!D6),(MOD((60-'V06 Calend 01'!C6),6)=0),(((60-'V06 Calend 01'!C6)/6)<='V06 Calend 01'!E6)),IF((60=('V06 Calend 01'!C6+(6*'V06 Calend 01'!E6))),('V06 Calend 01'!H6-('V06 Calend 01'!I6*('V06 Calend 01'!E6-1))),'V06 Calend 01'!I6),0))+IF((60='V06 Calend 01'!D6),'V06 Calend 01'!J6,0)) -> 0 | BU6: =((IF((61='V06 Calend 01'!C6),('V06 Calend 01'!F6+'V06 Calend 01'!G6),0)+IF(AND(('V06 Calend 01'!E6>0),(61>'V06 Calend 01'!C6),(61<'V06 Calend 01'!D6),(MOD((61-'V06 Calend 01'!C6),6)=0),(((61-'V06 Calend 01'!C6)/6)<='V06 Calend 01'!E6)),IF((61=('V06 Calend 01'!C6+(6*'V06 Calend 01'!E6))),('V06 Calend 01'!H6-('V06 Calend 01'!I6*('V06 Calend 01'!E6-1))),'V06 Calend 01'!I6),0))+IF((61='V06 Calend 01'!D6),'V06 Calend 01'!J6,0)) -> 0 | BV6: =((IF((62='V06 Calend 01'!C6),('V06 Calend 01'!F6+'V06 Calend 01'!G6),0)+IF(AND(('V06 Calend 01'!E6>0),(62>'V06 Calend 01'!C6),(62<'V06 Calend 01'!D6),(MOD((62-'V06 Calend 01'!C6),6)=0),(((62-'V06 Calend 01'!C6)/6)<='V06 Calend 01'!E6)),IF((62=('V06 Calend 01'!C6+(6*'V06 Calend 01'!E6))),('V06 Calend 01'!H6-('V06 Calend 01'!I6*('V06 Calend 01'!E6-1))),'V06 Calend 01'!I6),0))+IF((62='V06 Calend 01'!D6),'V06 Calend 01'!J6,0)) -> 0 | BW6: =((IF((63='V06 Calend 01'!C6),('V06 Calend 01'!F6+'V06 Calend 01'!G6),0)+IF(AND(('V06 Calend 01'!E6>0),(63>'V06 Calend 01'!C6),(63<'V06 Calend 01'!D6),(MOD((63-'V06 Calend 01'!C6),6)=0),(((63-'V06 Calend 01'!C6)/6)<='V06 Calend 01'!E6)),IF((63=('V06 Calend 01'!C6+(6*'V06 Calend 01'!E6))),('V06 Calend 01'!H6-('V06 Calend 01'!I6*('V06 Calend 01'!E6-1))),'V06 Calend 01'!I6),0))+IF((63='V06 Calend 01'!D6),'V06 Calend 01'!J6,0)) -> 0 | BX6: =((IF((64='V06 Calend 01'!C6),('V06 Calend 01'!F6+'V06 Calend 01'!G6),0)+IF(AND(('V06 Calend 01'!E6>0),(64>'V06 Calend 01'!C6),(64<'V06 Calend 01'!D6),(MOD((64-'V06 Calend 01'!C6),6)=0),(((64-'V06 Calend 01'!C6)/6)<='V06 Calend 01'!E6)),IF((64=('V06 Calend 01'!C6+(6*'V06 Calend 01'!E6))),('V06 Calend 01'!H6-('V06 Calend 01'!I6*('V06 Calend 01'!E6-1))),'V06 Calend 01'!I6),0))+IF((64='V06 Calend 01'!D6),'V06 Calend 01'!J6,0)) -> 0 | BY6: =((IF((65='V06 Calend 01'!C6),('V06 Calend 01'!F6+'V06 Calend 01'!G6),0)+IF(AND(('V06 Calend 01'!E6>0),(65>'V06 Calend 01'!C6),(65<'V06 Calend 01'!D6),(MOD((65-'V06 Calend 01'!C6),6)=0),(((65-'V06 Calend 01'!C6)/6)<='V06 Calend 01'!E6)),IF((65=('V06 Calend 01'!C6+(6*'V06 Calend 01'!E6))),('V06 Calend 01'!H6-('V06 Calend 01'!I6*('V06 Calend 01'!E6-1))),'V06 Calend 01'!I6),0))+IF((65='V06 Calend 01'!D6),'V06 Calend 01'!J6,0)) -> 0 | BZ6: =((IF((66='V06 Calend 01'!C6),('V06 Calend 01'!F6+'V06 Calend 01'!G6),0)+IF(AND(('V06 Calend 01'!E6>0),(66>'V06 Calend 01'!C6),(66<'V06 Calend 01'!D6),(MOD((66-'V06 Calend 01'!C6),6)=0),(((66-'V06 Calend 01'!C6)/6)<='V06 Calend 01'!E6)),IF((66=('V06 Calend 01'!C6+(6*'V06 Calend 01'!E6))),('V06 Calend 01'!H6-('V06 Calend 01'!I6*('V06 Calend 01'!E6-1))),'V06 Calend 01'!I6),0))+IF((66='V06 Calend 01'!D6),'V06 Calend 01'!J6,0)) -> 0 | CA6: =((IF((67='V06 Calend 01'!C6),('V06 Calend 01'!F6+'V06 Calend 01'!G6),0)+IF(AND(('V06 Calend 01'!E6>0),(67>'V06 Calend 01'!C6),(67<'V06 Calend 01'!D6),(MOD((67-'V06 Calend 01'!C6),6)=0),(((67-'V06 Calend 01'!C6)/6)<='V06 Calend 01'!E6)),IF((67=('V06 Calend 01'!C6+(6*'V06 Calend 01'!E6))),('V06 Calend 01'!H6-('V06 Calend 01'!I6*('V06 Calend 01'!E6-1))),'V06 Calend 01'!I6),0))+IF((67='V06 Calend 01'!D6),'V06 Calend 01'!J6,0)) -> 0 | CB6: =((IF((68='V06 Calend 01'!C6),('V06 Calend 01'!F6+'V06 Calend 01'!G6),0)+IF(AND(('V06 Calend 01'!E6>0),(68>'V06 Calend 01'!C6),(68<'V06 Calend 01'!D6),(MOD((68-'V06 Calend 01'!C6),6)=0),(((68-'V06 Calend 01'!C6)/6)<='V06 Calend 01'!E6)),IF((68=('V06 Calend 01'!C6+(6*'V06 Calend 01'!E6))),('V06 Calend 01'!H6-('V06 Calend 01'!I6*('V06 Calend 01'!E6-1))),'V06 Calend 01'!I6),0))+IF((68='V06 Calend 01'!D6),'V06 Calend 01'!J6,0)) -> 0 | CC6: =((IF((69='V06 Calend 01'!C6),('V06 Calend 01'!F6+'V06 Calend 01'!G6),0)+IF(AND(('V06 Calend 01'!E6>0),(69>'V06 Calend 01'!C6),(69<'V06 Calend 01'!D6),(MOD((69-'V06 Calend 01'!C6),6)=0),(((69-'V06 Calend 01'!C6)/6)<='V06 Calend 01'!E6)),IF((69=('V06 Calend 01'!C6+(6*'V06 Calend 01'!E6))),('V06 Calend 01'!H6-('V06 Calend 01'!I6*('V06 Calend 01'!E6-1))),'V06 Calend 01'!I6),0))+IF((69='V06 Calend 01'!D6),'V06 Calend 01'!J6,0)) -> 0 | CD6: =((IF((70='V06 Calend 01'!C6),('V06 Calend 01'!F6+'V06 Calend 01'!G6),0)+IF(AND(('V06 Calend 01'!E6>0),(70>'V06 Calend 01'!C6),(70<'V06 Calend 01'!D6),(MOD((70-'V06 Calend 01'!C6),6)=0),(((70-'V06 Calend 01'!C6)/6)<='V06 Calend 01'!E6)),IF((70=('V06 Calend 01'!C6+(6*'V06 Calend 01'!E6))),('V06 Calend 01'!H6-('V06 Calend 01'!I6*('V06 Calend 01'!E6-1))),'V06 Calend 01'!I6),0))+IF((70='V06 Calend 01'!D6),'V06 Calend 01'!J6,0)) -> 0 | CE6: =((IF((71='V06 Calend 01'!C6),('V06 Calend 01'!F6+'V06 Calend 01'!G6),0)+IF(AND(('V06 Calend 01'!E6>0),(71>'V06 Calend 01'!C6),(71<'V06 Calend 01'!D6),(MOD((71-'V06 Calend 01'!C6),6)=0),(((71-'V06 Calend 01'!C6)/6)<='V06 Calend 01'!E6)),IF((71=('V06 Calend 01'!C6+(6*'V06 Calend 01'!E6))),('V06 Calend 01'!H6-('V06 Calend 01'!I6*('V06 Calend 01'!E6-1))),'V06 Calend 01'!I6),0))+IF((71='V06 Calend 01'!D6),'V06 Calend 01'!J6,0)) -> 0 | CF6: =((IF((72='V06 Calend 01'!C6),('V06 Calend 01'!F6+'V06 Calend 01'!G6),0)+IF(AND(('V06 Calend 01'!E6>0),(72>'V06 Calend 01'!C6),(72<'V06 Calend 01'!D6),(MOD((72-'V06 Calend 01'!C6),6)=0),(((72-'V06 Calend 01'!C6)/6)<='V06 Calend 01'!E6)),IF((72=('V06 Calend 01'!C6+(6*'V06 Calend 01'!E6))),('V06 Calend 01'!H6-('V06 Calend 01'!I6*('V06 Calend 01'!E6-1))),'V06 Calend 01'!I6),0))+IF((72='V06 Calend 01'!D6),'V06 Calend 01'!J6,0)) -> 0 | CG6: =((IF((73='V06 Calend 01'!C6),('V06 Calend 01'!F6+'V06 Calend 01'!G6),0)+IF(AND(('V06 Calend 01'!E6>0),(73>'V06 Calend 01'!C6),(73<'V06 Calend 01'!D6),(MOD((73-'V06 Calend 01'!C6),6)=0),(((73-'V06 Calend 01'!C6)/6)<='V06 Calend 01'!E6)),IF((73=('V06 Calend 01'!C6+(6*'V06 Calend 01'!E6))),('V06 Calend 01'!H6-('V06 Calend 01'!I6*('V06 Calend 01'!E6-1))),'V06 Calend 01'!I6),0))+IF((73='V06 Calend 01'!D6),'V06 Calend 01'!J6,0)) -> 0 | CH6: =((IF((74='V06 Calend 01'!C6),('V06 Calend 01'!F6+'V06 Calend 01'!G6),0)+IF(AND(('V06 Calend 01'!E6>0),(74>'V06 Calend 01'!C6),(74<'V06 Calend 01'!D6),(MOD((74-'V06 Calend 01'!C6),6)=0),(((74-'V06 Calend 01'!C6)/6)<='V06 Calend 01'!E6)),IF((74=('V06 Calend 01'!C6+(6*'V06 Calend 01'!E6))),('V06 Calend 01'!H6-('V06 Calend 01'!I6*('V06 Calend 01'!E6-1))),'V06 Calend 01'!I6),0))+IF((74='V06 Calend 01'!D6),'V06 Calend 01'!J6,0)) -> 0 | CI6: =((IF((75='V06 Calend 01'!C6),('V06 Calend 01'!F6+'V06 Calend 01'!G6),0)+IF(AND(('V06 Calend 01'!E6>0),(75>'V06 Calend 01'!C6),(75<'V06 Calend 01'!D6),(MOD((75-'V06 Calend 01'!C6),6)=0),(((75-'V06 Calend 01'!C6)/6)<='V06 Calend 01'!E6)),IF((75=('V06 Calend 01'!C6+(6*'V06 Calend 01'!E6))),('V06 Calend 01'!H6-('V06 Calend 01'!I6*('V06 Calend 01'!E6-1))),'V06 Calend 01'!I6),0))+IF((75='V06 Calend 01'!D6),'V06 Calend 01'!J6,0)) -> 0 | CJ6: =((IF((76='V06 Calend 01'!C6),('V06 Calend 01'!F6+'V06 Calend 01'!G6),0)+IF(AND(('V06 Calend 01'!E6>0),(76>'V06 Calend 01'!C6),(76<'V06 Calend 01'!D6),(MOD((76-'V06 Calend 01'!C6),6)=0),(((76-'V06 Calend 01'!C6)/6)<='V06 Calend 01'!E6)),IF((76=('V06 Calend 01'!C6+(6*'V06 Calend 01'!E6))),('V06 Calend 01'!H6-('V06 Calend 01'!I6*('V06 Calend 01'!E6-1))),'V06 Calend 01'!I6),0))+IF((76='V06 Calend 01'!D6),'V06 Calend 01'!J6,0)) -> 0 | CK6: =((IF((77='V06 Calend 01'!C6),('V06 Calend 01'!F6+'V06 Calend 01'!G6),0)+IF(AND(('V06 Calend 01'!E6>0),(77>'V06 Calend 01'!C6),(77<'V06 Calend 01'!D6),(MOD((77-'V06 Calend 01'!C6),6)=0),(((77-'V06 Calend 01'!C6)/6)<='V06 Calend 01'!E6)),IF((77=('V06 Calend 01'!C6+(6*'V06 Calend 01'!E6))),('V06 Calend 01'!H6-('V06 Calend 01'!I6*('V06 Calend 01'!E6-1))),'V06 Calend 01'!I6),0))+IF((77='V06 Calend 01'!D6),'V06 Calend 01'!J6,0)) -> 0 | CL6: =((IF((78='V06 Calend 01'!C6),('V06 Calend 01'!F6+'V06 Calend 01'!G6),0)+IF(AND(('V06 Calend 01'!E6>0),(78>'V06 Calend 01'!C6),(78<'V06 Calend 01'!D6),(MOD((78-'V06 Calend 01'!C6),6)=0),(((78-'V06 Calend 01'!C6)/6)<='V06 Calend 01'!E6)),IF((78=('V06 Calend 01'!C6+(6*'V06 Calend 01'!E6))),('V06 Calend 01'!H6-('V06 Calend 01'!I6*('V06 Calend 01'!E6-1))),'V06 Calend 01'!I6),0))+IF((78='V06 Calend 01'!D6),'V06 Calend 01'!J6,0)) -> 0 | CM6: =((IF((79='V06 Calend 01'!C6),('V06 Calend 01'!F6+'V06 Calend 01'!G6),0)+IF(AND(('V06 Calend 01'!E6>0),(79>'V06 Calend 01'!C6),(79<'V06 Calend 01'!D6),(MOD((79-'V06 Calend 01'!C6),6)=0),(((79-'V06 Calend 01'!C6)/6)<='V06 Calend 01'!E6)),IF((79=('V06 Calend 01'!C6+(6*'V06 Calend 01'!E6))),('V06 Calend 01'!H6-('V06 Calend 01'!I6*('V06 Calend 01'!E6-1))),'V06 Calend 01'!I6),0))+IF((79='V06 Calend 01'!D6),'V06 Calend 01'!J6,0)) -> 0 | CN6: =((IF((80='V06 Calend 01'!C6),('V06 Calend 01'!F6+'V06 Calend 01'!G6),0)+IF(AND(('V06 Calend 01'!E6>0),(80>'V06 Calend 01'!C6),(80<'V06 Calend 01'!D6),(MOD((80-'V06 Calend 01'!C6),6)=0),(((80-'V06 Calend 01'!C6)/6)<='V06 Calend 01'!E6)),IF((80=('V06 Calend 01'!C6+(6*'V06 Calend 01'!E6))),('V06 Calend 01'!H6-('V06 Calend 01'!I6*('V06 Calend 01'!E6-1))),'V06 Calend 01'!I6),0))+IF((80='V06 Calend 01'!D6),'V06 Calend 01'!J6,0)) -> 0 | CO6: =((IF((81='V06 Calend 01'!C6),('V06 Calend 01'!F6+'V06 Calend 01'!G6),0)+IF(AND(('V06 Calend 01'!E6>0),(81>'V06 Calend 01'!C6),(81<'V06 Calend 01'!D6),(MOD((81-'V06 Calend 01'!C6),6)=0),(((81-'V06 Calend 01'!C6)/6)<='V06 Calend 01'!E6)),IF((81=('V06 Calend 01'!C6+(6*'V06 Calend 01'!E6))),('V06 Calend 01'!H6-('V06 Calend 01'!I6*('V06 Calend 01'!E6-1))),'V06 Calend 01'!I6),0))+IF((81='V06 Calend 01'!D6),'V06 Calend 01'!J6,0)) -> 0 | CP6: =((IF((82='V06 Calend 01'!C6),('V06 Calend 01'!F6+'V06 Calend 01'!G6),0)+IF(AND(('V06 Calend 01'!E6>0),(82>'V06 Calend 01'!C6),(82<'V06 Calend 01'!D6),(MOD((82-'V06 Calend 01'!C6),6)=0),(((82-'V06 Calend 01'!C6)/6)<='V06 Calend 01'!E6)),IF((82=('V06 Calend 01'!C6+(6*'V06 Calend 01'!E6))),('V06 Calend 01'!H6-('V06 Calend 01'!I6*('V06 Calend 01'!E6-1))),'V06 Calend 01'!I6),0))+IF((82='V06 Calend 01'!D6),'V06 Calend 01'!J6,0)) -> 0 | CQ6: =((IF((83='V06 Calend 01'!C6),('V06 Calend 01'!F6+'V06 Calend 01'!G6),0)+IF(AND(('V06 Calend 01'!E6>0),(83>'V06 Calend 01'!C6),(83<'V06 Calend 01'!D6),(MOD((83-'V06 Calend 01'!C6),6)=0),(((83-'V06 Calend 01'!C6)/6)<='V06 Calend 01'!E6)),IF((83=('V06 Calend 01'!C6+(6*'V06 Calend 01'!E6))),('V06 Calend 01'!H6-('V06 Calend 01'!I6*('V06 Calend 01'!E6-1))),'V06 Calend 01'!I6),0))+IF((83='V06 Calend 01'!D6),'V06 Calend 01'!J6,0)) -> 0 | CR6: =((IF((84='V06 Calend 01'!C6),('V06 Calend 01'!F6+'V06 Calend 01'!G6),0)+IF(AND(('V06 Calend 01'!E6>0),(84>'V06 Calend 01'!C6),(84<'V06 Calend 01'!D6),(MOD((84-'V06 Calend 01'!C6),6)=0),(((84-'V06 Calend 01'!C6)/6)<='V06 Calend 01'!E6)),IF((84=('V06 Calend 01'!C6+(6*'V06 Calend 01'!E6))),('V06 Calend 01'!H6-('V06 Calend 01'!I6*('V06 Calend 01'!E6-1))),'V06 Calend 01'!I6),0))+IF((84='V06 Calend 01'!D6),'V06 Calend 01'!J6,0)) -> 0 | CS6: =((IF((85='V06 Calend 01'!C6),('V06 Calend 01'!F6+'V06 Calend 01'!G6),0)+IF(AND(('V06 Calend 01'!E6>0),(85>'V06 Calend 01'!C6),(85<'V06 Calend 01'!D6),(MOD((85-'V06 Calend 01'!C6),6)=0),(((85-'V06 Calend 01'!C6)/6)<='V06 Calend 01'!E6)),IF((85=('V06 Calend 01'!C6+(6*'V06 Calend 01'!E6))),('V06 Calend 01'!H6-('V06 Calend 01'!I6*('V06 Calend 01'!E6-1))),'V06 Calend 01'!I6),0))+IF((85='V06 Calend 01'!D6),'V06 Calend 01'!J6,0)) -> 0 | CT6: =((IF((86='V06 Calend 01'!C6),('V06 Calend 01'!F6+'V06 Calend 01'!G6),0)+IF(AND(('V06 Calend 01'!E6>0),(86>'V06 Calend 01'!C6),(86<'V06 Calend 01'!D6),(MOD((86-'V06 Calend 01'!C6),6)=0),(((86-'V06 Calend 01'!C6)/6)<='V06 Calend 01'!E6)),IF((86=('V06 Calend 01'!C6+(6*'V06 Calend 01'!E6))),('V06 Calend 01'!H6-('V06 Calend 01'!I6*('V06 Calend 01'!E6-1))),'V06 Calend 01'!I6),0))+IF((86='V06 Calend 01'!D6),'V06 Calend 01'!J6,0)) -> 0 | CU6: =((IF((87='V06 Calend 01'!C6),('V06 Calend 01'!F6+'V06 Calend 01'!G6),0)+IF(AND(('V06 Calend 01'!E6>0),(87>'V06 Calend 01'!C6),(87<'V06 Calend 01'!D6),(MOD((87-'V06 Calend 01'!C6),6)=0),(((87-'V06 Calend 01'!C6)/6)<='V06 Calend 01'!E6)),IF((87=('V06 Calend 01'!C6+(6*'V06 Calend 01'!E6))),('V06 Calend 01'!H6-('V06 Calend 01'!I6*('V06 Calend 01'!E6-1))),'V06 Calend 01'!I6),0))+IF((87='V06 Calend 01'!D6),'V06 Calend 01'!J6,0)) -> 0 | CV6: =((IF((88='V06 Calend 01'!C6),('V06 Calend 01'!F6+'V06 Calend 01'!G6),0)+IF(AND(('V06 Calend 01'!E6>0),(88>'V06 Calend 01'!C6),(88<'V06 Calend 01'!D6),(MOD((88-'V06 Calend 01'!C6),6)=0),(((88-'V06 Calend 01'!C6)/6)<='V06 Calend 01'!E6)),IF((88=('V06 Calend 01'!C6+(6*'V06 Calend 01'!E6))),('V06 Calend 01'!H6-('V06 Calend 01'!I6*('V06 Calend 01'!E6-1))),'V06 Calend 01'!I6),0))+IF((88='V06 Calend 01'!D6),'V06 Calend 01'!J6,0)) -> 0 | CW6: =((IF((89='V06 Calend 01'!C6),('V06 Calend 01'!F6+'V06 Calend 01'!G6),0)+IF(AND(('V06 Calend 01'!E6>0),(89>'V06 Calend 01'!C6),(89<'V06 Calend 01'!D6),(MOD((89-'V06 Calend 01'!C6),6)=0),(((89-'V06 Calend 01'!C6)/6)<='V06 Calend 01'!E6)),IF((89=('V06 Calend 01'!C6+(6*'V06 Calend 01'!E6))),('V06 Calend 01'!H6-('V06 Calend 01'!I6*('V06 Calend 01'!E6-1))),'V06 Calend 01'!I6),0))+IF((89='V06 Calend 01'!D6),'V06 Calend 01'!J6,0)) -> 0 | CX6: =((IF((90='V06 Calend 01'!C6),('V06 Calend 01'!F6+'V06 Calend 01'!G6),0)+IF(AND(('V06 Calend 01'!E6>0),(90>'V06 Calend 01'!C6),(90<'V06 Calend 01'!D6),(MOD((90-'V06 Calend 01'!C6),6)=0),(((90-'V06 Calend 01'!C6)/6)<='V06 Calend 01'!E6)),IF((90=('V06 Calend 01'!C6+(6*'V06 Calend 01'!E6))),('V06 Calend 01'!H6-('V06 Calend 01'!I6*('V06 Calend 01'!E6-1))),'V06 Calend 01'!I6),0))+IF((90='V06 Calend 01'!D6),'V06 Calend 01'!J6,0)) -> 0 | CY6: =((IF((91='V06 Calend 01'!C6),('V06 Calend 01'!F6+'V06 Calend 01'!G6),0)+IF(AND(('V06 Calend 01'!E6>0),(91>'V06 Calend 01'!C6),(91<'V06 Calend 01'!D6),(MOD((91-'V06 Calend 01'!C6),6)=0),(((91-'V06 Calend 01'!C6)/6)<='V06 Calend 01'!E6)),IF((91=('V06 Calend 01'!C6+(6*'V06 Calend 01'!E6))),('V06 Calend 01'!H6-('V06 Calend 01'!I6*('V06 Calend 01'!E6-1))),'V06 Calend 01'!I6),0))+IF((91='V06 Calend 01'!D6),'V06 Calend 01'!J6,0)) -> 0 | CZ6: =((IF((92='V06 Calend 01'!C6),('V06 Calend 01'!F6+'V06 Calend 01'!G6),0)+IF(AND(('V06 Calend 01'!E6>0),(92>'V06 Calend 01'!C6),(92<'V06 Calend 01'!D6),(MOD((92-'V06 Calend 01'!C6),6)=0),(((92-'V06 Calend 01'!C6)/6)<='V06 Calend 01'!E6)),IF((92=('V06 Calend 01'!C6+(6*'V06 Calend 01'!E6))),('V06 Calend 01'!H6-('V06 Calend 01'!I6*('V06 Calend 01'!E6-1))),'V06 Calend 01'!I6),0))+IF((92='V06 Calend 01'!D6),'V06 Calend 01'!J6,0)) -> 0 | DA6: =((IF((93='V06 Calend 01'!C6),('V06 Calend 01'!F6+'V06 Calend 01'!G6),0)+IF(AND(('V06 Calend 01'!E6>0),(93>'V06 Calend 01'!C6),(93<'V06 Calend 01'!D6),(MOD((93-'V06 Calend 01'!C6),6)=0),(((93-'V06 Calend 01'!C6)/6)<='V06 Calend 01'!E6)),IF((93=('V06 Calend 01'!C6+(6*'V06 Calend 01'!E6))),('V06 Calend 01'!H6-('V06 Calend 01'!I6*('V06 Calend 01'!E6-1))),'V06 Calend 01'!I6),0))+IF((93='V06 Calend 01'!D6),'V06 Calend 01'!J6,0)) -> 0 | DB6: =((IF((94='V06 Calend 01'!C6),('V06 Calend 01'!F6+'V06 Calend 01'!G6),0)+IF(AND(('V06 Calend 01'!E6>0),(94>'V06 Calend 01'!C6),(94<'V06 Calend 01'!D6),(MOD((94-'V06 Calend 01'!C6),6)=0),(((94-'V06 Calend 01'!C6)/6)<='V06 Calend 01'!E6)),IF((94=('V06 Calend 01'!C6+(6*'V06 Calend 01'!E6))),('V06 Calend 01'!H6-('V06 Calend 01'!I6*('V06 Calend 01'!E6-1))),'V06 Calend 01'!I6),0))+IF((94='V06 Calend 01'!D6),'V06 Calend 01'!J6,0)) -> 0 | DC6: =((IF((95='V06 Calend 01'!C6),('V06 Calend 01'!F6+'V06 Calend 01'!G6),0)+IF(AND(('V06 Calend 01'!E6>0),(95>'V06 Calend 01'!C6),(95<'V06 Calend 01'!D6),(MOD((95-'V06 Calend 01'!C6),6)=0),(((95-'V06 Calend 01'!C6)/6)<='V06 Calend 01'!E6)),IF((95=('V06 Calend 01'!C6+(6*'V06 Calend 01'!E6))),('V06 Calend 01'!H6-('V06 Calend 01'!I6*('V06 Calend 01'!E6-1))),'V06 Calend 01'!I6),0))+IF((95='V06 Calend 01'!D6),'V06 Calend 01'!J6,0)) -> 0 | DD6: =((IF((96='V06 Calend 01'!C6),('V06 Calend 01'!F6+'V06 Calend 01'!G6),0)+IF(AND(('V06 Calend 01'!E6>0),(96>'V06 Calend 01'!C6),(96<'V06 Calend 01'!D6),(MOD((96-'V06 Calend 01'!C6),6)=0),(((96-'V06 Calend 01'!C6)/6)<='V06 Calend 01'!E6)),IF((96=('V06 Calend 01'!C6+(6*'V06 Calend 01'!E6))),('V06 Calend 01'!H6-('V06 Calend 01'!I6*('V06 Calend 01'!E6-1))),'V06 Calend 01'!I6),0))+IF((96='V06 Calend 01'!D6),'V06 Calend 01'!J6,0)) -> 0 | DE6: =((IF((97='V06 Calend 01'!C6),('V06 Calend 01'!F6+'V06 Calend 01'!G6),0)+IF(AND(('V06 Calend 01'!E6>0),(97>'V06 Calend 01'!C6),(97<'V06 Calend 01'!D6),(MOD((97-'V06 Calend 01'!C6),6)=0),(((97-'V06 Calend 01'!C6)/6)<='V06 Calend 01'!E6)),IF((97=('V06 Calend 01'!C6+(6*'V06 Calend 01'!E6))),('V06 Calend 01'!H6-('V06 Calend 01'!I6*('V06 Calend 01'!E6-1))),'V06 Calend 01'!I6),0))+IF((97='V06 Calend 01'!D6),'V06 Calend 01'!J6,0)) -> 0 | DF6: =((IF((98='V06 Calend 01'!C6),('V06 Calend 01'!F6+'V06 Calend 01'!G6),0)+IF(AND(('V06 Calend 01'!E6>0),(98>'V06 Calend 01'!C6),(98<'V06 Calend 01'!D6),(MOD((98-'V06 Calend 01'!C6),6)=0),(((98-'V06 Calend 01'!C6)/6)<='V06 Calend 01'!E6)),IF((98=('V06 Calend 01'!C6+(6*'V06 Calend 01'!E6))),('V06 Calend 01'!H6-('V06 Calend 01'!I6*('V06 Calend 01'!E6-1))),'V06 Calend 01'!I6),0))+IF((98='V06 Calend 01'!D6),'V06 Calend 01'!J6,0)) -> 0 | DG6: =((IF((99='V06 Calend 01'!C6),('V06 Calend 01'!F6+'V06 Calend 01'!G6),0)+IF(AND(('V06 Calend 01'!E6>0),(99>'V06 Calend 01'!C6),(99<'V06 Calend 01'!D6),(MOD((99-'V06 Calend 01'!C6),6)=0),(((99-'V06 Calend 01'!C6)/6)<='V06 Calend 01'!E6)),IF((99=('V06 Calend 01'!C6+(6*'V06 Calend 01'!E6))),('V06 Calend 01'!H6-('V06 Calend 01'!I6*('V06 Calend 01'!E6-1))),'V06 Calend 01'!I6),0))+IF((99='V06 Calend 01'!D6),'V06 Calend 01'!J6,0)) -> 0 | DH6: =((IF((100='V06 Calend 01'!C6),('V06 Calend 01'!F6+'V06 Calend 01'!G6),0)+IF(AND(('V06 Calend 01'!E6>0),(100>'V06 Calend 01'!C6),(100<'V06 Calend 01'!D6),(MOD((100-'V06 Calend 01'!C6),6)=0),(((100-'V06 Calend 01'!C6)/6)<='V06 Calend 01'!E6)),IF((100=('V06 Calend 01'!C6+(6*'V06 Calend 01'!E6))),('V06 Calend 01'!H6-('V06 Calend 01'!I6*('V06 Calend 01'!E6-1))),'V06 Calend 01'!I6),0))+IF((100='V06 Calend 01'!D6),'V06 Calend 01'!J6,0)) -> 0 | DI6: =((IF((101='V06 Calend 01'!C6),('V06 Calend 01'!F6+'V06 Calend 01'!G6),0)+IF(AND(('V06 Calend 01'!E6>0),(101>'V06 Calend 01'!C6),(101<'V06 Calend 01'!D6),(MOD((101-'V06 Calend 01'!C6),6)=0),(((101-'V06 Calend 01'!C6)/6)<='V06 Calend 01'!E6)),IF((101=('V06 Calend 01'!C6+(6*'V06 Calend 01'!E6))),('V06 Calend 01'!H6-('V06 Calend 01'!I6*('V06 Calend 01'!E6-1))),'V06 Calend 01'!I6),0))+IF((101='V06 Calend 01'!D6),'V06 Calend 01'!J6,0)) -> 0 | DJ6: =((IF((102='V06 Calend 01'!C6),('V06 Calend 01'!F6+'V06 Calend 01'!G6),0)+IF(AND(('V06 Calend 01'!E6>0),(102>'V06 Calend 01'!C6),(102<'V06 Calend 01'!D6),(MOD((102-'V06 Calend 01'!C6),6)=0),(((102-'V06 Calend 01'!C6)/6)<='V06 Calend 01'!E6)),IF((102=('V06 Calend 01'!C6+(6*'V06 Calend 01'!E6))),('V06 Calend 01'!H6-('V06 Calend 01'!I6*('V06 Calend 01'!E6-1))),'V06 Calend 01'!I6),0))+IF((102='V06 Calend 01'!D6),'V06 Calend 01'!J6,0)) -> 0 | DK6: =((IF((103='V06 Calend 01'!C6),('V06 Calend 01'!F6+'V06 Calend 01'!G6),0)+IF(AND(('V06 Calend 01'!E6>0),(103>'V06 Calend 01'!C6),(103<'V06 Calend 01'!D6),(MOD((103-'V06 Calend 01'!C6),6)=0),(((103-'V06 Calend 01'!C6)/6)<='V06 Calend 01'!E6)),IF((103=('V06 Calend 01'!C6+(6*'V06 Calend 01'!E6))),('V06 Calend 01'!H6-('V06 Calend 01'!I6*('V06 Calend 01'!E6-1))),'V06 Calend 01'!I6),0))+IF((103='V06 Calend 01'!D6),'V06 Calend 01'!J6,0)) -> 0 | DL6: =((IF((104='V06 Calend 01'!C6),('V06 Calend 01'!F6+'V06 Calend 01'!G6),0)+IF(AND(('V06 Calend 01'!E6>0),(104>'V06 Calend 01'!C6),(104<'V06 Calend 01'!D6),(MOD((104-'V06 Calend 01'!C6),6)=0),(((104-'V06 Calend 01'!C6)/6)<='V06 Calend 01'!E6)),IF((104=('V06 Calend 01'!C6+(6*'V06 Calend 01'!E6))),('V06 Calend 01'!H6-('V06 Calend 01'!I6*('V06 Calend 01'!E6-1))),'V06 Calend 01'!I6),0))+IF((104='V06 Calend 01'!D6),'V06 Calend 01'!J6,0)) -> 0 | DM6: =((IF((105='V06 Calend 01'!C6),('V06 Calend 01'!F6+'V06 Calend 01'!G6),0)+IF(AND(('V06 Calend 01'!E6>0),(105>'V06 Calend 01'!C6),(105<'V06 Calend 01'!D6),(MOD((105-'V06 Calend 01'!C6),6)=0),(((105-'V06 Calend 01'!C6)/6)<='V06 Calend 01'!E6)),IF((105=('V06 Calend 01'!C6+(6*'V06 Calend 01'!E6))),('V06 Calend 01'!H6-('V06 Calend 01'!I6*('V06 Calend 01'!E6-1))),'V06 Calend 01'!I6),0))+IF((105='V06 Calend 01'!D6),'V06 Calend 01'!J6,0)) -> 0 | DN6: =((IF((106='V06 Calend 01'!C6),('V06 Calend 01'!F6+'V06 Calend 01'!G6),0)+IF(AND(('V06 Calend 01'!E6>0),(106>'V06 Calend 01'!C6),(106<'V06 Calend 01'!D6),(MOD((106-'V06 Calend 01'!C6),6)=0),(((106-'V06 Calend 01'!C6)/6)<='V06 Calend 01'!E6)),IF((106=('V06 Calend 01'!C6+(6*'V06 Calend 01'!E6))),('V06 Calend 01'!H6-('V06 Calend 01'!I6*('V06 Calend 01'!E6-1))),'V06 Calend 01'!I6),0))+IF((106='V06 Calend 01'!D6),'V06 Calend 01'!J6,0)) -> 0 | DO6: =((IF((107='V06 Calend 01'!C6),('V06 Calend 01'!F6+'V06 Calend 01'!G6),0)+IF(AND(('V06 Calend 01'!E6>0),(107>'V06 Calend 01'!C6),(107<'V06 Calend 01'!D6),(MOD((107-'V06 Calend 01'!C6),6)=0),(((107-'V06 Calend 01'!C6)/6)<='V06 Calend 01'!E6)),IF((107=('V06 Calend 01'!C6+(6*'V06 Calend 01'!E6))),('V06 Calend 01'!H6-('V06 Calend 01'!I6*('V06 Calend 01'!E6-1))),'V06 Calend 01'!I6),0))+IF((107='V06 Calend 01'!D6),'V06 Calend 01'!J6,0)) -> 0 | DP6: =((IF((108='V06 Calend 01'!C6),('V06 Calend 01'!F6+'V06 Calend 01'!G6),0)+IF(AND(('V06 Calend 01'!E6>0),(108>'V06 Calend 01'!C6),(108<'V06 Calend 01'!D6),(MOD((108-'V06 Calend 01'!C6),6)=0),(((108-'V06 Calend 01'!C6)/6)<='V06 Calend 01'!E6)),IF((108=('V06 Calend 01'!C6+(6*'V06 Calend 01'!E6))),('V06 Calend 01'!H6-('V06 Calend 01'!I6*('V06 Calend 01'!E6-1))),'V06 Calend 01'!I6),0))+IF((108='V06 Calend 01'!D6),'V06 Calend 01'!J6,0)) -> 0 | DQ6: =((IF((109='V06 Calend 01'!C6),('V06 Calend 01'!F6+'V06 Calend 01'!G6),0)+IF(AND(('V06 Calend 01'!E6>0),(109>'V06 Calend 01'!C6),(109<'V06 Calend 01'!D6),(MOD((109-'V06 Calend 01'!C6),6)=0),(((109-'V06 Calend 01'!C6)/6)<='V06 Calend 01'!E6)),IF((109=('V06 Calend 01'!C6+(6*'V06 Calend 01'!E6))),('V06 Calend 01'!H6-('V06 Calend 01'!I6*('V06 Calend 01'!E6-1))),'V06 Calend 01'!I6),0))+IF((109='V06 Calend 01'!D6),'V06 Calend 01'!J6,0)) -> 0 | DR6: =((IF((110='V06 Calend 01'!C6),('V06 Calend 01'!F6+'V06 Calend 01'!G6),0)+IF(AND(('V06 Calend 01'!E6>0),(110>'V06 Calend 01'!C6),(110<'V06 Calend 01'!D6),(MOD((110-'V06 Calend 01'!C6),6)=0),(((110-'V06 Calend 01'!C6)/6)<='V06 Calend 01'!E6)),IF((110=('V06 Calend 01'!C6+(6*'V06 Calend 01'!E6))),('V06 Calend 01'!H6-('V06 Calend 01'!I6*('V06 Calend 01'!E6-1))),'V06 Calend 01'!I6),0))+IF((110='V06 Calend 01'!D6),'V06 Calend 01'!J6,0)) -> 0 | DS6: =((IF((111='V06 Calend 01'!C6),('V06 Calend 01'!F6+'V06 Calend 01'!G6),0)+IF(AND(('V06 Calend 01'!E6>0),(111>'V06 Calend 01'!C6),(111<'V06 Calend 01'!D6),(MOD((111-'V06 Calend 01'!C6),6)=0),(((111-'V06 Calend 01'!C6)/6)<='V06 Calend 01'!E6)),IF((111=('V06 Calend 01'!C6+(6*'V06 Calend 01'!E6))),('V06 Calend 01'!H6-('V06 Calend 01'!I6*('V06 Calend 01'!E6-1))),'V06 Calend 01'!I6),0))+IF((111='V06 Calend 01'!D6),'V06 Calend 01'!J6,0)) -> 0 | DT6: =((IF((112='V06 Calend 01'!C6),('V06 Calend 01'!F6+'V06 Calend 01'!G6),0)+IF(AND(('V06 Calend 01'!E6>0),(112>'V06 Calend 01'!C6),(112<'V06 Calend 01'!D6),(MOD((112-'V06 Calend 01'!C6),6)=0),(((112-'V06 Calend 01'!C6)/6)<='V06 Calend 01'!E6)),IF((112=('V06 Calend 01'!C6+(6*'V06 Calend 01'!E6))),('V06 Calend 01'!H6-('V06 Calend 01'!I6*('V06 Calend 01'!E6-1))),'V06 Calend 01'!I6),0))+IF((112='V06 Calend 01'!D6),'V06 Calend 01'!J6,0)) -> 0 | DU6: =((IF((113='V06 Calend 01'!C6),('V06 Calend 01'!F6+'V06 Calend 01'!G6),0)+IF(AND(('V06 Calend 01'!E6>0),(113>'V06 Calend 01'!C6),(113<'V06 Calend 01'!D6),(MOD((113-'V06 Calend 01'!C6),6)=0),(((113-'V06 Calend 01'!C6)/6)<='V06 Calend 01'!E6)),IF((113=('V06 Calend 01'!C6+(6*'V06 Calend 01'!E6))),('V06 Calend 01'!H6-('V06 Calend 01'!I6*('V06 Calend 01'!E6-1))),'V06 Calend 01'!I6),0))+IF((113='V06 Calend 01'!D6),'V06 Calend 01'!J6,0)) -> 0 | DV6: =((IF((114='V06 Calend 01'!C6),('V06 Calend 01'!F6+'V06 Calend 01'!G6),0)+IF(AND(('V06 Calend 01'!E6>0),(114>'V06 Calend 01'!C6),(114<'V06 Calend 01'!D6),(MOD((114-'V06 Calend 01'!C6),6)=0),(((114-'V06 Calend 01'!C6)/6)<='V06 Calend 01'!E6)),IF((114=('V06 Calend 01'!C6+(6*'V06 Calend 01'!E6))),('V06 Calend 01'!H6-('V06 Calend 01'!I6*('V06 Calend 01'!E6-1))),'V06 Calend 01'!I6),0))+IF((114='V06 Calend 01'!D6),'V06 Calend 01'!J6,0)) -> 0 | DW6: =((IF((115='V06 Calend 01'!C6),('V06 Calend 01'!F6+'V06 Calend 01'!G6),0)+IF(AND(('V06 Calend 01'!E6>0),(115>'V06 Calend 01'!C6),(115<'V06 Calend 01'!D6),(MOD((115-'V06 Calend 01'!C6),6)=0),(((115-'V06 Calend 01'!C6)/6)<='V06 Calend 01'!E6)),IF((115=('V06 Calend 01'!C6+(6*'V06 Calend 01'!E6))),('V06 Calend 01'!H6-('V06 Calend 01'!I6*('V06 Calend 01'!E6-1))),'V06 Calend 01'!I6),0))+IF((115='V06 Calend 01'!D6),'V06 Calend 01'!J6,0)) -> 0 | DX6: =((IF((116='V06 Calend 01'!C6),('V06 Calend 01'!F6+'V06 Calend 01'!G6),0)+IF(AND(('V06 Calend 01'!E6>0),(116>'V06 Calend 01'!C6),(116<'V06 Calend 01'!D6),(MOD((116-'V06 Calend 01'!C6),6)=0),(((116-'V06 Calend 01'!C6)/6)<='V06 Calend 01'!E6)),IF((116=('V06 Calend 01'!C6+(6*'V06 Calend 01'!E6))),('V06 Calend 01'!H6-('V06 Calend 01'!I6*('V06 Calend 01'!E6-1))),'V06 Calend 01'!I6),0))+IF((116='V06 Calend 01'!D6),'V06 Calend 01'!J6,0)) -> 0 | DY6: =((IF((117='V06 Calend 01'!C6),('V06 Calend 01'!F6+'V06 Calend 01'!G6),0)+IF(AND(('V06 Calend 01'!E6>0),(117>'V06 Calend 01'!C6),(117<'V06 Calend 01'!D6),(MOD((117-'V06 Calend 01'!C6),6)=0),(((117-'V06 Calend 01'!C6)/6)<='V06 Calend 01'!E6)),IF((117=('V06 Calend 01'!C6+(6*'V06 Calend 01'!E6))),('V06 Calend 01'!H6-('V06 Calend 01'!I6*('V06 Calend 01'!E6-1))),'V06 Calend 01'!I6),0))+IF((117='V06 Calend 01'!D6),'V06 Calend 01'!J6,0)) -> 0 | DZ6: =((IF((118='V06 Calend 01'!C6),('V06 Calend 01'!F6+'V06 Calend 01'!G6),0)+IF(AND(('V06 Calend 01'!E6>0),(118>'V06 Calend 01'!C6),(118<'V06 Calend 01'!D6),(MOD((118-'V06 Calend 01'!C6),6)=0),(((118-'V06 Calend 01'!C6)/6)<='V06 Calend 01'!E6)),IF((118=('V06 Calend 01'!C6+(6*'V06 Calend 01'!E6))),('V06 Calend 01'!H6-('V06 Calend 01'!I6*('V06 Calend 01'!E6-1))),'V06 Calend 01'!I6),0))+IF((118='V06 Calend 01'!D6),'V06 Calend 01'!J6,0)) -> 0 | EA6: =((IF((119='V06 Calend 01'!C6),('V06 Calend 01'!F6+'V06 Calend 01'!G6),0)+IF(AND(('V06 Calend 01'!E6>0),(119>'V06 Calend 01'!C6),(119<'V06 Calend 01'!D6),(MOD((119-'V06 Calend 01'!C6),6)=0),(((119-'V06 Calend 01'!C6)/6)<='V06 Calend 01'!E6)),IF((119=('V06 Calend 01'!C6+(6*'V06 Calend 01'!E6))),('V06 Calend 01'!H6-('V06 Calend 01'!I6*('V06 Calend 01'!E6-1))),'V06 Calend 01'!I6),0))+IF((119='V06 Calend 01'!D6),'V06 Calend 01'!J6,0)) -> 0 | EB6: =((IF((120='V06 Calend 01'!C6),('V06 Calend 01'!F6+'V06 Calend 01'!G6),0)+IF(AND(('V06 Calend 01'!E6>0),(120>'V06 Calend 01'!C6),(120<'V06 Calend 01'!D6),(MOD((120-'V06 Calend 01'!C6),6)=0),(((120-'V06 Calend 01'!C6)/6)<='V06 Calend 01'!E6)),IF((120=('V06 Calend 01'!C6+(6*'V06 Calend 01'!E6))),('V06 Calend 01'!H6-('V06 Calend 01'!I6*('V06 Calend 01'!E6-1))),'V06 Calend 01'!I6),0))+IF((120='V06 Calend 01'!D6),'V06 Calend 01'!J6,0)) -> 0 | EC6: =((IF((121='V06 Calend 01'!C6),('V06 Calend 01'!F6+'V06 Calend 01'!G6),0)+IF(AND(('V06 Calend 01'!E6>0),(121>'V06 Calend 01'!C6),(121<'V06 Calend 01'!D6),(MOD((121-'V06 Calend 01'!C6),6)=0),(((121-'V06 Calend 01'!C6)/6)<='V06 Calend 01'!E6)),IF((121=('V06 Calend 01'!C6+(6*'V06 Calend 01'!E6))),('V06 Calend 01'!H6-('V06 Calend 01'!I6*('V06 Calend 01'!E6-1))),'V06 Calend 01'!I6),0))+IF((121='V06 Calend 01'!D6),'V06 Calend 01'!J6,0)) -> 0 | ED6: =((IF((122='V06 Calend 01'!C6),('V06 Calend 01'!F6+'V06 Calend 01'!G6),0)+IF(AND(('V06 Calend 01'!E6>0),(122>'V06 Calend 01'!C6),(122<'V06 Calend 01'!D6),(MOD((122-'V06 Calend 01'!C6),6)=0),(((122-'V06 Calend 01'!C6)/6)<='V06 Calend 01'!E6)),IF((122=('V06 Calend 01'!C6+(6*'V06 Calend 01'!E6))),('V06 Calend 01'!H6-('V06 Calend 01'!I6*('V06 Calend 01'!E6-1))),'V06 Calend 01'!I6),0))+IF((122='V06 Calend 01'!D6),'V06 Calend 01'!J6,0)) -> 0 | EE6: =((IF((123='V06 Calend 01'!C6),('V06 Calend 01'!F6+'V06 Calend 01'!G6),0)+IF(AND(('V06 Calend 01'!E6>0),(123>'V06 Calend 01'!C6),(123<'V06 Calend 01'!D6),(MOD((123-'V06 Calend 01'!C6),6)=0),(((123-'V06 Calend 01'!C6)/6)<='V06 Calend 01'!E6)),IF((123=('V06 Calend 01'!C6+(6*'V06 Calend 01'!E6))),('V06 Calend 01'!H6-('V06 Calend 01'!I6*('V06 Calend 01'!E6-1))),'V06 Calend 01'!I6),0))+IF((123='V06 Calend 01'!D6),'V06 Calend 01'!J6,0)) -> 0 | EF6: =((IF((124='V06 Calend 01'!C6),('V06 Calend 01'!F6+'V06 Calend 01'!G6),0)+IF(AND(('V06 Calend 01'!E6>0),(124>'V06 Calend 01'!C6),(124<'V06 Calend 01'!D6),(MOD((124-'V06 Calend 01'!C6),6)=0),(((124-'V06 Calend 01'!C6)/6)<='V06 Calend 01'!E6)),IF((124=('V06 Calend 01'!C6+(6*'V06 Calend 01'!E6))),('V06 Calend 01'!H6-('V06 Calend 01'!I6*('V06 Calend 01'!E6-1))),'V06 Calend 01'!I6),0))+IF((124='V06 Calend 01'!D6),'V06 Calend 01'!J6,0)) -> 0 | EG6: =((IF((125='V06 Calend 01'!C6),('V06 Calend 01'!F6+'V06 Calend 01'!G6),0)+IF(AND(('V06 Calend 01'!E6>0),(125>'V06 Calend 01'!C6),(125<'V06 Calend 01'!D6),(MOD((125-'V06 Calend 01'!C6),6)=0),(((125-'V06 Calend 01'!C6)/6)<='V06 Calend 01'!E6)),IF((125=('V06 Calend 01'!C6+(6*'V06 Calend 01'!E6))),('V06 Calend 01'!H6-('V06 Calend 01'!I6*('V06 Calend 01'!E6-1))),'V06 Calend 01'!I6),0))+IF((125='V06 Calend 01'!D6),'V06 Calend 01'!J6,0)) -> 0 | EH6: =((IF((126='V06 Calend 01'!C6),('V06 Calend 01'!F6+'V06 Calend 01'!G6),0)+IF(AND(('V06 Calend 01'!E6>0),(126>'V06 Calend 01'!C6),(126<'V06 Calend 01'!D6),(MOD((126-'V06 Calend 01'!C6),6)=0),(((126-'V06 Calend 01'!C6)/6)<='V06 Calend 01'!E6)),IF((126=('V06 Calend 01'!C6+(6*'V06 Calend 01'!E6))),('V06 Calend 01'!H6-('V06 Calend 01'!I6*('V06 Calend 01'!E6-1))),'V06 Calend 01'!I6),0))+IF((126='V06 Calend 01'!D6),'V06 Calend 01'!J6,0)) -> 0 | EI6: =((IF((127='V06 Calend 01'!C6),('V06 Calend 01'!F6+'V06 Calend 01'!G6),0)+IF(AND(('V06 Calend 01'!E6>0),(127>'V06 Calend 01'!C6),(127<'V06 Calend 01'!D6),(MOD((127-'V06 Calend 01'!C6),6)=0),(((127-'V06 Calend 01'!C6)/6)<='V06 Calend 01'!E6)),IF((127=('V06 Calend 01'!C6+(6*'V06 Calend 01'!E6))),('V06 Calend 01'!H6-('V06 Calend 01'!I6*('V06 Calend 01'!E6-1))),'V06 Calend 01'!I6),0))+IF((127='V06 Calend 01'!D6),'V06 Calend 01'!J6,0)) -> 0 | EJ6: =((IF((128='V06 Calend 01'!C6),('V06 Calend 01'!F6+'V06 Calend 01'!G6),0)+IF(AND(('V06 Calend 01'!E6>0),(128>'V06 Calend 01'!C6),(128<'V06 Calend 01'!D6),(MOD((128-'V06 Calend 01'!C6),6)=0),(((128-'V06 Calend 01'!C6)/6)<='V06 Calend 01'!E6)),IF((128=('V06 Calend 01'!C6+(6*'V06 Calend 01'!E6))),('V06 Calend 01'!H6-('V06 Calend 01'!I6*('V06 Calend 01'!E6-1))),'V06 Calend 01'!I6),0))+IF((128='V06 Calend 01'!D6),'V06 Calend 01'!J6,0)) -> 0 | EK6: =((IF((129='V06 Calend 01'!C6),('V06 Calend 01'!F6+'V06 Calend 01'!G6),0)+IF(AND(('V06 Calend 01'!E6>0),(129>'V06 Calend 01'!C6),(129<'V06 Calend 01'!D6),(MOD((129-'V06 Calend 01'!C6),6)=0),(((129-'V06 Calend 01'!C6)/6)<='V06 Calend 01'!E6)),IF((129=('V06 Calend 01'!C6+(6*'V06 Calend 01'!E6))),('V06 Calend 01'!H6-('V06 Calend 01'!I6*('V06 Calend 01'!E6-1))),'V06 Calend 01'!I6),0))+IF((129='V06 Calend 01'!D6),'V06 Calend 01'!J6,0)) -> 0 | EL6: =((IF((130='V06 Calend 01'!C6),('V06 Calend 01'!F6+'V06 Calend 01'!G6),0)+IF(AND(('V06 Calend 01'!E6>0),(130>'V06 Calend 01'!C6),(130<'V06 Calend 01'!D6),(MOD((130-'V06 Calend 01'!C6),6)=0),(((130-'V06 Calend 01'!C6)/6)<='V06 Calend 01'!E6)),IF((130=('V06 Calend 01'!C6+(6*'V06 Calend 01'!E6))),('V06 Calend 01'!H6-('V06 Calend 01'!I6*('V06 Calend 01'!E6-1))),'V06 Calend 01'!I6),0))+IF((130='V06 Calend 01'!D6),'V06 Calend 01'!J6,0)) -> 0 | EM6: =((IF((131='V06 Calend 01'!C6),('V06 Calend 01'!F6+'V06 Calend 01'!G6),0)+IF(AND(('V06 Calend 01'!E6>0),(131>'V06 Calend 01'!C6),(131<'V06 Calend 01'!D6),(MOD((131-'V06 Calend 01'!C6),6)=0),(((131-'V06 Calend 01'!C6)/6)<='V06 Calend 01'!E6)),IF((131=('V06 Calend 01'!C6+(6*'V06 Calend 01'!E6))),('V06 Calend 01'!H6-('V06 Calend 01'!I6*('V06 Calend 01'!E6-1))),'V06 Calend 01'!I6),0))+IF((131='V06 Calend 01'!D6),'V06 Calend 01'!J6,0)) -> 0 | EN6: =((IF((132='V06 Calend 01'!C6),('V06 Calend 01'!F6+'V06 Calend 01'!G6),0)+IF(AND(('V06 Calend 01'!E6>0),(132>'V06 Calend 01'!C6),(132<'V06 Calend 01'!D6),(MOD((132-'V06 Calend 01'!C6),6)=0),(((132-'V06 Calend 01'!C6)/6)<='V06 Calend 01'!E6)),IF((132=('V06 Calend 01'!C6+(6*'V06 Calend 01'!E6))),('V06 Calend 01'!H6-('V06 Calend 01'!I6*('V06 Calend 01'!E6-1))),'V06 Calend 01'!I6),0))+IF((132='V06 Calend 01'!D6),'V06 Calend 01'!J6,0)) -> 0 | EO6: =((IF((133='V06 Calend 01'!C6),('V06 Calend 01'!F6+'V06 Calend 01'!G6),0)+IF(AND(('V06 Calend 01'!E6>0),(133>'V06 Calend 01'!C6),(133<'V06 Calend 01'!D6),(MOD((133-'V06 Calend 01'!C6),6)=0),(((133-'V06 Calend 01'!C6)/6)<='V06 Calend 01'!E6)),IF((133=('V06 Calend 01'!C6+(6*'V06 Calend 01'!E6))),('V06 Calend 01'!H6-('V06 Calend 01'!I6*('V06 Calend 01'!E6-1))),'V06 Calend 01'!I6),0))+IF((133='V06 Calend 01'!D6),'V06 Calend 01'!J6,0)) -> 0 | EP6: =((IF((134='V06 Calend 01'!C6),('V06 Calend 01'!F6+'V06 Calend 01'!G6),0)+IF(AND(('V06 Calend 01'!E6>0),(134>'V06 Calend 01'!C6),(134<'V06 Calend 01'!D6),(MOD((134-'V06 Calend 01'!C6),6)=0),(((134-'V06 Calend 01'!C6)/6)<='V06 Calend 01'!E6)),IF((134=('V06 Calend 01'!C6+(6*'V06 Calend 01'!E6))),('V06 Calend 01'!H6-('V06 Calend 01'!I6*('V06 Calend 01'!E6-1))),'V06 Calend 01'!I6),0))+IF((134='V06 Calend 01'!D6),'V06 Calend 01'!J6,0)) -> 0 | EQ6: =((IF((135='V06 Calend 01'!C6),('V06 Calend 01'!F6+'V06 Calend 01'!G6),0)+IF(AND(('V06 Calend 01'!E6>0),(135>'V06 Calend 01'!C6),(135<'V06 Calend 01'!D6),(MOD((135-'V06 Calend 01'!C6),6)=0),(((135-'V06 Calend 01'!C6)/6)<='V06 Calend 01'!E6)),IF((135=('V06 Calend 01'!C6+(6*'V06 Calend 01'!E6))),('V06 Calend 01'!H6-('V06 Calend 01'!I6*('V06 Calend 01'!E6-1))),'V06 Calend 01'!I6),0))+IF((135='V06 Calend 01'!D6),'V06 Calend 01'!J6,0)) -> 0 | ER6: =((IF((136='V06 Calend 01'!C6),('V06 Calend 01'!F6+'V06 Calend 01'!G6),0)+IF(AND(('V06 Calend 01'!E6>0),(136>'V06 Calend 01'!C6),(136<'V06 Calend 01'!D6),(MOD((136-'V06 Calend 01'!C6),6)=0),(((136-'V06 Calend 01'!C6)/6)<='V06 Calend 01'!E6)),IF((136=('V06 Calend 01'!C6+(6*'V06 Calend 01'!E6))),('V06 Calend 01'!H6-('V06 Calend 01'!I6*('V06 Calend 01'!E6-1))),'V06 Calend 01'!I6),0))+IF((136='V06 Calend 01'!D6),'V06 Calend 01'!J6,0)) -> 0 | ES6: =((IF((137='V06 Calend 01'!C6),('V06 Calend 01'!F6+'V06 Calend 01'!G6),0)+IF(AND(('V06 Calend 01'!E6>0),(137>'V06 Calend 01'!C6),(137<'V06 Calend 01'!D6),(MOD((137-'V06 Calend 01'!C6),6)=0),(((137-'V06 Calend 01'!C6)/6)<='V06 Calend 01'!E6)),IF((137=('V06 Calend 01'!C6+(6*'V06 Calend 01'!E6))),('V06 Calend 01'!H6-('V06 Calend 01'!I6*('V06 Calend 01'!E6-1))),'V06 Calend 01'!I6),0))+IF((137='V06 Calend 01'!D6),'V06 Calend 01'!J6,0)) -> 0 | ET6: =((IF((138='V06 Calend 01'!C6),('V06 Calend 01'!F6+'V06 Calend 01'!G6),0)+IF(AND(('V06 Calend 01'!E6>0),(138>'V06 Calend 01'!C6),(138<'V06 Calend 01'!D6),(MOD((138-'V06 Calend 01'!C6),6)=0),(((138-'V06 Calend 01'!C6)/6)<='V06 Calend 01'!E6)),IF((138=('V06 Calend 01'!C6+(6*'V06 Calend 01'!E6))),('V06 Calend 01'!H6-('V06 Calend 01'!I6*('V06 Calend 01'!E6-1))),'V06 Calend 01'!I6),0))+IF((138='V06 Calend 01'!D6),'V06 Calend 01'!J6,0)) -> 0 | EU6: =((IF((139='V06 Calend 01'!C6),('V06 Calend 01'!F6+'V06 Calend 01'!G6),0)+IF(AND(('V06 Calend 01'!E6>0),(139>'V06 Calend 01'!C6),(139<'V06 Calend 01'!D6),(MOD((139-'V06 Calend 01'!C6),6)=0),(((139-'V06 Calend 01'!C6)/6)<='V06 Calend 01'!E6)),IF((139=('V06 Calend 01'!C6+(6*'V06 Calend 01'!E6))),('V06 Calend 01'!H6-('V06 Calend 01'!I6*('V06 Calend 01'!E6-1))),'V06 Calend 01'!I6),0))+IF((139='V06 Calend 01'!D6),'V06 Calend 01'!J6,0)) -> 0 | EV6: =((IF((140='V06 Calend 01'!C6),('V06 Calend 01'!F6+'V06 Calend 01'!G6),0)+IF(AND(('V06 Calend 01'!E6>0),(140>'V06 Calend 01'!C6),(140<'V06 Calend 01'!D6),(MOD((140-'V06 Calend 01'!C6),6)=0),(((140-'V06 Calend 01'!C6)/6)<='V06 Calend 01'!E6)),IF((140=('V06 Calend 01'!C6+(6*'V06 Calend 01'!E6))),('V06 Calend 01'!H6-('V06 Calend 01'!I6*('V06 Calend 01'!E6-1))),'V06 Calend 01'!I6),0))+IF((140='V06 Calend 01'!D6),'V06 Calend 01'!J6,0)) -> 0 | EW6: =((IF((141='V06 Calend 01'!C6),('V06 Calend 01'!F6+'V06 Calend 01'!G6),0)+IF(AND(('V06 Calend 01'!E6>0),(141>'V06 Calend 01'!C6),(141<'V06 Calend 01'!D6),(MOD((141-'V06 Calend 01'!C6),6)=0),(((141-'V06 Calend 01'!C6)/6)<='V06 Calend 01'!E6)),IF((141=('V06 Calend 01'!C6+(6*'V06 Calend 01'!E6))),('V06 Calend 01'!H6-('V06 Calend 01'!I6*('V06 Calend 01'!E6-1))),'V06 Calend 01'!I6),0))+IF((141='V06 Calend 01'!D6),'V06 Calend 01'!J6,0)) -> 0 | EX6: =((IF((142='V06 Calend 01'!C6),('V06 Calend 01'!F6+'V06 Calend 01'!G6),0)+IF(AND(('V06 Calend 01'!E6>0),(142>'V06 Calend 01'!C6),(142<'V06 Calend 01'!D6),(MOD((142-'V06 Calend 01'!C6),6)=0),(((142-'V06 Calend 01'!C6)/6)<='V06 Calend 01'!E6)),IF((142=('V06 Calend 01'!C6+(6*'V06 Calend 01'!E6))),('V06 Calend 01'!H6-('V06 Calend 01'!I6*('V06 Calend 01'!E6-1))),'V06 Calend 01'!I6),0))+IF((142='V06 Calend 01'!D6),'V06 Calend 01'!J6,0)) -> 0 | EY6: =((IF((143='V06 Calend 01'!C6),('V06 Calend 01'!F6+'V06 Calend 01'!G6),0)+IF(AND(('V06 Calend 01'!E6>0),(143>'V06 Calend 01'!C6),(143<'V06 Calend 01'!D6),(MOD((143-'V06 Calend 01'!C6),6)=0),(((143-'V06 Calend 01'!C6)/6)<='V06 Calend 01'!E6)),IF((143=('V06 Calend 01'!C6+(6*'V06 Calend 01'!E6))),('V06 Calend 01'!H6-('V06 Calend 01'!I6*('V06 Calend 01'!E6-1))),'V06 Calend 01'!I6),0))+IF((143='V06 Calend 01'!D6),'V06 Calend 01'!J6,0)) -> 0 | EZ6: =((IF((144='V06 Calend 01'!C6),('V06 Calend 01'!F6+'V06 Calend 01'!G6),0)+IF(AND(('V06 Calend 01'!E6>0),(144>'V06 Calend 01'!C6),(144<'V06 Calend 01'!D6),(MOD((144-'V06 Calend 01'!C6),6)=0),(((144-'V06 Calend 01'!C6)/6)<='V06 Calend 01'!E6)),IF((144=('V06 Calend 01'!C6+(6*'V06 Calend 01'!E6))),('V06 Calend 01'!H6-('V06 Calend 01'!I6*('V06 Calend 01'!E6-1))),'V06 Calend 01'!I6),0))+IF((144='V06 Calend 01'!D6),'V06 Calend 01'!J6,0)) -> 0 | FA6: =((IF((145='V06 Calend 01'!C6),('V06 Calend 01'!F6+'V06 Calend 01'!G6),0)+IF(AND(('V06 Calend 01'!E6>0),(145>'V06 Calend 01'!C6),(145<'V06 Calend 01'!D6),(MOD((145-'V06 Calend 01'!C6),6)=0),(((145-'V06 Calend 01'!C6)/6)<='V06 Calend 01'!E6)),IF((145=('V06 Calend 01'!C6+(6*'V06 Calend 01'!E6))),('V06 Calend 01'!H6-('V06 Calend 01'!I6*('V06 Calend 01'!E6-1))),'V06 Calend 01'!I6),0))+IF((145='V06 Calend 01'!D6),'V06 Calend 01'!J6,0)) -> 0 | FB6: =((IF((146='V06 Calend 01'!C6),('V06 Calend 01'!F6+'V06 Calend 01'!G6),0)+IF(AND(('V06 Calend 01'!E6>0),(146>'V06 Calend 01'!C6),(146<'V06 Calend 01'!D6),(MOD((146-'V06 Calend 01'!C6),6)=0),(((146-'V06 Calend 01'!C6)/6)<='V06 Calend 01'!E6)),IF((146=('V06 Calend 01'!C6+(6*'V06 Calend 01'!E6))),('V06 Calend 01'!H6-('V06 Calend 01'!I6*('V06 Calend 01'!E6-1))),'V06 Calend 01'!I6),0))+IF((146='V06 Calend 01'!D6),'V06 Calend 01'!J6,0)) -> 0 | FC6: =((IF((147='V06 Calend 01'!C6),('V06 Calend 01'!F6+'V06 Calend 01'!G6),0)+IF(AND(('V06 Calend 01'!E6>0),(147>'V06 Calend 01'!C6),(147<'V06 Calend 01'!D6),(MOD((147-'V06 Calend 01'!C6),6)=0),(((147-'V06 Calend 01'!C6)/6)<='V06 Calend 01'!E6)),IF((147=('V06 Calend 01'!C6+(6*'V06 Calend 01'!E6))),('V06 Calend 01'!H6-('V06 Calend 01'!I6*('V06 Calend 01'!E6-1))),'V06 Calend 01'!I6),0))+IF((147='V06 Calend 01'!D6),'V06 Calend 01'!J6,0)) -> 0 | FD6: =((IF((148='V06 Calend 01'!C6),('V06 Calend 01'!F6+'V06 Calend 01'!G6),0)+IF(AND(('V06 Calend 01'!E6>0),(148>'V06 Calend 01'!C6),(148<'V06 Calend 01'!D6),(MOD((148-'V06 Calend 01'!C6),6)=0),(((148-'V06 Calend 01'!C6)/6)<='V06 Calend 01'!E6)),IF((148=('V06 Calend 01'!C6+(6*'V06 Calend 01'!E6))),('V06 Calend 01'!H6-('V06 Calend 01'!I6*('V06 Calend 01'!E6-1))),'V06 Calend 01'!I6),0))+IF((148='V06 Calend 01'!D6),'V06 Calend 01'!J6,0)) -> 0 | FE6: =((IF((149='V06 Calend 01'!C6),('V06 Calend 01'!F6+'V06 Calend 01'!G6),0)+IF(AND(('V06 Calend 01'!E6>0),(149>'V06 Calend 01'!C6),(149<'V06 Calend 01'!D6),(MOD((149-'V06 Calend 01'!C6),6)=0),(((149-'V06 Calend 01'!C6)/6)<='V06 Calend 01'!E6)),IF((149=('V06 Calend 01'!C6+(6*'V06 Calend 01'!E6))),('V06 Calend 01'!H6-('V06 Calend 01'!I6*('V06 Calend 01'!E6-1))),'V06 Calend 01'!I6),0))+IF((149='V06 Calend 01'!D6),'V06 Calend 01'!J6,0)) -> 0 | FF6: =((IF((150='V06 Calend 01'!C6),('V06 Calend 01'!F6+'V06 Calend 01'!G6),0)+IF(AND(('V06 Calend 01'!E6>0),(150>'V06 Calend 01'!C6),(150<'V06 Calend 01'!D6),(MOD((150-'V06 Calend 01'!C6),6)=0),(((150-'V06 Calend 01'!C6)/6)<='V06 Calend 01'!E6)),IF((150=('V06 Calend 01'!C6+(6*'V06 Calend 01'!E6))),('V06 Calend 01'!H6-('V06 Calend 01'!I6*('V06 Calend 01'!E6-1))),'V06 Calend 01'!I6),0))+IF((150='V06 Calend 01'!D6),'V06 Calend 01'!J6,0)) -> 0 | FG6: =((IF((151='V06 Calend 01'!C6),('V06 Calend 01'!F6+'V06 Calend 01'!G6),0)+IF(AND(('V06 Calend 01'!E6>0),(151>'V06 Calend 01'!C6),(151<'V06 Calend 01'!D6),(MOD((151-'V06 Calend 01'!C6),6)=0),(((151-'V06 Calend 01'!C6)/6)<='V06 Calend 01'!E6)),IF((151=('V06 Calend 01'!C6+(6*'V06 Calend 01'!E6))),('V06 Calend 01'!H6-('V06 Calend 01'!I6*('V06 Calend 01'!E6-1))),'V06 Calend 01'!I6),0))+IF((151='V06 Calend 01'!D6),'V06 Calend 01'!J6,0)) -> 0 | FH6: =((IF((152='V06 Calend 01'!C6),('V06 Calend 01'!F6+'V06 Calend 01'!G6),0)+IF(AND(('V06 Calend 01'!E6>0),(152>'V06 Calend 01'!C6),(152<'V06 Calend 01'!D6),(MOD((152-'V06 Calend 01'!C6),6)=0),(((152-'V06 Calend 01'!C6)/6)<='V06 Calend 01'!E6)),IF((152=('V06 Calend 01'!C6+(6*'V06 Calend 01'!E6))),('V06 Calend 01'!H6-('V06 Calend 01'!I6*('V06 Calend 01'!E6-1))),'V06 Calend 01'!I6),0))+IF((152='V06 Calend 01'!D6),'V06 Calend 01'!J6,0)) -> 0 | FI6: =((IF((153='V06 Calend 01'!C6),('V06 Calend 01'!F6+'V06 Calend 01'!G6),0)+IF(AND(('V06 Calend 01'!E6>0),(153>'V06 Calend 01'!C6),(153<'V06 Calend 01'!D6),(MOD((153-'V06 Calend 01'!C6),6)=0),(((153-'V06 Calend 01'!C6)/6)<='V06 Calend 01'!E6)),IF((153=('V06 Calend 01'!C6+(6*'V06 Calend 01'!E6))),('V06 Calend 01'!H6-('V06 Calend 01'!I6*('V06 Calend 01'!E6-1))),'V06 Calend 01'!I6),0))+IF((153='V06 Calend 01'!D6),'V06 Calend 01'!J6,0)) -> 0 | FJ6: =((IF((154='V06 Calend 01'!C6),('V06 Calend 01'!F6+'V06 Calend 01'!G6),0)+IF(AND(('V06 Calend 01'!E6>0),(154>'V06 Calend 01'!C6),(154<'V06 Calend 01'!D6),(MOD((154-'V06 Calend 01'!C6),6)=0),(((154-'V06 Calend 01'!C6)/6)<='V06 Calend 01'!E6)),IF((154=('V06 Calend 01'!C6+(6*'V06 Calend 01'!E6))),('V06 Calend 01'!H6-('V06 Calend 01'!I6*('V06 Calend 01'!E6-1))),'V06 Calend 01'!I6),0))+IF((154='V06 Calend 01'!D6),'V06 Calend 01'!J6,0)) -> 0 | FK6: =((IF((155='V06 Calend 01'!C6),('V06 Calend 01'!F6+'V06 Calend 01'!G6),0)+IF(AND(('V06 Calend 01'!E6>0),(155>'V06 Calend 01'!C6),(155<'V06 Calend 01'!D6),(MOD((155-'V06 Calend 01'!C6),6)=0),(((155-'V06 Calend 01'!C6)/6)<='V06 Calend 01'!E6)),IF((155=('V06 Calend 01'!C6+(6*'V06 Calend 01'!E6))),('V06 Calend 01'!H6-('V06 Calend 01'!I6*('V06 Calend 01'!E6-1))),'V06 Calend 01'!I6),0))+IF((155='V06 Calend 01'!D6),'V06 Calend 01'!J6,0)) -> 0 | FL6: =((IF((156='V06 Calend 01'!C6),('V06 Calend 01'!F6+'V06 Calend 01'!G6),0)+IF(AND(('V06 Calend 01'!E6>0),(156>'V06 Calend 01'!C6),(156<'V06 Calend 01'!D6),(MOD((156-'V06 Calend 01'!C6),6)=0),(((156-'V06 Calend 01'!C6)/6)<='V06 Calend 01'!E6)),IF((156=('V06 Calend 01'!C6+(6*'V06 Calend 01'!E6))),('V06 Calend 01'!H6-('V06 Calend 01'!I6*('V06 Calend 01'!E6-1))),'V06 Calend 01'!I6),0))+IF((156='V06 Calend 01'!D6),'V06 Calend 01'!J6,0)) -> 0 | FM6: =((IF((157='V06 Calend 01'!C6),('V06 Calend 01'!F6+'V06 Calend 01'!G6),0)+IF(AND(('V06 Calend 01'!E6>0),(157>'V06 Calend 01'!C6),(157<'V06 Calend 01'!D6),(MOD((157-'V06 Calend 01'!C6),6)=0),(((157-'V06 Calend 01'!C6)/6)<='V06 Calend 01'!E6)),IF((157=('V06 Calend 01'!C6+(6*'V06 Calend 01'!E6))),('V06 Calend 01'!H6-('V06 Calend 01'!I6*('V06 Calend 01'!E6-1))),'V06 Calend 01'!I6),0))+IF((157='V06 Calend 01'!D6),'V06 Calend 01'!J6,0)) -> 0 | FN6: =((IF((158='V06 Calend 01'!C6),('V06 Calend 01'!F6+'V06 Calend 01'!G6),0)+IF(AND(('V06 Calend 01'!E6>0),(158>'V06 Calend 01'!C6),(158<'V06 Calend 01'!D6),(MOD((158-'V06 Calend 01'!C6),6)=0),(((158-'V06 Calend 01'!C6)/6)<='V06 Calend 01'!E6)),IF((158=('V06 Calend 01'!C6+(6*'V06 Calend 01'!E6))),('V06 Calend 01'!H6-('V06 Calend 01'!I6*('V06 Calend 01'!E6-1))),'V06 Calend 01'!I6),0))+IF((158='V06 Calend 01'!D6),'V06 Calend 01'!J6,0)) -> 0 | FO6: =((IF((159='V06 Calend 01'!C6),('V06 Calend 01'!F6+'V06 Calend 01'!G6),0)+IF(AND(('V06 Calend 01'!E6>0),(159>'V06 Calend 01'!C6),(159<'V06 Calend 01'!D6),(MOD((159-'V06 Calend 01'!C6),6)=0),(((159-'V06 Calend 01'!C6)/6)<='V06 Calend 01'!E6)),IF((159=('V06 Calend 01'!C6+(6*'V06 Calend 01'!E6))),('V06 Calend 01'!H6-('V06 Calend 01'!I6*('V06 Calend 01'!E6-1))),'V06 Calend 01'!I6),0))+IF((159='V06 Calend 01'!D6),'V06 Calend 01'!J6,0)) -> 0 | FP6: =((IF((160='V06 Calend 01'!C6),('V06 Calend 01'!F6+'V06 Calend 01'!G6),0)+IF(AND(('V06 Calend 01'!E6>0),(160>'V06 Calend 01'!C6),(160<'V06 Calend 01'!D6),(MOD((160-'V06 Calend 01'!C6),6)=0),(((160-'V06 Calend 01'!C6)/6)<='V06 Calend 01'!E6)),IF((160=('V06 Calend 01'!C6+(6*'V06 Calend 01'!E6))),('V06 Calend 01'!H6-('V06 Calend 01'!I6*('V06 Calend 01'!E6-1))),'V06 Calend 01'!I6),0))+IF((160='V06 Calend 01'!D6),'V06 Calend 01'!J6,0)) -> 0 | FQ6: =((IF((161='V06 Calend 01'!C6),('V06 Calend 01'!F6+'V06 Calend 01'!G6),0)+IF(AND(('V06 Calend 01'!E6>0),(161>'V06 Calend 01'!C6),(161<'V06 Calend 01'!D6),(MOD((161-'V06 Calend 01'!C6),6)=0),(((161-'V06 Calend 01'!C6)/6)<='V06 Calend 01'!E6)),IF((161=('V06 Calend 01'!C6+(6*'V06 Calend 01'!E6))),('V06 Calend 01'!H6-('V06 Calend 01'!I6*('V06 Calend 01'!E6-1))),'V06 Calend 01'!I6),0))+IF((161='V06 Calend 01'!D6),'V06 Calend 01'!J6,0)) -> 0 | FR6: =((IF((162='V06 Calend 01'!C6),('V06 Calend 01'!F6+'V06 Calend 01'!G6),0)+IF(AND(('V06 Calend 01'!E6>0),(162>'V06 Calend 01'!C6),(162<'V06 Calend 01'!D6),(MOD((162-'V06 Calend 01'!C6),6)=0),(((162-'V06 Calend 01'!C6)/6)<='V06 Calend 01'!E6)),IF((162=('V06 Calend 01'!C6+(6*'V06 Calend 01'!E6))),('V06 Calend 01'!H6-('V06 Calend 01'!I6*('V06 Calend 01'!E6-1))),'V06 Calend 01'!I6),0))+IF((162='V06 Calend 01'!D6),'V06 Calend 01'!J6,0)) -> 0 | FS6: =((IF((163='V06 Calend 01'!C6),('V06 Calend 01'!F6+'V06 Calend 01'!G6),0)+IF(AND(('V06 Calend 01'!E6>0),(163>'V06 Calend 01'!C6),(163<'V06 Calend 01'!D6),(MOD((163-'V06 Calend 01'!C6),6)=0),(((163-'V06 Calend 01'!C6)/6)<='V06 Calend 01'!E6)),IF((163=('V06 Calend 01'!C6+(6*'V06 Calend 01'!E6))),('V06 Calend 01'!H6-('V06 Calend 01'!I6*('V06 Calend 01'!E6-1))),'V06 Calend 01'!I6),0))+IF((163='V06 Calend 01'!D6),'V06 Calend 01'!J6,0)) -> 0 | FT6: =((IF((164='V06 Calend 01'!C6),('V06 Calend 01'!F6+'V06 Calend 01'!G6),0)+IF(AND(('V06 Calend 01'!E6>0),(164>'V06 Calend 01'!C6),(164<'V06 Calend 01'!D6),(MOD((164-'V06 Calend 01'!C6),6)=0),(((164-'V06 Calend 01'!C6)/6)<='V06 Calend 01'!E6)),IF((164=('V06 Calend 01'!C6+(6*'V06 Calend 01'!E6))),('V06 Calend 01'!H6-('V06 Calend 01'!I6*('V06 Calend 01'!E6-1))),'V06 Calend 01'!I6),0))+IF((164='V06 Calend 01'!D6),'V06 Calend 01'!J6,0)) -> 0 | FU6: =((IF((165='V06 Calend 01'!C6),('V06 Calend 01'!F6+'V06 Calend 01'!G6),0)+IF(AND(('V06 Calend 01'!E6>0),(165>'V06 Calend 01'!C6),(165<'V06 Calend 01'!D6),(MOD((165-'V06 Calend 01'!C6),6)=0),(((165-'V06 Calend 01'!C6)/6)<='V06 Calend 01'!E6)),IF((165=('V06 Calend 01'!C6+(6*'V06 Calend 01'!E6))),('V06 Calend 01'!H6-('V06 Calend 01'!I6*('V06 Calend 01'!E6-1))),'V06 Calend 01'!I6),0))+IF((165='V06 Calend 01'!D6),'V06 Calend 01'!J6,0)) -> 0 | FV6: =((IF((166='V06 Calend 01'!C6),('V06 Calend 01'!F6+'V06 Calend 01'!G6),0)+IF(AND(('V06 Calend 01'!E6>0),(166>'V06 Calend 01'!C6),(166<'V06 Calend 01'!D6),(MOD((166-'V06 Calend 01'!C6),6)=0),(((166-'V06 Calend 01'!C6)/6)<='V06 Calend 01'!E6)),IF((166=('V06 Calend 01'!C6+(6*'V06 Calend 01'!E6))),('V06 Calend 01'!H6-('V06 Calend 01'!I6*('V06 Calend 01'!E6-1))),'V06 Calend 01'!I6),0))+IF((166='V06 Calend 01'!D6),'V06 Calend 01'!J6,0)) -> 0 | FW6: =((IF((167='V06 Calend 01'!C6),('V06 Calend 01'!F6+'V06 Calend 01'!G6),0)+IF(AND(('V06 Calend 01'!E6>0),(167>'V06 Calend 01'!C6),(167<'V06 Calend 01'!D6),(MOD((167-'V06 Calend 01'!C6),6)=0),(((167-'V06 Calend 01'!C6)/6)<='V06 Calend 01'!E6)),IF((167=('V06 Calend 01'!C6+(6*'V06 Calend 01'!E6))),('V06 Calend 01'!H6-('V06 Calend 01'!I6*('V06 Calend 01'!E6-1))),'V06 Calend 01'!I6),0))+IF((167='V06 Calend 01'!D6),'V06 Calend 01'!J6,0)) -> 0 | FX6: =((IF((168='V06 Calend 01'!C6),('V06 Calend 01'!F6+'V06 Calend 01'!G6),0)+IF(AND(('V06 Calend 01'!E6>0),(168>'V06 Calend 01'!C6),(168<'V06 Calend 01'!D6),(MOD((168-'V06 Calend 01'!C6),6)=0),(((168-'V06 Calend 01'!C6)/6)<='V06 Calend 01'!E6)),IF((168=('V06 Calend 01'!C6+(6*'V06 Calend 01'!E6))),('V06 Calend 01'!H6-('V06 Calend 01'!I6*('V06 Calend 01'!E6-1))),'V06 Calend 01'!I6),0))+IF((168='V06 Calend 01'!D6),'V06 Calend 01'!J6,0)) -> 0 | FY6: =((IF((169='V06 Calend 01'!C6),('V06 Calend 01'!F6+'V06 Calend 01'!G6),0)+IF(AND(('V06 Calend 01'!E6>0),(169>'V06 Calend 01'!C6),(169<'V06 Calend 01'!D6),(MOD((169-'V06 Calend 01'!C6),6)=0),(((169-'V06 Calend 01'!C6)/6)<='V06 Calend 01'!E6)),IF((169=('V06 Calend 01'!C6+(6*'V06 Calend 01'!E6))),('V06 Calend 01'!H6-('V06 Calend 01'!I6*('V06 Calend 01'!E6-1))),'V06 Calend 01'!I6),0))+IF((169='V06 Calend 01'!D6),'V06 Calend 01'!J6,0)) -> 0 | FZ6: =((IF((170='V06 Calend 01'!C6),('V06 Calend 01'!F6+'V06 Calend 01'!G6),0)+IF(AND(('V06 Calend 01'!E6>0),(170>'V06 Calend 01'!C6),(170<'V06 Calend 01'!D6),(MOD((170-'V06 Calend 01'!C6),6)=0),(((170-'V06 Calend 01'!C6)/6)<='V06 Calend 01'!E6)),IF((170=('V06 Calend 01'!C6+(6*'V06 Calend 01'!E6))),('V06 Calend 01'!H6-('V06 Calend 01'!I6*('V06 Calend 01'!E6-1))),'V06 Calend 01'!I6),0))+IF((170='V06 Calend 01'!D6),'V06 Calend 01'!J6,0)) -> 0 | GA6: =((IF((171='V06 Calend 01'!C6),('V06 Calend 01'!F6+'V06 Calend 01'!G6),0)+IF(AND(('V06 Calend 01'!E6>0),(171>'V06 Calend 01'!C6),(171<'V06 Calend 01'!D6),(MOD((171-'V06 Calend 01'!C6),6)=0),(((171-'V06 Calend 01'!C6)/6)<='V06 Calend 01'!E6)),IF((171=('V06 Calend 01'!C6+(6*'V06 Calend 01'!E6))),('V06 Calend 01'!H6-('V06 Calend 01'!I6*('V06 Calend 01'!E6-1))),'V06 Calend 01'!I6),0))+IF((171='V06 Calend 01'!D6),'V06 Calend 01'!J6,0)) -> 0 | GB6: =((IF((172='V06 Calend 01'!C6),('V06 Calend 01'!F6+'V06 Calend 01'!G6),0)+IF(AND(('V06 Calend 01'!E6>0),(172>'V06 Calend 01'!C6),(172<'V06 Calend 01'!D6),(MOD((172-'V06 Calend 01'!C6),6)=0),(((172-'V06 Calend 01'!C6)/6)<='V06 Calend 01'!E6)),IF((172=('V06 Calend 01'!C6+(6*'V06 Calend 01'!E6))),('V06 Calend 01'!H6-('V06 Calend 01'!I6*('V06 Calend 01'!E6-1))),'V06 Calend 01'!I6),0))+IF((172='V06 Calend 01'!D6),'V06 Calend 01'!J6,0)) -> 0 | GC6: =((IF((173='V06 Calend 01'!C6),('V06 Calend 01'!F6+'V06 Calend 01'!G6),0)+IF(AND(('V06 Calend 01'!E6>0),(173>'V06 Calend 01'!C6),(173<'V06 Calend 01'!D6),(MOD((173-'V06 Calend 01'!C6),6)=0),(((173-'V06 Calend 01'!C6)/6)<='V06 Calend 01'!E6)),IF((173=('V06 Calend 01'!C6+(6*'V06 Calend 01'!E6))),('V06 Calend 01'!H6-('V06 Calend 01'!I6*('V06 Calend 01'!E6-1))),'V06 Calend 01'!I6),0))+IF((173='V06 Calend 01'!D6),'V06 Calend 01'!J6,0)) -> 0 | GD6: =((IF((174='V06 Calend 01'!C6),('V06 Calend 01'!F6+'V06 Calend 01'!G6),0)+IF(AND(('V06 Calend 01'!E6>0),(174>'V06 Calend 01'!C6),(174<'V06 Calend 01'!D6),(MOD((174-'V06 Calend 01'!C6),6)=0),(((174-'V06 Calend 01'!C6)/6)<='V06 Calend 01'!E6)),IF((174=('V06 Calend 01'!C6+(6*'V06 Calend 01'!E6))),('V06 Calend 01'!H6-('V06 Calend 01'!I6*('V06 Calend 01'!E6-1))),'V06 Calend 01'!I6),0))+IF((174='V06 Calend 01'!D6),'V06 Calend 01'!J6,0)) -> 0 | GE6: =((IF((175='V06 Calend 01'!C6),('V06 Calend 01'!F6+'V06 Calend 01'!G6),0)+IF(AND(('V06 Calend 01'!E6>0),(175>'V06 Calend 01'!C6),(175<'V06 Calend 01'!D6),(MOD((175-'V06 Calend 01'!C6),6)=0),(((175-'V06 Calend 01'!C6)/6)<='V06 Calend 01'!E6)),IF((175=('V06 Calend 01'!C6+(6*'V06 Calend 01'!E6))),('V06 Calend 01'!H6-('V06 Calend 01'!I6*('V06 Calend 01'!E6-1))),'V06 Calend 01'!I6),0))+IF((175='V06 Calend 01'!D6),'V06 Calend 01'!J6,0)) -> 0 | GF6: =((IF((176='V06 Calend 01'!C6),('V06 Calend 01'!F6+'V06 Calend 01'!G6),0)+IF(AND(('V06 Calend 01'!E6>0),(176>'V06 Calend 01'!C6),(176<'V06 Calend 01'!D6),(MOD((176-'V06 Calend 01'!C6),6)=0),(((176-'V06 Calend 01'!C6)/6)<='V06 Calend 01'!E6)),IF((176=('V06 Calend 01'!C6+(6*'V06 Calend 01'!E6))),('V06 Calend 01'!H6-('V06 Calend 01'!I6*('V06 Calend 01'!E6-1))),'V06 Calend 01'!I6),0))+IF((176='V06 Calend 01'!D6),'V06 Calend 01'!J6,0)) -> 0 | GG6: =((IF((177='V06 Calend 01'!C6),('V06 Calend 01'!F6+'V06 Calend 01'!G6),0)+IF(AND(('V06 Calend 01'!E6>0),(177>'V06 Calend 01'!C6),(177<'V06 Calend 01'!D6),(MOD((177-'V06 Calend 01'!C6),6)=0),(((177-'V06 Calend 01'!C6)/6)<='V06 Calend 01'!E6)),IF((177=('V06 Calend 01'!C6+(6*'V06 Calend 01'!E6))),('V06 Calend 01'!H6-('V06 Calend 01'!I6*('V06 Calend 01'!E6-1))),'V06 Calend 01'!I6),0))+IF((177='V06 Calend 01'!D6),'V06 Calend 01'!J6,0)) -> 0 | GH6: =((IF((178='V06 Calend 01'!C6),('V06 Calend 01'!F6+'V06 Calend 01'!G6),0)+IF(AND(('V06 Calend 01'!E6>0),(178>'V06 Calend 01'!C6),(178<'V06 Calend 01'!D6),(MOD((178-'V06 Calend 01'!C6),6)=0),(((178-'V06 Calend 01'!C6)/6)<='V06 Calend 01'!E6)),IF((178=('V06 Calend 01'!C6+(6*'V06 Calend 01'!E6))),('V06 Calend 01'!H6-('V06 Calend 01'!I6*('V06 Calend 01'!E6-1))),'V06 Calend 01'!I6),0))+IF((178='V06 Calend 01'!D6),'V06 Calend 01'!J6,0)) -> 0 | GI6: =((IF((179='V06 Calend 01'!C6),('V06 Calend 01'!F6+'V06 Calend 01'!G6),0)+IF(AND(('V06 Calend 01'!E6>0),(179>'V06 Calend 01'!C6),(179<'V06 Calend 01'!D6),(MOD((179-'V06 Calend 01'!C6),6)=0),(((179-'V06 Calend 01'!C6)/6)<='V06 Calend 01'!E6)),IF((179=('V06 Calend 01'!C6+(6*'V06 Calend 01'!E6))),('V06 Calend 01'!H6-('V06 Calend 01'!I6*('V06 Calend 01'!E6-1))),'V06 Calend 01'!I6),0))+IF((179='V06 Calend 01'!D6),'V06 Calend 01'!J6,0)) -> 0 | GJ6: =((IF((180='V06 Calend 01'!C6),('V06 Calend 01'!F6+'V06 Calend 01'!G6),0)+IF(AND(('V06 Calend 01'!E6>0),(180>'V06 Calend 01'!C6),(180<'V06 Calend 01'!D6),(MOD((180-'V06 Calend 01'!C6),6)=0),(((180-'V06 Calend 01'!C6)/6)<='V06 Calend 01'!E6)),IF((180=('V06 Calend 01'!C6+(6*'V06 Calend 01'!E6))),('V06 Calend 01'!H6-('V06 Calend 01'!I6*('V06 Calend 01'!E6-1))),'V06 Calend 01'!I6),0))+IF((180='V06 Calend 01'!D6),'V06 Calend 01'!J6,0)) -> 0
